Workbook

Sheet Boletim_do_Veiculo_2026-09-08_2
A1: PLACA | B1: PREFIXO | C1: UO | D1: MOTORISTAS | E1: DIA | F1: DISTÂNCIA PERCORRIDA | G1: TEMPO IGNIÇÃO LIGADA | H1: TEMPO EM VIGENCIA | I1: EXCESSO DE VELOCIDADE | J1: ACELERAÇÃO BRUSCA | K1: FRENAGEM BRUSCA | L1: FRENAGEM BRUSCA SEM ACIONAMENTO DO PEDAL | M1: FRENAGEM BRUSCA COM ACIONAMENTO DO PEDAL | N1: CURVA BRUSCA | O1: BANGUELA | P1: PARADO LIGADO | Q1: CONSUMO DE COMBUSTIVEL | R1: MÉDIA CONSUMO | S1: RPM MARCHA LENTA | T1: RPM ABAIXO DA VERDE | U1: RPM VERDE (ECONÔMICO) | V1: RPM VERDE (POTÊNCIA) | W1: RPM AMARELO | X1: RPM VERMELHO | Y1: EXCESSO DE RPM | Z1: PEDAL ACIONADO FAIXA 1 | AA1: PEDAL ACIONADO FAIXA 2 | AB1: PEDAL ACIONADO FAIXA 3 | AC1: LOGRADOURO INICIAL | AD1: LOGRADOURO FINAL | AE1: HODOMETRO INICIAL | AF1: HODOMETRO FINAL | AG1: TEMPO EM MOVIMENTO | AH1: TEMPO PARADO | AI1: TEMPO COM GPS INVALIDO | AJ1: TEMPO EQUIP DESLIGADO | AK1: TEMPO BATENDO TRANSMISSÃO | AL1: TEMPO FREIO MOTOR | AM1: CHECKLIST | AN1: SEM CINTO | AO1: BOCEJO | AP1: SEM MOTORISTA | AQ1: USO DE CIGARRO | AR1: DISTRAÇÃO | AS1: FADIGA | AT1: USO DE CELULAR | AU1: DISTÂNCIA PERIGOSA | AV1: CÂMERA OBSTRUÍDA | AW1: ULTRAPASSAGEM ILEGAL | AX1: SEM CONE | AY1: SEM ÓCULOS DE EPI | AZ1: SEM LUVAS | BA1: CARONA | BB1: DESCONEXÃO DA CÂMERA DE AUDITORIA | BC1: DESCONEXÃO DA CÂMERA DO MOTORISTA | BD1: DESCONEXÃO DA CÂMERA DA PISTA | BE1: USO INDEVIDO DE VEÍCULO | BF1: TEMPO USO INDEVIDO DE VEÍCULO | BG1: MANUSEIO DE OBJETO | BH1: PARADA INCOMPLETA | BI1: NÃO PAROU | BJ1: SEM CASQUETE | BK1: DESVIO DE ROTA | BM1: Distância (km) - todos os dias | BN1: Consumo (L) - dias com reporte | BO1: Média (Km/L) - dias com reporte | BP1: Distância (km) - dias com reporte | BQ1: Tracinho (1=sem reporte telemetria)
A2: JQC9385 | B2: R5115 | C2: ROTA TRANSPORTES - ITABUNA | D2: WILSON DE SOUSA LEAL - 70853592500, ALEGUIRINALDO DE SOUZA LEITE JUNIOR - 05053784507 | E2: 46273 | F2: 126.33 | G2: 0.29738426 | H2: 0.29380787 | I2: 0.00017361111 | J2: 1 | K2: 0 | L2: 0 | M2: 0 | N2: 0 | O2: 0 | P2: 0 | Q2: - | R2: - | S2: 0 | T2: 0 | U2: 0 | V2: 0 | W2: 0 | X2: 0 | Y2: 0 | Z2: 0 | AA2: 0 | AB2: 0 | AC2: Rua K | AD2: Avenida Amélia Amado | AE2: 91534.21 | AF2: 91660.54 | AG2: 0.26135417 | AH2: 0.14390046 | AI2: 0 | AJ2: 0 | AK2: 0 | AL2: 0 | AM2: N/A | AN2: 0 | AO2: 0 | AP2: 0 | AQ2: 0 | AR2: 0 | AS2: 0 | AT2: 0 | AU2: 9 | AV2: 0 | AW2: 0 | AX2: 0 | AY2: 0 | AZ2: 0 | BA2: 0 | BB2: 0 | BC2: 0 | BD2: 0 | BE2: 0 | BF2: 0 | BG2: 0 | BH2: 0 | BI2: 0 | BJ2: 0 | BK2: 0 | BM2: =IFERROR(VALUE(F2),"") -> 126.33 | BN2: =IF(R2="-","",IFERROR(VALUE(LEFT(Q2,LEN(Q2)-2)),"")) | BO2: =IF(R2="-","",IFERROR(VALUE(LEFT(R2,LEN(R2)-5)),"")) | BP2: =IF(R2="-","",IFERROR(VALUE(F2),"")) | BQ2: =IF(R2="-",1,0) -> 1
A3: JQC9385 | B3: R5115 | C3: ROTA TRANSPORTES - ITABUNA | D3: WILSON DE SOUSA LEAL - 70853592500, RAFAEL DE JESUS BARRETO - 85830111500 | E3: 46274 | F3: 106.06 | G3: 0.28118056 | H3: 0.27314815 | I3: 9.2592593e-05 | J3: 0 | K3: 1 | L3: 0 | M3: 0 | N3: 1 | O3: 0 | P3: 0 | Q3: - | R3: - | S3: 0 | T3: 0 | U3: 0 | V3: 0 | W3: 0 | X3: 0 | Y3: 0 | Z3: 0 | AA3: 0 | AB3: 0 | AC3: Rua Castro Alves | AD3: Avenida Amélia Amado | AE3: 91660.54 | AF3: 91766.60 | AG3: 0.22017361 | AH3: 0.14052083 | AI3: 0 | AJ3: 0 | AK3: 0 | AL3: 0 | AM3: N/A | AN3: 0 | AO3: 0 | AP3: 0 | AQ3: 0 | AR3: 0 | AS3: 0 | AT3: 0 | AU3: 2 | AV3: 0 | AW3: 0 | AX3: 0 | AY3: 0 | AZ3: 0 | BA3: 0 | BB3: 0 | BC3: 0 | BD3: 0 | BE3: 0 | BF3: 0 | BG3: 0 | BH3: 0 | BI3: 0 | BJ3: 0 | BK3: 0 | BM3: =IFERROR(VALUE(F3),"") -> 106.06 | BN3: =IF(R3="-","",IFERROR(VALUE(LEFT(Q3,LEN(Q3)-2)),"")) | BO3: =IF(R3="-","",IFERROR(VALUE(LEFT(R3,LEN(R3)-5)),"")) | BP3: =IF(R3="-","",IFERROR(VALUE(F3),"")) | BQ3: =IF(R3="-",1,0) -> 1
A4: JQC9385 | B4: R5115 | C4: ROTA TRANSPORTES - ITABUNA | D4: WILSON DE SOUSA LEAL - 70853592500 | E4: 46275 | F4: 104.03 | G4: 0.23736111 | H4: 0.22246528 | I4: 4.6296296e-05 | J4: 0 | K4: 0 | L4: 0 | M4: 0 | N4: 0 | O4: 0 | P4: 0 | Q4: - | R4: - | S4: 0 | T4: 0 | U4: 0 | V4: 0 | W4: 0 | X4: 0 | Y4: 0 | Z4: 0 | AA4: 0 | AB4: 0 | AC4: Rua K | AD4: Avenida Amélia Amado | AE4: 91766.60 | AF4: 91870.63 | AG4: 0.205 | AH4: 0.14122685 | AI4: 0 | AJ4: 0 | AK4: 0 | AL4: 0 | AM4: N/A | AN4: 0 | AO4: 0 | AP4: 0 | AQ4: 0 | AR4: 0 | AS4: 1 | AT4: 0 | AU4: 5 | AV4: 0 | AW4: 0 | AX4: 0 | AY4: 0 | AZ4: 0 | BA4: 0 | BB4: 0 | BC4: 0 | BD4: 0 | BE4: 0 | BF4: 0 | BG4: 0 | BH4: 0 | BI4: 0 | BJ4: 0 | BK4: 0 | BM4: =IFERROR(VALUE(F4),"") -> 104.03 | BN4: =IF(R4="-","",IFERROR(VALUE(LEFT(Q4,LEN(Q4)-2)),"")) | BO4: =IF(R4="-","",IFERROR(VALUE(LEFT(R4,LEN(R4)-5)),"")) | BP4: =IF(R4="-","",IFERROR(VALUE(F4),"")) | BQ4: =IF(R4="-",1,0) -> 1
A5: JQC9385 | B5: R5115 | C5: ROTA TRANSPORTES - ITABUNA | D5: WILSON DE SOUSA LEAL - 70853592500 | E5: 46276 | F5: 104.35 | G5: 0.27340278 | H5: 0.26832176 | I5: 9.2592593e-05 | J5: 1 | K5: 0 | L5: 0 | M5: 0 | N5: 0 | O5: 0 | P5: 0 | Q5: - | R5: - | S5: 0 | T5: 0 | U5: 0 | V5: 0 | W5: 0 | X5: 0 | Y5: 0 | Z5: 0 | AA5: 0 | AB5: 0 | AC5: Rua K | AD5: Avenida Amélia Amado | AE5: 91870.63 | AF5: 91974.98 | AG5: 0.21420139 | AH5: 0.11803241 | AI5: 0 | AJ5: 0 | AK5: 0 | AL5: 0 | AM5: N/A | AN5: 0 | AO5: 0 | AP5: 0 | AQ5: 0 | AR5: 0 | AS5: 0 | AT5: 0 | AU5: 7 | AV5: 0 | AW5: 0 | AX5: 0 | AY5: 0 | AZ5: 0 | BA5: 0 | BB5: 0 | BC5: 0 | BD5: 0 | BE5: 0 | BF5: 0 | BG5: 0 | BH5: 0 | BI5: 0 | BJ5: 0 | BK5: 0 | BM5: =IFERROR(VALUE(F5),"") -> 104.35 | BN5: =IF(R5="-","",IFERROR(VALUE(LEFT(Q5,LEN(Q5)-2)),"")) | BO5: =IF(R5="-","",IFERROR(VALUE(LEFT(R5,LEN(R5)-5)),"")) | BP5: =IF(R5="-","",IFERROR(VALUE(F5),"")) | BQ5: =IF(R5="-",1,0) -> 1
A6: JQC9385 | B6: R5115 | C6: ROTA TRANSPORTES - ITABUNA | D6: WILSON DE SOUSA LEAL - 70853592500, RENILDO FREITAS PEREIRA - 40936805587 | E6: 46277 | F6: 81.95 | G6: 0.22818287 | H6: 0.224375 | I6: 5.787037e-05 | J6: 0 | K6: 0 | L6: 0 | M6: 0 | N6: 1 | O6: 0 | P6: 0 | Q6: - | R6: - | S6: 0 | T6: 0 | U6: 0 | V6: 0 | W6: 0 | X6: 0 | Y6: 0 | Z6: 0 | AA6: 0 | AB6: 0 | AC6: Rua K | AD6: Avenida Amélia Amado | AE6: 91974.98 | AF6: 92056.93 | AG6: 0.18332176 | AH6: 0.095983796 | AI6: 0 | AJ6: 0 | AK6: 0 | AL6: 0 | AM6: N/A | AN6: 0 | AO6: 0 | AP6: 0 | AQ6: 0 | AR6: 0 | AS6: 0 | AT6: 0 | AU6: 2 | AV6: 0 | AW6: 0 | AX6: 0 | AY6: 0 | AZ6: 0 | BA6: 0 | BB6: 0 | BC6: 0 | BD6: 0 | BE6: 0 | BF6: 0 | BG6: 0 | BH6: 0 | BI6: 0 | BJ6: 0 | BK6: 0 | BM6: =IFERROR(VALUE(F6),"") -> 81.95 | BN6: =IF(R6="-","",IFERROR(VALUE(LEFT(Q6,LEN(Q6)-2)),"")) | BO6: =IF(R6="-","",IFERROR(VALUE(LEFT(R6,LEN(R6)-5)),"")) | BP6: =IF(R6="-","",IFERROR(VALUE(F6),"")) | BQ6: =IF(R6="-",1,0) -> 1
A7: JQC9385 | B7: R5115 | C7: ROTA TRANSPORTES - ITABUNA | D7: WILSON DE SOUSA LEAL - 70853592500 | E7: 46279 | F7: 105.31 | G7: 0.25493056 | H7: 0.25422454 | I7: 0.00017361111 | J7: 0 | K7: 0 | L7: 0 | M7: 0 | N7: 2 | O7: 0 | P7: 0 | Q7: - | R7: - | S7: 0 | T7: 0 | U7: 0 | V7: 0 | W7: 0 | X7: 0 | Y7: 0 | Z7: 0 | AA7: 0 | AB7: 0 | AC7: Avenida Amélia Amado | AD7: Avenida Amélia Amado | AE7: 92056.93 | AF7: 92162.23 | AG7: 0.21837963 | AH7: 0.092094907 | AI7: 0 | AJ7: 0 | AK7: 0 | AL7: 0 | AM7: N/A | AN7: 0 | AO7: 0 | AP7: 0 | AQ7: 0 | AR7: 0 | AS7: 1 | AT7: 0 | AU7: 9 | AV7: 0 | AW7: 0 | AX7: 0 | AY7: 0 | AZ7: 0 | BA7: 0 | BB7: 0 | BC7: 0 | BD7: 0 | BE7: 0 | BF7: 0 | BG7: 0 | BH7: 0 | BI7: 0 | BJ7: 0 | BK7: 0 | BM7: =IFERROR(VALUE(F7),"") -> 105.31 | BN7: =IF(R7="-","",IFERROR(VALUE(LEFT(Q7,LEN(Q7)-2)),"")) | BO7: =IF(R7="-","",IFERROR(VALUE(LEFT(R7,LEN(R7)-5)),"")) | BP7: =IF(R7="-","",IFERROR(VALUE(F7),"")) | BQ7: =IF(R7="-",1,0) -> 1
A8: JQC9404 | B8: R5125 | C8: ROTA TRANSPORTES - ITABUNA | E8: 46273 | F8: 0.00 | G8: 0.011018519 | H8: 0 | I8: 0 | J8: 0 | K8: 0 | L8: 0 | M8: 0 | N8: 0 | O8: 0 | P8: 0 | Q8: - | R8: - | S8: 0 | T8: 0 | U8: 0 | V8: 0 | W8: 0 | X8: 0 | Y8: 0 | Z8: 0 | AA8: 0 | AB8: 0 | AC8: Avenida Amélia Amado | AD8: Rua K | AE8: 91485.00 | AF8: 91485.00 | AG8: 0.00087962963 | AH8: 0.011122685 | AI8: 0 | AJ8: 0 | AK8: 0 | AL8: 0 | AM8: N/A | AN8: 0 | AO8: 0 | AP8: 0 | AQ8: 0 | AR8: 0 | AS8: 0 | AT8: 0 | AU8: 0 | AV8: 0 | AW8: 0 | AX8: 0 | AY8: 0 | AZ8: 0 | BA8: 0 | BB8: 0 | BC8: 0 | BD8: 0 | BE8: 0 | BF8: 0 | BG8: 0 | BH8: 0 | BI8: 0 | BJ8: 0 | BK8: 0 | BM8: =IFERROR(VALUE(F8),"") -> 0 | BN8: =IF(R8="-","",IFERROR(VALUE(LEFT(Q8,LEN(Q8)-2)),"")) | BO8: =IF(R8="-","",IFERROR(VALUE(LEFT(R8,LEN(R8)-5)),"")) | BP8: =IF(R8="-","",IFERROR(VALUE(F8),"")) | BQ8: =IF(R8="-",1,0) -> 1
A9: JQC9414 | B9: R5155 | C9: ROTA TRANSPORTES - ITABUNA | D9: ISRAEL SOARES DOS SANTOS - 09628284916, EDVALDO ELIAS SILVA - 99881624568 | E9: 46273 | F9: 128.72 | G9: 0.32350694 | H9: 0.24025463 | I9: 0.00016203704 | J9: 0 | K9: 0 | L9: 0 | M9: 0 | N9: 2 | O9: 0 | P9: 0 | Q9: - | R9: - | S9: 0 | T9: 0 | U9: 0 | V9: 0 | W9: 0 | X9: 0 | Y9: 0 | Z9: 0 | AA9: 0 | AB9: 0 | AC9: Avenida Amélia Amado | AD9: - | AE9: 726636.49 | AF9: 726765.21 | AG9: 0.27494213 | AH9: 0.12979167 | AI9: 0 | AJ9: 0 | AK9: 0 | AL9: 0 | AM9: N/A | AN9: 0 | AO9: 0 | AP9: 0 | AQ9: 0 | AR9: 0 | AS9: 0 | AT9: 0 | AU9: 0 | AV9: 0 | AW9: 0 | AX9: 0 | AY9: 0 | AZ9: 0 | BA9: 0 | BB9: 0 | BC9: 0 | BD9: 0 | BE9: 0 | BF9: 0 | BG9: 0 | BH9: 0 | BI9: 0 | BJ9: 0 | BK9: 0 | BM9: =IFERROR(VALUE(F9),"") -> 128.72 | BN9: =IF(R9="-","",IFERROR(VALUE(LEFT(Q9,LEN(Q9)-2)),"")) | BO9: =IF(R9="-","",IFERROR(VALUE(LEFT(R9,LEN(R9)-5)),"")) | BP9: =IF(R9="-","",IFERROR(VALUE(F9),"")) | BQ9: =IF(R9="-",1,0) -> 1
A10: JQC9414 | B10: R5155 | C10: ROTA TRANSPORTES - ITABUNA | D10: ISRAEL SOARES DOS SANTOS - 09628284916, EDVALDO ELIAS SILVA - 99881624568 | E10: 46274 | F10: 148.75 | G10: 0.37881944 | H10: 0.28887731 | I10: 0.00025462963 | J10: 0 | K10: 2 | L10: 0 | M10: 0 | N10: 1 | O10: 0 | P10: 0 | Q10: - | R10: - | S10: 0 | T10: 0 | U10: 0 | V10: 0 | W10: 0 | X10: 0 | Y10: 0 | Z10: 0 | AA10: 0 | AB10: 0 | AC10: - | AD10: Avenida Amélia Amado | AE10: 726765.50 | AF10: 726914.25 | AG10: 0.30527778 | AH10: 0.19894676 | AI10: 0 | AJ10: 0 | AK10: 0 | AL10: 0 | AM10: N/A | AN10: 0 | AO10: 0 | AP10: 0 | AQ10: 0 | AR10: 0 | AS10: 0 | AT10: 0 | AU10: 1 | AV10: 0 | AW10: 0 | AX10: 0 | AY10: 0 | AZ10: 0 | BA10: 0 | BB10: 0 | BC10: 0 | BD10: 0 | BE10: 0 | BF10: 0 | BG10: 0 | BH10: 0 | BI10: 0 | BJ10: 0 | BK10: 0 | BM10: =IFERROR(VALUE(F10),"") -> 148.75 | BN10: =IF(R10="-","",IFERROR(VALUE(LEFT(Q10,LEN(Q10)-2)),"")) | BO10: =IF(R10="-","",IFERROR(VALUE(LEFT(R10,LEN(R10)-5)),"")) | BP10: =IF(R10="-","",IFERROR(VALUE(F10),"")) | BQ10: =IF(R10="-",1,0) -> 1
A11: JQC9414 | B11: R5155 | C11: ROTA TRANSPORTES - ITABUNA | D11: ISRAEL SOARES DOS SANTOS - 09628284916, EDVALDO ELIAS SILVA - 99881624568, EMERSON ANDRADE DA SILVA - 96170824549 | E11: 46275 | F11: 127.59 | G11: 0.29146991 | H11: 0.23175926 | I11: 0.0013425926 | J11: 0 | K11: 0 | L11: 0 | M11: 0 | N11: 2 | O11: 0 | P11: 0 | Q11: - | R11: - | S11: 0 | T11: 0 | U11: 0 | V11: 0 | W11: 0 | X11: 0 | Y11: 0 | Z11: 0 | AA11: 0 | AB11: 0 | AC11: Avenida Amélia Amado | AD11: - | AE11: 726914.25 | AF11: 727041.84 | AG11: 0.26199074 | AH11: 0.13716435 | AI11: 0 | AJ11: 0 | AK11: 0 | AL11: 0 | AM11: N/A | AN11: 0 | AO11: 0 | AP11: 0 | AQ11: 0 | AR11: 0 | AS11: 0 | AT11: 0 | AU11: 2 | AV11: 0 | AW11: 0 | AX11: 0 | AY11: 0 | AZ11: 0 | BA11: 0 | BB11: 0 | BC11: 0 | BD11: 0 | BE11: 0 | BF11: 0 | BG11: 0 | BH11: 0 | BI11: 0 | BJ11: 0 | BK11: 0 | BM11: =IFERROR(VALUE(F11),"") -> 127.59 | BN11: =IF(R11="-","",IFERROR(VALUE(LEFT(Q11,LEN(Q11)-2)),"")) | BO11: =IF(R11="-","",IFERROR(VALUE(LEFT(R11,LEN(R11)-5)),"")) | BP11: =IF(R11="-","",IFERROR(VALUE(F11),"")) | BQ11: =IF(R11="-",1,0) -> 1
A12: JQC9414 | B12: R5155 | C12: ROTA TRANSPORTES - ITABUNA | D12: ISRAEL SOARES DOS SANTOS - 09628284916, Jose Raimundo dos Santos - 00335224563, EDVALDO ELIAS SILVA - 99881624568, ERICO OLIVEIRA PEREIRA - 04284740555 | E12: 46276 | F12: 183.77 | G12: 0.42375 | H12: 0.32835648 | I12: 0.00016203704 | J12: 0 | K12: 3 | L12: 0 | M12: 0 | N12: 1 | O12: 0 | P12: 0 | Q12: - | R12: - | S12: 0 | T12: 0 | U12: 0 | V12: 0 | W12: 0 | X12: 0 | Y12: 0 | Z12: 0 | AA12: 0 | AB12: 0 | AC12: - | AD12: BR-415 | AE12: 727042.08 | AF12: 727225.86 | AG12: 0.36813657 | AH12: 0.16981481 | AI12: 0 | AJ12: 0 | AK12: 0 | AL12: 0 | AM12: N/A | AN12: 0 | AO12: 0 | AP12: 0 | AQ12: 0 | AR12: 0 | AS12: 0 | AT12: 0 | AU12: 5 | AV12: 0 | AW12: 0 | AX12: 0 | AY12: 0 | AZ12: 0 | BA12: 0 | BB12: 0 | BC12: 0 | BD12: 0 | BE12: 0 | BF12: 0 | BG12: 0 | BH12: 0 | BI12: 0 | BJ12: 0 | BK12: 0 | BM12: =IFERROR(VALUE(F12),"") -> 183.77 | BN12: =IF(R12="-","",IFERROR(VALUE(LEFT(Q12,LEN(Q12)-2)),"")) | BO12: =IF(R12="-","",IFERROR(VALUE(LEFT(R12,LEN(R12)-5)),"")) | BP12: =IF(R12="-","",IFERROR(VALUE(F12),"")) | BQ12: =IF(R12="-",1,0) -> 1
A13: JQC9414 | B13: R5155 | C13: ROTA TRANSPORTES - ITABUNA | D13: EDVALDO ELIAS SILVA - 99881624568 | E13: 46277 | F13: 38.64 | G13: 0.1306713 | H13: 0.029560185 | I13: 0 | J13: 0 | K13: 0 | L13: 0 | M13: 0 | N13: 0 | O13: 0 | P13: 0 | Q13: - | R13: - | S13: 0 | T13: 0 | U13: 0 | V13: 0 | W13: 0 | X13: 0 | Y13: 0 | Z13: 0 | AA13: 0 | AB13: 0 | AC13: BR-415 | AD13: Avenida Amélia Amado | AE13: 727226.00 | AF13: 727264.64 | AG13: 0.076319444 | AH13: 0.17378472 | AI13: 0 | AJ13: 0 | AK13: 0 | AL13: 0 | AM13: N/A | AN13: 0 | AO13: 1 | AP13: 0 | AQ13: 0 | AR13: 0 | AS13: 0 | AT13: 0 | AU13: 0 | AV13: 0 | AW13: 0 | AX13: 0 | AY13: 0 | AZ13: 0 | BA13: 0 | BB13: 0 | BC13: 0 | BD13: 0 | BE13: 0 | BF13: 0 | BG13: 0 | BH13: 0 | BI13: 0 | BJ13: 0 | BK13: 0 | BM13: =IFERROR(VALUE(F13),"") -> 38.64 | BN13: =IF(R13="-","",IFERROR(VALUE(LEFT(Q13,LEN(Q13)-2)),"")) | BO13: =IF(R13="-","",IFERROR(VALUE(LEFT(R13,LEN(R13)-5)),"")) | BP13: =IF(R13="-","",IFERROR(VALUE(F13),"")) | BQ13: =IF(R13="-",1,0) -> 1
A14: JQC9414 | B14: R5155 | C14: ROTA TRANSPORTES - ITABUNA | D14: MARCOS CARVALHO RIBEIRO - 03981643550, EDVALDO ELIAS SILVA - 99881624568, EMERSON ANDRADE DA SILVA - 96170824549 | E14: 46279 | F14: 167.71 | G14: 0.35394676 | H14: 0.15900463 | I14: 0.0017013889 | J14: 0 | K14: 1 | L14: 0 | M14: 0 | N14: 3 | O14: 0 | P14: 0 | Q14: - | R14: - | S14: 0 | T14: 0 | U14: 0 | V14: 0 | W14: 0 | X14: 0 | Y14: 0 | Z14: 0 | AA14: 0 | AB14: 0 | AC14: Rua K | AD14: Avenida Amélia Amado | AE14: 727264.64 | AF14: 727432.35 | AG14: 0.32133102 | AH14: 0.12704861 | AI14: 0 | AJ14: 0 | AK14: 0 | AL14: 0 | AM14: N/A | AN14: 0 | AO14: 2 | AP14: 0 | AQ14: 0 | AR14: 0 | AS14: 0 | AT14: 0 | AU14: 1 | AV14: 0 | AW14: 0 | AX14: 0 | AY14: 0 | AZ14: 0 | BA14: 0 | BB14: 0 | BC14: 0 | BD14: 0 | BE14: 0 | BF14: 0 | BG14: 0 | BH14: 0 | BI14: 0 | BJ14: 0 | BK14: 0 | BM14: =IFERROR(VALUE(F14),"") -> 167.71 | BN14: =IF(R14="-","",IFERROR(VALUE(LEFT(Q14,LEN(Q14)-2)),"")) | BO14: =IF(R14="-","",IFERROR(VALUE(LEFT(R14,LEN(R14)-5)),"")) | BP14: =IF(R14="-","",IFERROR(VALUE(F14),"")) | BQ14: =IF(R14="-",1,0) -> 1
A15: OUK9598 | B15: R7005 | C15: ROTA TRANSPORTES - ITABUNA | E15: 46273 | F15: 0.34 | G15: 0.0059490741 | H15: 0 | I15: 0 | J15: 0 | K15: 0 | L15: 0 | M15: 0 | N15: 0 | O15: 0 | P15: 0 | Q15: 0.13 L | R15: 2.56 Km/L | S15: 0 | T15: 0.0037037037 | U15: 0.0012731481 | V15: 0.00011574074 | W15: 0 | X15: 0 | Y15: 0 | Z15: 0 | AA15: 0 | AB15: 0 | AE15: 502189.71 | AF15: 502190.05 | AG15: 0.0041550926 | AH15: 0.01994213 | AI15: 0 | AJ15: 0 | AK15: 0 | AL15: 0 | AM15: N/A | AN15: 0 | AO15: 0 | AP15: 0 | AQ15: 0 | AR15: 0 | AS15: 0 | AT15: 0 | AU15: 0 | AV15: 0 | AW15: 0 | AX15: 0 | AY15: 0 | AZ15: 0 | BA15: 0 | BB15: 0 | BC15: 0 | BD15: 0 | BE15: 0 | BF15: 0 | BG15: 0 | BH15: 0 | BI15: 0 | BJ15: 0 | BK15: 0 | BM15: =IFERROR(VALUE(F15),"") -> 0.34 | BN15: =IF(R15="-","",IFERROR(VALUE(LEFT(Q15,LEN(Q15)-2)),"")) -> 0.13 | BO15: =IF(R15="-","",IFERROR(VALUE(LEFT(R15,LEN(R15)-5)),"")) -> 2.56 | BP15: =IF(R15="-","",IFERROR(VALUE(F15),"")) -> 0.34 | BQ15: =IF(R15="-",1,0) -> 0
A16: OUK9598 | B16: R7005 | C16: ROTA TRANSPORTES - ITABUNA | E16: 46274 | F16: 0.00 | G16: 0 | H16: 0 | I16: 0 | J16: 0 | K16: 0 | L16: 0 | M16: 0 | N16: 0 | O16: 0 | P16: 0 | Q16: - | R16: - | S16: 0 | T16: 0 | U16: 0 | V16: 0 | W16: 0 | X16: 0 | Y16: 0 | Z16: 0 | AA16: 0 | AB16: 0 | AE16: 502190.05 | AF16: 502190.05 | AG16: 0 | AH16: 0.017824074 | AI16: 0 | AJ16: 0 | AK16: 0 | AL16: 0 | AM16: N/A | AN16: 0 | AO16: 0 | AP16: 0 | AQ16: 0 | AR16: 0 | AS16: 0 | AT16: 0 | AU16: 0 | AV16: 0 | AW16: 0 | AX16: 0 | AY16: 0 | AZ16: 0 | BA16: 0 | BB16: 0 | BC16: 0 | BD16: 0 | BE16: 0 | BF16: 0 | BG16: 0 | BH16: 0 | BI16: 0 | BJ16: 0 | BK16: 0 | BM16: =IFERROR(VALUE(F16),"") -> 0 | BN16: =IF(R16="-","",IFERROR(VALUE(LEFT(Q16,LEN(Q16)-2)),"")) | BO16: =IF(R16="-","",IFERROR(VALUE(LEFT(R16,LEN(R16)-5)),"")) | BP16: =IF(R16="-","",IFERROR(VALUE(F16),"")) | BQ16: =IF(R16="-",1,0) -> 1
A17: OUK9598 | B17: R7005 | C17: ROTA TRANSPORTES - ITABUNA | D17: JOSE EUDES SANTOS - 93703503572 | E17: 46275 | F17: 175.25 | G17: 0.25594907 | H17: 0.13570602 | I17: 0.0022685185 | J17: 0 | K17: 0 | L17: 0 | M17: 0 | N17: 0 | O17: 0 | P17: 0.01818287 | Q17: 24.98 L | R17: 7.02 Km/L | S17: 0 | T17: 0.067361111 | U17: 0.031597222 | V17: 0.09537037 | W17: 0.00034722222 | X17: 0 | Y17: 0 | Z17: 0 | AA17: 0 | AB17: 0 | AE17: 502190.05 | AF17: 502365.29 | AG17: 0.15369213 | AH17: 0.19775463 | AI17: 0 | AJ17: 0 | AK17: 0 | AL17: 0 | AM17: N/A | AN17: 0 | AO17: 0 | AP17: 0 | AQ17: 0 | AR17: 0 | AS17: 0 | AT17: 0 | AU17: 0 | AV17: 0 | AW17: 0 | AX17: 0 | AY17: 0 | AZ17: 0 | BA17: 0 | BB17: 0 | BC17: 0 | BD17: 0 | BE17: 0 | BF17: 0 | BG17: 0 | BH17: 0 | BI17: 0 | BJ17: 0 | BK17: 0 | BM17: =IFERROR(VALUE(F17),"") -> 175.25 | BN17: =IF(R17="-","",IFERROR(VALUE(LEFT(Q17,LEN(Q17)-2)),"")) -> 24.98 | BO17: =IF(R17="-","",IFERROR(VALUE(LEFT(R17,LEN(R17)-5)),"")) -> 7.02 | BP17: =IF(R17="-","",IFERROR(VALUE(F17),"")) -> 175.25 | BQ17: =IF(R17="-",1,0) -> 0
A18: OUK9598 | B18: R7005 | C18: ROTA TRANSPORTES - ITABUNA | D18: JOSE EUDES SANTOS - 93703503572 | E18: 46276 | F18: 242.45 | G18: 0.30369213 | H18: 0.21016204 | I18: 0.0046412037 | J18: 0 | K18: 0 | L18: 0 | M18: 0 | N18: 0 | O18: 0 | P18: 0.030960648 | Q18: 44.94 L | R18: 5.39 Km/L | S18: 0 | T18: 0.086689815 | U18: 0.0403125 | V18: 0.14716435 | W18: 0.00071759259 | X18: 0 | Y18: 5.787037e-05 | Z18: 0 | AA18: 0 | AB18: 0 | AE18: 502365.29 | AF18: 502607.74 | AG18: 0.21251157 | AH18: 0.15988426 | AI18: 0 | AJ18: 0 | AK18: 0 | AL18: 0 | AM18: N/A | AN18: 0 | AO18: 0 | AP18: 0 | AQ18: 0 | AR18: 0 | AS18: 0 | AT18: 0 | AU18: 1 | AV18: 0 | AW18: 0 | AX18: 0 | AY18: 0 | AZ18: 0 | BA18: 0 | BB18: 0 | BC18: 0 | BD18: 0 | BE18: 0 | BF18: 0 | BG18: 0 | BH18: 0 | BI18: 0 | BJ18: 0 | BK18: 0 | BM18: =IFERROR(VALUE(F18),"") -> 242.45 | BN18: =IF(R18="-","",IFERROR(VALUE(LEFT(Q18,LEN(Q18)-2)),"")) -> 44.94 | BO18: =IF(R18="-","",IFERROR(VALUE(LEFT(R18,LEN(R18)-5)),"")) -> 5.39 | BP18: =IF(R18="-","",IFERROR(VALUE(F18),"")) -> 242.45 | BQ18: =IF(R18="-",1,0) -> 0
A19: OUK9598 | B19: R7005 | C19: ROTA TRANSPORTES - ITABUNA | E19: 46277 | F19: 0.14 | G19: 0.0030092593 | H19: 0 | I19: 0 | J19: 0 | K19: 0 | L19: 0 | M19: 0 | N19: 0 | O19: 0 | P19: 0 | Q19: 0.06 L | R19: 2.46 Km/L | S19: 0 | T19: 0.0024305556 | U19: 0.00034722222 | V19: 0 | W19: 0 | X19: 0 | Y19: 0 | Z19: 0 | AA19: 0 | AB19: 0 | AE19: 502607.74 | AF19: 502607.87 | AG19: 0.0010069444 | AH19: 0.021388889 | AI19: 0 | AJ19: 0 | AK19: 0 | AL19: 0 | AM19: N/A | AN19: 0 | AO19: 0 | AP19: 0 | AQ19: 0 | AR19: 0 | AS19: 0 | AT19: 0 | AU19: 0 | AV19: 0 | AW19: 0 | AX19: 0 | AY19: 0 | AZ19: 0 | BA19: 0 | BB19: 0 | BC19: 0 | BD19: 0 | BE19: 0 | BF19: 0 | BG19: 0 | BH19: 0 | BI19: 0 | BJ19: 0 | BK19: 0 | BM19: =IFERROR(VALUE(F19),"") -> 0.14 | BN19: =IF(R19="-","",IFERROR(VALUE(LEFT(Q19,LEN(Q19)-2)),"")) -> 0.06 | BO19: =IF(R19="-","",IFERROR(VALUE(LEFT(R19,LEN(R19)-5)),"")) -> 2.46 | BP19: =IF(R19="-","",IFERROR(VALUE(F19),"")) -> 0.14 | BQ19: =IF(R19="-",1,0) -> 0
A20: OUK9598 | B20: R7005 | C20: ROTA TRANSPORTES - ITABUNA | D20: ROBERTO CARLOS HIGINO P JUNIOR - 09578097514 | E20: 46279 | F20: 90.26 | G20: 0.13196759 | H20: 0.12896991 | I20: 0.00024305556 | J20: 0 | K20: 0 | L20: 0 | M20: 0 | N20: 0 | O20: 0 | P20: 0 | Q20: 15.81 L | R20: 5.71 Km/L | S20: 0.00011574074 | T20: 0.047569444 | U20: 0.036458333 | V20: 0.045949074 | W20: 0 | X20: 0 | Y20: 0 | Z20: 0 | AA20: 0 | AB20: 0 | AE20: 502607.87 | AF20: 502698.13 | AG20: 0.10657407 | AH20: 0.064826389 | AI20: 0 | AJ20: 0 | AK20: 0 | AL20: 0 | AM20: N/A | AN20: 0 | AO20: 0 | AP20: 0 | AQ20: 0 | AR20: 0 | AS20: 0 | AT20: 0 | AU20: 1 | AV20: 0 | AW20: 0 | AX20: 0 | AY20: 0 | AZ20: 0 | BA20: 0 | BB20: 0 | BC20: 0 | BD20: 0 | BE20: 0 | BF20: 0 | BG20: 0 | BH20: 0 | BI20: 0 | BJ20: 0 | BK20: 0 | BM20: =IFERROR(VALUE(F20),"") -> 90.26 | BN20: =IF(R20="-","",IFERROR(VALUE(LEFT(Q20,LEN(Q20)-2)),"")) -> 15.81 | BO20: =IF(R20="-","",IFERROR(VALUE(LEFT(R20,LEN(R20)-5)),"")) -> 5.71 | BP20: =IF(R20="-","",IFERROR(VALUE(F20),"")) -> 90.26 | BQ20: =IF(R20="-",1,0) -> 0
A21: OUK7589 | B21: R7015 | C21: ROTA TRANSPORTES - ITABUNA | D21: ANTONIEL SILVA NOVAIS - 16687097830 | E21: 46273 | F21: 324.04 | G21: 0.32373843 | H21: 0.32052083 | I21: 0.00024305556 | J21: 0 | K21: 1 | L21: 0 | M21: 0 | N21: 1 | O21: 0 | P21: 0.0084722222 | Q21: 57.56 L | R21: 5.63 Km/L | S21: 0 | T21: 0.078472222 | U21: 0.07025463 | V21: 0.1699537 | W21: 0.00018518519 | X21: 0 | Y21: 0 | Z21: 0 | AA21: 0 | AB21: 0 | AC21: Rua Xavantes | AD21: Rua Xavantes | AE21: 511386.19 | AF21: 511710.23 | AG21: 0.28899306 | AH21: 0.072835648 | AI21: 0 | AJ21: 0 | AK21: 0 | AL21: 0 | AM21: N/A | AN21: 0 | AO21: 0 | AP21: 0 | AQ21: 0 | AR21: 0 | AS21: 0 | AT21: 0 | AU21: 0 | AV21: 0 | AW21: 0 | AX21: 0 | AY21: 0 | AZ21: 0 | BA21: 0 | BB21: 0 | BC21: 0 | BD21: 0 | BE21: 0 | BF21: 0 | BG21: 0 | BH21: 0 | BI21: 0 | BJ21: 0 | BK21: 0 | BM21: =IFERROR(VALUE(F21),"") -> 324.04 | BN21: =IF(R21="-","",IFERROR(VALUE(LEFT(Q21,LEN(Q21)-2)),"")) -> 57.56 | BO21: =IF(R21="-","",IFERROR(VALUE(LEFT(R21,LEN(R21)-5)),"")) -> 5.63 | BP21: =IF(R21="-","",IFERROR(VALUE(F21),"")) -> 324.04 | BQ21: =IF(R21="-",1,0) -> 0
A22: OUK7589 | B22: R7015 | C22: ROTA TRANSPORTES - ITABUNA | E22: 46274 | F22: 1.75 | G22: 0.023900463 | H22: 0 | I22: 0 | J22: 0 | K22: 0 | L22: 0 | M22: 0 | N22: 0 | O22: 0 | P22: 0.014502315 | Q22: 1.65 L | R22: 1.06 Km/L | S22: 0 | T22: 0.02025463 | U22: 0.0023148148 | V22: 0.0005787037 | W22: 0 | X22: 0 | Y22: 0 | Z22: 0 | AA22: 0 | AB22: 0 | AC22: Rua Tupinambás | AD22: Avenida Presidente Dutra | AE22: 511710.23 | AF22: 511711.98 | AG22: 0.0059953704 | AH22: 0.022222222 | AI22: 0 | AJ22: 0 | AK22: 0 | AL22: 0 | AM22: N/A | AN22: 0 | AO22: 0 | AP22: 0 | AQ22: 0 | AR22: 0 | AS22: 0 | AT22: 0 | AU22: 0 | AV22: 0 | AW22: 0 | AX22: 0 | AY22: 0 | AZ22: 0 | BA22: 0 | BB22: 0 | BC22: 0 | BD22: 0 | BE22: 0 | BF22: 0 | BG22: 0 | BH22: 0 | BI22: 0 | BJ22: 0 | BK22: 0 | BM22: =IFERROR(VALUE(F22),"") -> 1.75 | BN22: =IF(R22="-","",IFERROR(VALUE(LEFT(Q22,LEN(Q22)-2)),"")) -> 1.65 | BO22: =IF(R22="-","",IFERROR(VALUE(LEFT(R22,LEN(R22)-5)),"")) -> 1.06 | BP22: =IF(R22="-","",IFERROR(VALUE(F22),"")) -> 1.75 | BQ22: =IF(R22="-",1,0) -> 0
A23: OUK7589 | B23: R7015 | C23: ROTA TRANSPORTES - ITABUNA | D23: JAIMILTON OLIVEIRA ROCHA - 05812579520 | E23: 46275 | F23: 109.12 | G23: 0.20525463 | H23: 0.0171875 | I23: 0.00065972222 | J23: 0 | K23: 0 | L23: 0 | M23: 0 | N23: 0 | O23: 0 | P23: 0.027962963 | Q23: 22.26 L | R23: 4.90 Km/L | S23: 0 | T23: 0.084490741 | U23: 0.082060185 | V23: 0.030439815 | W23: 0.00011574074 | X23: 0 | Y23: 0 | Z23: 0 | AA23: 0 | AB23: 0 | AC23: Avenida Presidente Dutra | AD23: Avenida Presidente Dutra | AE23: 511711.98 | AF23: 511821.10 | AG23: 0.15728009 | AH23: 0.14041667 | AI23: 0 | AJ23: 0 | AK23: 0 | AL23: 0 | AM23: N/A | AN23: 0 | AO23: 0 | AP23: 0 | AQ23: 0 | AR23: 0 | AS23: 0 | AT23: 0 | AU23: 0 | AV23: 0 | AW23: 0 | AX23: 0 | AY23: 0 | AZ23: 0 | BA23: 0 | BB23: 0 | BC23: 0 | BD23: 0 | BE23: 0 | BF23: 0 | BG23: 0 | BH23: 0 | BI23: 0 | BJ23: 0 | BK23: 0 | BM23: =IFERROR(VALUE(F23),"") -> 109.12 | BN23: =IF(R23="-","",IFERROR(VALUE(LEFT(Q23,LEN(Q23)-2)),"")) -> 22.26 | BO23: =IF(R23="-","",IFERROR(VALUE(LEFT(R23,LEN(R23)-5)),"")) -> 4.9 | BP23: =IF(R23="-","",IFERROR(VALUE(F23),"")) -> 109.12 | BQ23: =IF(R23="-",1,0) -> 0
A24: OUK7589 | B24: R7015 | C24: ROTA TRANSPORTES - ITABUNA | E24: 46276 | F24: 107.82 | G24: 0.19203704 | H24: 0 | I24: 0.00038194444 | J24: 0 | K24: 0 | L24: 0 | M24: 0 | N24: 1 | O24: 0 | P24: 0.023229167 | Q24: 21.04 L | R24: 5.12 Km/L | S24: 0 | T24: 0.071180556 | U24: 0.084259259 | V24: 0.030439815 | W24: 0 | X24: 0 | Y24: 0 | Z24: 0 | AA24: 0 | AB24: 0 | AC24: Avenida Presidente Dutra | AD24: Avenida Presidente Dutra | AE24: 511821.10 | AF24: 511928.92 | AG24: 0.15143519 | AH24: 0.1316088 | AI24: 0 | AJ24: 0 | AK24: 0 | AL24: 0 | AM24: N/A | AN24: 0 | AO24: 0 | AP24: 0 | AQ24: 0 | AR24: 0 | AS24: 0 | AT24: 0 | AU24: 0 | AV24: 0 | AW24: 0 | AX24: 0 | AY24: 0 | AZ24: 0 | BA24: 0 | BB24: 0 | BC24: 0 | BD24: 0 | BE24: 0 | BF24: 0 | BG24: 0 | BH24: 0 | BI24: 0 | BJ24: 0 | BK24: 0 | BM24: =IFERROR(VALUE(F24),"") -> 107.82 | BN24: =IF(R24="-","",IFERROR(VALUE(LEFT(Q24,LEN(Q24)-2)),"")) -> 21.04 | BO24: =IF(R24="-","",IFERROR(VALUE(LEFT(R24,LEN(R24)-5)),"")) -> 5.12 | BP24: =IF(R24="-","",IFERROR(VALUE(F24),"")) -> 107.82 | BQ24: =IF(R24="-",1,0) -> 0
A25: OUK7589 | B25: R7015 | C25: ROTA TRANSPORTES - ITABUNA | E25: 46277 | F25: 0.14 | G25: 0.004224537 | H25: 0 | I25: 5.787037e-05 | J25: 0 | K25: 0 | L25: 0 | M25: 0 | N25: 0 | O25: 0 | P25: 0 | Q25: 0.25 L | R25: 0.55 Km/L | S25: 0 | T25: 0.0028935185 | U25: 0.00081018519 | V25: 0.00023148148 | W25: 0 | X25: 0 | Y25: 0 | Z25: 0 | AA25: 0 | AB25: 0 | AC25: Avenida Presidente Dutra | AD25: Avenida Presidente Dutra | AE25: 511928.92 | AF25: 511929.06 | AG25: 0.0011805556 | AH25: 0.030185185 | AI25: 0 | AJ25: 0 | AK25: 0 | AL25: 0 | AM25: N/A | AN25: 0 | AO25: 0 | AP25: 0 | AQ25: 0 | AR25: 0 | AS25: 0 | AT25: 0 | AU25: 0 | AV25: 0 | AW25: 0 | AX25: 0 | AY25: 0 | AZ25: 0 | BA25: 0 | BB25: 0 | BC25: 0 | BD25: 0 | BE25: 0 | BF25: 0 | BG25: 0 | BH25: 0 | BI25: 0 | BJ25: 0 | BK25: 0 | BM25: =IFERROR(VALUE(F25),"") -> 0.14 | BN25: =IF(R25="-","",IFERROR(VALUE(LEFT(Q25,LEN(Q25)-2)),"")) -> 0.25 | BO25: =IF(R25="-","",IFERROR(VALUE(LEFT(R25,LEN(R25)-5)),"")) -> 0.55 | BP25: =IF(R25="-","",IFERROR(VALUE(F25),"")) -> 0.14 | BQ25: =IF(R25="-",1,0) -> 0
A26: OUK7589 | B26: R7015 | C26: ROTA TRANSPORTES - ITABUNA | D26: VALDINEUDO JOSE ALVES CLARO - 87261758434 | E26: 46279 | F26: 107.89 | G26: 0.19121528 | H26: 0.0036111111 | I26: 0.00052083333 | J26: 0 | K26: 0 | L26: 0 | M26: 0 | N26: 1 | O26: 0 | P26: 0.027789352 | Q26: 21.97 L | R26: 4.91 Km/L | S26: 0 | T26: 0.071643519 | U26: 0.076747685 | V26: 0.03587963 | W26: 0.00037037037 | X26: 0 | Y26: 6.9444444e-05 | Z26: 0 | AA26: 0 | AB26: 0 | AC26: Avenida Presidente Dutra | AD26: Avenida Presidente Dutra | AE26: 511929.06 | AF26: 512036.95 | AG26: 0.14619213 | AH26: 0.12109954 | AI26: 0 | AJ26: 0 | AK26: 0 | AL26: 0 | AM26: N/A | AN26: 0 | AO26: 0 | AP26: 0 | AQ26: 0 | AR26: 0 | AS26: 0 | AT26: 0 | AU26: 0 | AV26: 0 | AW26: 0 | AX26: 0 | AY26: 0 | AZ26: 0 | BA26: 0 | BB26: 0 | BC26: 0 | BD26: 0 | BE26: 0 | BF26: 0 | BG26: 0 | BH26: 0 | BI26: 0 | BJ26: 0 | BK26: 0 | BM26: =IFERROR(VALUE(F26),"") -> 107.89 | BN26: =IF(R26="-","",IFERROR(VALUE(LEFT(Q26,LEN(Q26)-2)),"")) -> 21.97 | BO26: =IF(R26="-","",IFERROR(VALUE(LEFT(R26,LEN(R26)-5)),"")) -> 4.91 | BP26: =IF(R26="-","",IFERROR(VALUE(F26),"")) -> 107.89 | BQ26: =IF(R26="-",1,0) -> 0
A27: OUK7974 | B27: R7025 | C27: ROTA TRANSPORTES - ITABUNA | E27: 46273 | F27: 175.73 | G27: 0.17023148 | H27: 0 | I27: 0.00013888889 | J27: 0 | K27: 1 | L27: 0 | M27: 0 | N27: 2 | O27: 0 | P27: 0 | Q27: 33.79 L | R27: 5.20 Km/L | S27: 0 | T27: 0.038425926 | U27: 0.035763889 | V27: 0.093055556 | W27: 0 | X27: 0 | Y27: 0 | Z27: 0 | AA27: 0 | AB27: 0 | AC27: Rua Castro Alves | AD27: Rua Bela Vista | AE27: 615405.81 | AF27: 615581.54 | AG27: 0.15524306 | AH27: 0.036840278 | AI27: 0 | AJ27: 0 | AK27: 0 | AL27: 0 | AM27: N/A | AN27: 0 | AO27: 0 | AP27: 0 | AQ27: 0 | AR27: 0 | AS27: 0 | AT27: 0 | AU27: 1 | AV27: 0 | AW27: 0 | AX27: 0 | AY27: 0 | AZ27: 0 | BA27: 0 | BB27: 0 | BC27: 0 | BD27: 0 | BE27: 0 | BF27: 0 | BG27: 0 | BH27: 0 | BI27: 0 | BJ27: 0 | BK27: 0 | BM27: =IFERROR(VALUE(F27),"") -> 175.73 | BN27: =IF(R27="-","",IFERROR(VALUE(LEFT(Q27,LEN(Q27)-2)),"")) -> 33.79 | BO27: =IF(R27="-","",IFERROR(VALUE(LEFT(R27,LEN(R27)-5)),"")) -> 5.2 | BP27: =IF(R27="-","",IFERROR(VALUE(F27),"")) -> 175.73 | BQ27: =IF(R27="-",1,0) -> 0
A28: OUK7974 | B28: R7025 | C28: ROTA TRANSPORTES - ITABUNA | E28: 46274 | F28: 296.22 | G28: 0.23802083 | H28: 0 | I28: 0.00011574074 | J28: 0 | K28: 2 | L28: 0 | M28: 0 | N28: 1 | O28: 0 | P28: 0 | Q28: 50.70 L | R28: 5.84 Km/L | S28: 0 | T28: 0.044212963 | U28: 0.026851852 | V28: 0.15810185 | W28: 0.00011574074 | X28: 0 | Y28: 0 | Z28: 0 | AA28: 0 | AB28: 0 | AC28: Rua Rui Barbosa | AD28: Rua Bela Vista | AE28: 615581.54 | AF28: 615877.76 | AG28: 0.21241898 | AH28: 0.1184375 | AI28: 0 | AJ28: 0 | AK28: 0 | AL28: 0 | AM28: N/A | AN28: 0 | AO28: 0 | AP28: 0 | AQ28: 0 | AR28: 0 | AS28: 0 | AT28: 0 | AU28: 1 | AV28: 0 | AW28: 0 | AX28: 0 | AY28: 0 | AZ28: 0 | BA28: 0 | BB28: 0 | BC28: 0 | BD28: 0 | BE28: 0 | BF28: 0 | BG28: 0 | BH28: 0 | BI28: 0 | BJ28: 0 | BK28: 0 | BM28: =IFERROR(VALUE(F28),"") -> 296.22 | BN28: =IF(R28="-","",IFERROR(VALUE(LEFT(Q28,LEN(Q28)-2)),"")) -> 50.7 | BO28: =IF(R28="-","",IFERROR(VALUE(LEFT(R28,LEN(R28)-5)),"")) -> 5.84 | BP28: =IF(R28="-","",IFERROR(VALUE(F28),"")) -> 296.22 | BQ28: =IF(R28="-",1,0) -> 0
A29: OUK7974 | B29: R7025 | C29: ROTA TRANSPORTES - ITABUNA | D29: FABIANO REIS DOS SANTOS - 06063406530 | E29: 46275 | F29: 297.74 | G29: 0.25791667 | H29: 0.0056365741 | I29: 0.00024305556 | J29: 0 | K29: 0 | L29: 0 | M29: 0 | N29: 1 | O29: 0 | P29: 0 | Q29: 52.49 L | R29: 5.67 Km/L | S29: 0 | T29: 0.061574074 | U29: 0.029282407 | V29: 0.15856481 | W29: 0.00034722222 | X29: 0 | Y29: 0 | Z29: 0 | AA29: 0 | AB29: 0 | AC29: Rua Rui Barbosa | AD29: Rua Bela Vista | AE29: 615877.76 | AF29: 616175.49 | AG29: 0.22024306 | AH29: 0.096446759 | AI29: 0 | AJ29: 0 | AK29: 0 | AL29: 0 | AM29: N/A | AN29: 0 | AO29: 0 | AP29: 0 | AQ29: 0 | AR29: 0 | AS29: 0 | AT29: 0 | AU29: 0 | AV29: 0 | AW29: 0 | AX29: 0 | AY29: 0 | AZ29: 0 | BA29: 0 | BB29: 0 | BC29: 0 | BD29: 0 | BE29: 0 | BF29: 0 | BG29: 0 | BH29: 0 | BI29: 0 | BJ29: 0 | BK29: 0 | BM29: =IFERROR(VALUE(F29),"") -> 297.74 | BN29: =IF(R29="-","",IFERROR(VALUE(LEFT(Q29,LEN(Q29)-2)),"")) -> 52.49 | BO29: =IF(R29="-","",IFERROR(VALUE(LEFT(R29,LEN(R29)-5)),"")) -> 5.67 | BP29: =IF(R29="-","",IFERROR(VALUE(F29),"")) -> 297.74 | BQ29: =IF(R29="-",1,0) -> 0
A30: OUK7974 | B30: R7025 | C30: ROTA TRANSPORTES - ITABUNA | E30: 46276 | F30: 297.71 | G30: 0.25681713 | H30: 0 | I30: 0.00023148148 | J30: 0 | K30: 0 | L30: 0 | M30: 0 | N30: 4 | O30: 0 | P30: 0 | Q30: 52.18 L | R30: 5.71 Km/L | S30: 0 | T30: 0.055208333 | U30: 0.038657407 | V30: 0.15601852 | W30: 0.00023148148 | X30: 0 | Y30: 0 | Z30: 0 | AA30: 0 | AB30: 0 | AC30: Rua Bela Vista | AD30: Rua Bela Vista | AE30: 616175.49 | AF30: 616473.20 | AG30: 0.23126157 | AH30: 0.10664352 | AI30: 0 | AJ30: 0 | AK30: 0 | AL30: 0 | AM30: N/A | AN30: 0 | AO30: 0 | AP30: 0 | AQ30: 0 | AR30: 0 | AS30: 0 | AT30: 0 | AU30: 0 | AV30: 0 | AW30: 0 | AX30: 0 | AY30: 0 | AZ30: 0 | BA30: 0 | BB30: 0 | BC30: 0 | BD30: 0 | BE30: 0 | BF30: 0 | BG30: 0 | BH30: 0 | BI30: 0 | BJ30: 0 | BK30: 0 | BM30: =IFERROR(VALUE(F30),"") -> 297.71 | BN30: =IF(R30="-","",IFERROR(VALUE(LEFT(Q30,LEN(Q30)-2)),"")) -> 52.18 | BO30: =IF(R30="-","",IFERROR(VALUE(LEFT(R30,LEN(R30)-5)),"")) -> 5.71 | BP30: =IF(R30="-","",IFERROR(VALUE(F30),"")) -> 297.71 | BQ30: =IF(R30="-",1,0) -> 0
A31: OUK7974 | B31: R7025 | C31: ROTA TRANSPORTES - ITABUNA | E31: 46279 | F31: 297.83 | G31: 0.25217593 | H31: 0 | I31: 0.00037037037 | J31: 0 | K31: 0 | L31: 0 | M31: 0 | N31: 2 | O31: 0 | P31: 0 | Q31: 53.17 L | R31: 5.60 Km/L | S31: 0 | T31: 0.058680556 | U31: 0.029166667 | V31: 0.15601852 | W31: 0.00023148148 | X31: 0 | Y31: 0 | Z31: 0 | AA31: 0 | AB31: 0 | AC31: Rua Bela Vista | AD31: Rua Bela Vista | AE31: 616473.20 | AF31: 616771.03 | AG31: 0.22146991 | AH31: 0.099884259 | AI31: 0 | AJ31: 0 | AK31: 0 | AL31: 0 | AM31: N/A | AN31: 0 | AO31: 0 | AP31: 0 | AQ31: 0 | AR31: 0 | AS31: 0 | AT31: 0 | AU31: 2 | AV31: 0 | AW31: 0 | AX31: 0 | AY31: 0 | AZ31: 0 | BA31: 0 | BB31: 0 | BC31: 0 | BD31: 0 | BE31: 0 | BF31: 0 | BG31: 0 | BH31: 0 | BI31: 0 | BJ31: 0 | BK31: 0 | BM31: =IFERROR(VALUE(F31),"") -> 297.83 | BN31: =IF(R31="-","",IFERROR(VALUE(LEFT(Q31,LEN(Q31)-2)),"")) -> 53.17 | BO31: =IF(R31="-","",IFERROR(VALUE(LEFT(R31,LEN(R31)-5)),"")) -> 5.6 | BP31: =IF(R31="-","",IFERROR(VALUE(F31),"")) -> 297.83 | BQ31: =IF(R31="-",1,0) -> 0
A32: OUK3365 | B32: R7035 | C32: ROTA TRANSPORTES - ITABUNA | E32: 46274 | F32: 0.23 | G32: 0.0025694444 | H32: 0 | I32: 0 | J32: 0 | K32: 0 | L32: 0 | M32: 0 | N32: 0 | O32: 0 | P32: 0 | Q32: 0.17 L | R32: 1.35 Km/L | S32: 0 | T32: 0.0015046296 | U32: 0.00034722222 | V32: 0.00034722222 | W32: 0.00011574074 | X32: 0 | Y32: 0 | Z32: 0 | AA32: 0 | AB32: 0 | AC32: Avenida Governador Roberto Santos | AD32: Avenida Governador Roberto Santos | AE32: 572437.20 | AF32: 572437.42 | AG32: 0.0011574074 | AH32: 0.0033796296 | AI32: 0 | AJ32: 0 | AK32: 0 | AL32: 0 | AM32: N/A | AN32: 0 | AO32: 0 | AP32: 0 | AQ32: 0 | AR32: 0 | AS32: 0 | AT32: 0 | AU32: 0 | AV32: 0 | AW32: 0 | AX32: 0 | AY32: 0 | AZ32: 0 | BA32: 0 | BB32: 0 | BC32: 0 | BD32: 0 | BE32: 0 | BF32: 0 | BG32: 0 | BH32: 0 | BI32: 0 | BJ32: 0 | BK32: 0 | BM32: =IFERROR(VALUE(F32),"") -> 0.23 | BN32: =IF(R32="-","",IFERROR(VALUE(LEFT(Q32,LEN(Q32)-2)),"")) -> 0.17 | BO32: =IF(R32="-","",IFERROR(VALUE(LEFT(R32,LEN(R32)-5)),"")) -> 1.35 | BP32: =IF(R32="-","",IFERROR(VALUE(F32),"")) -> 0.23 | BQ32: =IF(R32="-",1,0) -> 0
A33: OUK3365 | B33: R7035 | C33: ROTA TRANSPORTES - ITABUNA | D33: EDSON RIBEIRO BATISTA SANTOS - 03640303563 | E33: 46276 | F33: 6.34 | G33: 0.01412037 | H33: 0.01412037 | I33: 0.00010416667 | J33: 0 | K33: 0 | L33: 0 | M33: 0 | N33: 0 | O33: 0 | P33: 0 | Q33: 1.57 L | R33: 4.04 Km/L | S33: 0 | T33: 0.0046296296 | U33: 0.0060185185 | V33: 0.0032407407 | W33: 0 | X33: 0 | Y33: 0 | Z33: 0 | AA33: 0 | AB33: 0 | AC33: Avenida Governador Roberto Santos | AD33: Avenida Governador Roberto Santos | AE33: 572437.42 | AF33: 572443.76 | AG33: 0.012893519 | AH33: 0.015428241 | AI33: 0 | AJ33: 0 | AK33: 0 | AL33: 0 | AM33: N/A | AN33: 0 | AO33: 0 | AP33: 0 | AQ33: 0 | AR33: 0 | AS33: 0 | AT33: 0 | AU33: 0 | AV33: 0 | AW33: 0 | AX33: 0 | AY33: 0 | AZ33: 0 | BA33: 0 | BB33: 0 | BC33: 0 | BD33: 0 | BE33: 0 | BF33: 0 | BG33: 0 | BH33: 0 | BI33: 0 | BJ33: 0 | BK33: 0 | BM33: =IFERROR(VALUE(F33),"") -> 6.34 | BN33: =IF(R33="-","",IFERROR(VALUE(LEFT(Q33,LEN(Q33)-2)),"")) -> 1.57 | BO33: =IF(R33="-","",IFERROR(VALUE(LEFT(R33,LEN(R33)-5)),"")) -> 4.04 | BP33: =IF(R33="-","",IFERROR(VALUE(F33),"")) -> 6.34 | BQ33: =IF(R33="-",1,0) -> 0
A34: OUK3365 | B34: R7035 | C34: ROTA TRANSPORTES - ITABUNA | E34: 46277 | F34: 0.19 | G34: 0.0028125 | H34: 0 | I34: 0 | J34: 0 | K34: 0 | L34: 0 | M34: 0 | N34: 0 | O34: 0 | P34: 0 | Q34: 0.20 L | R34: 0.93 Km/L | S34: 0 | T34: 0.0011574074 | U34: 0.00092592593 | V34: 0.00046296296 | W34: 0 | X34: 0 | Y34: 0 | Z34: 0 | AA34: 0 | AB34: 0 | AC34: Avenida Governador Roberto Santos | AD34: Avenida Governador Roberto Santos | AE34: 572443.76 | AF34: 572443.95 | AG34: 0.0020601852 | AH34: 0.014618056 | AI34: 0 | AJ34: 0 | AK34: 0 | AL34: 0 | AM34: N/A | AN34: 0 | AO34: 0 | AP34: 0 | AQ34: 0 | AR34: 0 | AS34: 0 | AT34: 0 | AU34: 0 | AV34: 0 | AW34: 0 | AX34: 0 | AY34: 0 | AZ34: 0 | BA34: 0 | BB34: 0 | BC34: 0 | BD34: 0 | BE34: 0 | BF34: 0 | BG34: 0 | BH34: 0 | BI34: 0 | BJ34: 0 | BK34: 0 | BM34: =IFERROR(VALUE(F34),"") -> 0.19 | BN34: =IF(R34="-","",IFERROR(VALUE(LEFT(Q34,LEN(Q34)-2)),"")) -> 0.2 | BO34: =IF(R34="-","",IFERROR(VALUE(LEFT(R34,LEN(R34)-5)),"")) -> 0.93 | BP34: =IF(R34="-","",IFERROR(VALUE(F34),"")) -> 0.19 | BQ34: =IF(R34="-",1,0) -> 0
A35: JQI1373 | B35: R5485 | C35: ROTA TRANSPORTES - ITABUNA | D35: Jose Raimundo dos Santos - 00335224563, JOVANDO SANTANA MOREIRA - 65889843591, TIAGO SILVA BASTOS - 02581506539 | E35: 46273 | F35: 340.86 | G35: 0.59043981 | H35: 0.58486111 | I35: 0.00077546296 | J35: 1 | K35: 4 | L35: 0 | M35: 0 | N35: 8 | O35: 0 | P35: 0 | Q35: - | R35: - | S35: 0 | T35: 0 | U35: 0 | V35: 0 | W35: 0 | X35: 0 | Y35: 0 | Z35: 0 | AA35: 0 | AB35: 0 | AC35: Avenida Amélia Amado | AD35: Avenida Amélia Amado | AE35: 89788.48 | AF35: 90129.34 | AG35: 0.50140046 | AH35: 0.18913194 | AI35: 1.1574074e-05 | AJ35: 0 | AK35: 0 | AL35: 0 | AM35: N/A | AN35: 0 | AO35: 1 | AP35: 0 | AQ35: 0 | AR35: 0 | AS35: 0 | AT35: 0 | AU35: 3 | AV35: 0 | AW35: 0 | AX35: 0 | AY35: 0 | AZ35: 0 | BA35: 0 | BB35: 0 | BC35: 0 | BD35: 0 | BE35: 0 | BF35: 0 | BG35: 0 | BH35: 0 | BI35: 0 | BJ35: 0 | BK35: 0 | BM35: =IFERROR(VALUE(F35),"") -> 340.86 | BN35: =IF(R35="-","",IFERROR(VALUE(LEFT(Q35,LEN(Q35)-2)),"")) | BO35: =IF(R35="-","",IFERROR(VALUE(LEFT(R35,LEN(R35)-5)),"")) | BP35: =IF(R35="-","",IFERROR(VALUE(F35),"")) | BQ35: =IF(R35="-",1,0) -> 1
A36: JQI1373 | B36: R5485 | C36: ROTA TRANSPORTES - ITABUNA | D36: FABIANO REIS DOS SANTOS - 06063406530, FERNANDO DAMASCENO DE JESUS - 03779273500 | E36: 46274 | F36: 31.50 | G36: 0.084386574 | H36: 0.078402778 | I36: 4.6296296e-05 | J36: 0 | K36: 0 | L36: 0 | M36: 0 | N36: 0 | O36: 0 | P36: 0 | Q36: - | R36: - | S36: 0 | T36: 0 | U36: 0 | V36: 0 | W36: 0 | X36: 0 | Y36: 0 | Z36: 0 | AA36: 0 | AB36: 0 | AC36: Avenida Amélia Amado | AD36: Rua João Franco | AE36: 90129.34 | AF36: 90160.84 | AG36: 0.057893519 | AH36: 0.046770833 | AI36: 0 | AJ36: 0 | AK36: 0 | AL36: 0 | AM36: N/A | AN36: 0 | AO36: 0 | AP36: 0 | AQ36: 0 | AR36: 0 | AS36: 0 | AT36: 0 | AU36: 3 | AV36: 0 | AW36: 0 | AX36: 0 | AY36: 0 | AZ36: 0 | BA36: 0 | BB36: 0 | BC36: 0 | BD36: 0 | BE36: 0 | BF36: 0 | BG36: 0 | BH36: 0 | BI36: 0 | BJ36: 0 | BK36: 0 | BM36: =IFERROR(VALUE(F36),"") -> 31.5 | BN36: =IF(R36="-","",IFERROR(VALUE(LEFT(Q36,LEN(Q36)-2)),"")) | BO36: =IF(R36="-","",IFERROR(VALUE(LEFT(R36,LEN(R36)-5)),"")) | BP36: =IF(R36="-","",IFERROR(VALUE(F36),"")) | BQ36: =IF(R36="-",1,0) -> 1
A37: JQI1373 | B37: R5485 | C37: ROTA TRANSPORTES - ITABUNA | D37: Jose Adilson Dos Santos Reis - 02053767545, JUCIMAR DE JESUS SANTOS - 03136869559 | E37: 46275 | F37: 181.93 | G37: 0.42074074 | H37: 0.37482639 | I37: 0.0003125 | J37: 0 | K37: 0 | L37: 0 | M37: 0 | N37: 0 | O37: 0 | P37: 0 | Q37: - | R37: - | S37: 0 | T37: 0 | U37: 0 | V37: 0 | W37: 0 | X37: 0 | Y37: 0 | Z37: 0 | AA37: 0 | AB37: 0 | AC37: Rua Castro Alves | AD37: Rua K | AE37: 90160.84 | AF37: 90342.77 | AG37: 0.31783565 | AH37: 0.19135417 | AI37: 0 | AJ37: 0 | AK37: 0 | AL37: 0 | AM37: N/A | AN37: 0 | AO37: 0 | AP37: 0 | AQ37: 0 | AR37: 0 | AS37: 0 | AT37: 0 | AU37: 7 | AV37: 0 | AW37: 0 | AX37: 0 | AY37: 0 | AZ37: 0 | BA37: 0 | BB37: 0 | BC37: 0 | BD37: 0 | BE37: 0 | BF37: 0 | BG37: 0 | BH37: 0 | BI37: 0 | BJ37: 0 | BK37: 0 | BM37: =IFERROR(VALUE(F37),"") -> 181.93 | BN37: =IF(R37="-","",IFERROR(VALUE(LEFT(Q37,LEN(Q37)-2)),"")) | BO37: =IF(R37="-","",IFERROR(VALUE(LEFT(R37,LEN(R37)-5)),"")) | BP37: =IF(R37="-","",IFERROR(VALUE(F37),"")) | BQ37: =IF(R37="-",1,0) -> 1
A38: JQI1373 | B38: R5485 | C38: ROTA TRANSPORTES - ITABUNA | D38: JOVANDO SANTANA MOREIRA - 65889843591, ERICO OLIVEIRA PEREIRA - 04284740555, MARCELO BATISTA SANTOS - 08636731550 | E38: 46276 | F38: 167.34 | G38: 0.31263889 | H38: 0.29927083 | I38: 0.00090277778 | J38: 0 | K38: 1 | L38: 0 | M38: 0 | N38: 4 | O38: 0 | P38: 0 | Q38: - | R38: - | S38: 0 | T38: 0 | U38: 0 | V38: 0 | W38: 0 | X38: 0 | Y38: 0 | Z38: 0 | AA38: 0 | AB38: 0 | AC38: Rua João Franco | AD38: Rua K | AE38: 90342.77 | AF38: 90510.10 | AG38: 0.2565625 | AH38: 0.14783565 | AI38: 0 | AJ38: 0 | AK38: 0 | AL38: 0 | AM38: N/A | AN38: 0 | AO38: 0 | AP38: 0 | AQ38: 0 | AR38: 0 | AS38: 0 | AT38: 0 | AU38: 3 | AV38: 0 | AW38: 0 | AX38: 0 | AY38: 0 | AZ38: 0 | BA38: 0 | BB38: 0 | BC38: 0 | BD38: 0 | BE38: 0 | BF38: 0 | BG38: 0 | BH38: 0 | BI38: 0 | BJ38: 0 | BK38: 0 | BM38: =IFERROR(VALUE(F38),"") -> 167.34 | BN38: =IF(R38="-","",IFERROR(VALUE(LEFT(Q38,LEN(Q38)-2)),"")) | BO38: =IF(R38="-","",IFERROR(VALUE(LEFT(R38,LEN(R38)-5)),"")) | BP38: =IF(R38="-","",IFERROR(VALUE(F38),"")) | BQ38: =IF(R38="-",1,0) -> 1
A39: JQI1373 | B39: R5485 | C39: ROTA TRANSPORTES - ITABUNA | D39: RAFAEL DE JESUS BARRETO - 85830111500, Jose Raimundo dos Santos - 00335224563, JUCIMAR DE JESUS SANTOS - 03136869559, OSNILDO CLEMENTINO ROCHA DOS - 87948125515, TALES ANTONIO ALMEIDA ALVES JUNIOR - 09534524506 | E39: 46279 | F39: 265.67 | G39: 0.50819444 | H39: 0.45653935 | I39: 0.0019907407 | J39: 0 | K39: 1 | L39: 0 | M39: 0 | N39: 1 | O39: 0 | P39: 0 | Q39: - | R39: - | S39: 0 | T39: 0 | U39: 0 | V39: 0 | W39: 0 | X39: 0 | Y39: 0 | Z39: 0 | AA39: 0 | AB39: 0 | AC39: Avenida Amélia Amado | AD39: Rua K | AE39: 90510.10 | AF39: 90775.77 | AG39: 0.33578704 | AH39: 0.25248843 | AI39: 0 | AJ39: 0 | AK39: 0 | AL39: 0 | AM39: N/A | AN39: 0 | AO39: 0 | AP39: 0 | AQ39: 0 | AR39: 0 | AS39: 0 | AT39: 0 | AU39: 9 | AV39: 0 | AW39: 0 | AX39: 0 | AY39: 0 | AZ39: 0 | BA39: 0 | BB39: 0 | BC39: 0 | BD39: 0 | BE39: 0 | BF39: 0 | BG39: 0 | BH39: 0 | BI39: 0 | BJ39: 0 | BK39: 0 | BM39: =IFERROR(VALUE(F39),"") -> 265.67 | BN39: =IF(R39="-","",IFERROR(VALUE(LEFT(Q39,LEN(Q39)-2)),"")) | BO39: =IF(R39="-","",IFERROR(VALUE(LEFT(R39,LEN(R39)-5)),"")) | BP39: =IF(R39="-","",IFERROR(VALUE(F39),"")) | BQ39: =IF(R39="-",1,0) -> 1
A40: JQI1371 | B40: R5495 | C40: ROTA TRANSPORTES - ITABUNA | E40: 46273 | F40: 0.00 | G40: 0.95377315 | H40: 0 | I40: 0 | J40: 0 | K40: 0 | L40: 0 | M40: 0 | N40: 0 | O40: 0 | P40: 0 | Q40: - | R40: - | S40: 0 | T40: 0 | U40: 0 | V40: 0 | W40: 0 | X40: 0 | Y40: 0 | Z40: 0 | AA40: 0 | AB40: 0 | AC40: Rua K | AD40: Rua K | AE40: 18530.35 | AF40: 18530.35 | AG40: 0 | AH40: 0.026747685 | AI40: 0 | AJ40: 0 | AK40: 0 | AL40: 0 | AM40: N/A | AN40: 0 | AO40: 0 | AP40: 0 | AQ40: 0 | AR40: 0 | AS40: 0 | AT40: 0 | AU40: 0 | AV40: 0 | AW40: 0 | AX40: 0 | AY40: 0 | AZ40: 0 | BA40: 0 | BB40: 0 | BC40: 0 | BD40: 0 | BE40: 0 | BF40: 0 | BG40: 0 | BH40: 0 | BI40: 0 | BJ40: 0 | BK40: 0 | BM40: =IFERROR(VALUE(F40),"") -> 0 | BN40: =IF(R40="-","",IFERROR(VALUE(LEFT(Q40,LEN(Q40)-2)),"")) | BO40: =IF(R40="-","",IFERROR(VALUE(LEFT(R40,LEN(R40)-5)),"")) | BP40: =IF(R40="-","",IFERROR(VALUE(F40),"")) | BQ40: =IF(R40="-",1,0) -> 1
A41: JQI1371 | B41: R5495 | C41: ROTA TRANSPORTES - ITABUNA | E41: 46274 | F41: 0.82 | G41: 0.35806713 | H41: 0 | I41: 0 | J41: 0 | K41: 0 | L41: 0 | M41: 0 | N41: 0 | O41: 0 | P41: 0 | Q41: - | R41: - | S41: 0 | T41: 0 | U41: 0 | V41: 0 | W41: 0 | X41: 0 | Y41: 0 | Z41: 0 | AA41: 0 | AB41: 0 | AC41: Rua K | AD41: Rua K | AE41: 18530.35 | AF41: 18531.17 | AG41: 0.010601852 | AH41: 0.036944444 | AI41: 0 | AJ41: 0 | AK41: 0 | AL41: 0 | AM41: N/A | AN41: 0 | AO41: 0 | AP41: 0 | AQ41: 0 | AR41: 0 | AS41: 0 | AT41: 0 | AU41: 0 | AV41: 0 | AW41: 0 | AX41: 0 | AY41: 0 | AZ41: 0 | BA41: 0 | BB41: 0 | BC41: 0 | BD41: 0 | BE41: 0 | BF41: 0 | BG41: 0 | BH41: 0 | BI41: 0 | BJ41: 0 | BK41: 0 | BM41: =IFERROR(VALUE(F41),"") -> 0.82 | BN41: =IF(R41="-","",IFERROR(VALUE(LEFT(Q41,LEN(Q41)-2)),"")) | BO41: =IF(R41="-","",IFERROR(VALUE(LEFT(R41,LEN(R41)-5)),"")) | BP41: =IF(R41="-","",IFERROR(VALUE(F41),"")) | BQ41: =IF(R41="-",1,0) -> 1
A42: JQI1371 | B42: R5495 | C42: ROTA TRANSPORTES - ITABUNA | E42: 46275 | F42: 0.90 | G42: 0.37753472 | H42: 0 | I42: 0 | J42: 0 | K42: 0 | L42: 0 | M42: 0 | N42: 0 | O42: 0 | P42: 0 | Q42: - | R42: - | S42: 0 | T42: 0 | U42: 0 | V42: 0 | W42: 0 | X42: 0 | Y42: 0 | Z42: 0 | AA42: 0 | AB42: 0 | AC42: Rua K | AD42: Rua João Franco | AE42: 18531.17 | AF42: 18532.07 | AG42: 0.0097222222 | AH42: 0.062523148 | AI42: 0 | AJ42: 0 | AK42: 0 | AL42: 0 | AM42: N/A | AN42: 0 | AO42: 0 | AP42: 0 | AQ42: 0 | AR42: 0 | AS42: 0 | AT42: 0 | AU42: 0 | AV42: 0 | AW42: 0 | AX42: 0 | AY42: 0 | AZ42: 0 | BA42: 0 | BB42: 0 | BC42: 0 | BD42: 0 | BE42: 0 | BF42: 0 | BG42: 0 | BH42: 0 | BI42: 0 | BJ42: 0 | BK42: 0 | BM42: =IFERROR(VALUE(F42),"") -> 0.9 | BN42: =IF(R42="-","",IFERROR(VALUE(LEFT(Q42,LEN(Q42)-2)),"")) | BO42: =IF(R42="-","",IFERROR(VALUE(LEFT(R42,LEN(R42)-5)),"")) | BP42: =IF(R42="-","",IFERROR(VALUE(F42),"")) | BQ42: =IF(R42="-",1,0) -> 1
A43: JQI1371 | B43: R5495 | C43: ROTA TRANSPORTES - ITABUNA | E43: 46276 | F43: 83.69 | G43: 0.41054398 | H43: 0 | I43: 0.0012152778 | J43: 0 | K43: 0 | L43: 0 | M43: 0 | N43: 0 | O43: 0 | P43: 0 | Q43: - | R43: - | S43: 0 | T43: 0 | U43: 0 | V43: 0 | W43: 0 | X43: 0 | Y43: 0 | Z43: 0 | AA43: 0 | AB43: 0 | AC43: Rua K | AD43: Rua K | AE43: 18532.07 | AF43: 18615.76 | AG43: 0.14280093 | AH43: 0.12939815 | AI43: 0 | AJ43: 0 | AK43: 0 | AL43: 0 | AM43: N/A | AN43: 0 | AO43: 0 | AP43: 0 | AQ43: 0 | AR43: 0 | AS43: 0 | AT43: 0 | AU43: 0 | AV43: 0 | AW43: 0 | AX43: 0 | AY43: 0 | AZ43: 0 | BA43: 0 | BB43: 0 | BC43: 0 | BD43: 0 | BE43: 0 | BF43: 0 | BG43: 0 | BH43: 0 | BI43: 0 | BJ43: 0 | BK43: 0 | BM43: =IFERROR(VALUE(F43),"") -> 83.69 | BN43: =IF(R43="-","",IFERROR(VALUE(LEFT(Q43,LEN(Q43)-2)),"")) | BO43: =IF(R43="-","",IFERROR(VALUE(LEFT(R43,LEN(R43)-5)),"")) | BP43: =IF(R43="-","",IFERROR(VALUE(F43),"")) | BQ43: =IF(R43="-",1,0) -> 1
A44: JQI1371 | B44: R5495 | C44: ROTA TRANSPORTES - ITABUNA | E44: 46277 | F44: 60.04 | G44: 0.38164352 | H44: 0 | I44: 0.0014814815 | J44: 0 | K44: 0 | L44: 0 | M44: 0 | N44: 0 | O44: 0 | P44: 0 | Q44: - | R44: - | S44: 0 | T44: 0 | U44: 0 | V44: 0 | W44: 0 | X44: 0 | Y44: 0 | Z44: 0 | AA44: 0 | AB44: 0 | AC44: Rua João Franco | AD44: Rua K | AE44: 18615.76 | AF44: 18675.80 | AG44: 0.090497685 | AH44: 0.031875 | AI44: 0 | AJ44: 0 | AK44: 0 | AL44: 0 | AM44: N/A | AN44: 0 | AO44: 0 | AP44: 0 | AQ44: 0 | AR44: 0 | AS44: 0 | AT44: 0 | AU44: 0 | AV44: 0 | AW44: 0 | AX44: 0 | AY44: 0 | AZ44: 0 | BA44: 0 | BB44: 0 | BC44: 0 | BD44: 0 | BE44: 0 | BF44: 0 | BG44: 0 | BH44: 0 | BI44: 0 | BJ44: 0 | BK44: 0 | BM44: =IFERROR(VALUE(F44),"") -> 60.04 | BN44: =IF(R44="-","",IFERROR(VALUE(LEFT(Q44,LEN(Q44)-2)),"")) | BO44: =IF(R44="-","",IFERROR(VALUE(LEFT(R44,LEN(R44)-5)),"")) | BP44: =IF(R44="-","",IFERROR(VALUE(F44),"")) | BQ44: =IF(R44="-",1,0) -> 1
A45: JQI1371 | B45: R5495 | C45: ROTA TRANSPORTES - ITABUNA | E45: 46279 | F45: 209.66 | G45: 0.63059028 | H45: 0 | I45: 0.011111111 | J45: 0 | K45: 3 | L45: 0 | M45: 0 | N45: 0 | O45: 0 | P45: 0 | Q45: - | R45: - | S45: 0 | T45: 0 | U45: 0 | V45: 0 | W45: 0 | X45: 0 | Y45: 0 | Z45: 0 | AA45: 0 | AB45: 0 | AC45: Avenida Amélia Amado | AD45: Rua K | AE45: 18675.80 | AF45: 18885.46 | AG45: 0.27453704 | AH45: 0.19850694 | AI45: 0 | AJ45: 0 | AK45: 0 | AL45: 0 | AM45: N/A | AN45: 0 | AO45: 0 | AP45: 0 | AQ45: 0 | AR45: 0 | AS45: 0 | AT45: 0 | AU45: 0 | AV45: 0 | AW45: 0 | AX45: 0 | AY45: 0 | AZ45: 0 | BA45: 0 | BB45: 0 | BC45: 0 | BD45: 0 | BE45: 0 | BF45: 0 | BG45: 0 | BH45: 0 | BI45: 0 | BJ45: 0 | BK45: 0 | BM45: =IFERROR(VALUE(F45),"") -> 209.66 | BN45: =IF(R45="-","",IFERROR(VALUE(LEFT(Q45,LEN(Q45)-2)),"")) | BO45: =IF(R45="-","",IFERROR(VALUE(LEFT(R45,LEN(R45)-5)),"")) | BP45: =IF(R45="-","",IFERROR(VALUE(F45),"")) | BQ45: =IF(R45="-",1,0) -> 1
A46: JQI1377 | B46: R5515 | C46: ROTA TRANSPORTES - ITABUNA | E46: 46273 | F46: 0.00 | G46: 0 | H46: 0 | I46: 0 | J46: 0 | K46: 0 | L46: 0 | M46: 0 | N46: 0 | O46: 0 | P46: 0 | Q46: - | R46: - | S46: 0 | T46: 0 | U46: 0 | V46: 0 | W46: 0 | X46: 0 | Y46: 0 | Z46: 0 | AA46: 0 | AB46: 0 | AE46: - | AF46: - | AG46: 0 | AH46: 0 | AI46: 0 | AJ46: 1 | AK46: 0 | AL46: 0 | AM46: N/A | AN46: 0 | AO46: 0 | AP46: 0 | AQ46: 0 | AR46: 0 | AS46: 0 | AT46: 0 | AU46: 0 | AV46: 0 | AW46: 0 | AX46: 0 | AY46: 0 | AZ46: 0 | BA46: 0 | BB46: 0 | BC46: 0 | BD46: 0 | BE46: 0 | BF46: 0 | BG46: 0 | BH46: 0 | BI46: 0 | BJ46: 0 | BK46: 0 | BM46: =IFERROR(VALUE(F46),"") -> 0 | BN46: =IF(R46="-","",IFERROR(VALUE(LEFT(Q46,LEN(Q46)-2)),"")) | BO46: =IF(R46="-","",IFERROR(VALUE(LEFT(R46,LEN(R46)-5)),"")) | BP46: =IF(R46="-","",IFERROR(VALUE(F46),"")) | BQ46: =IF(R46="-",1,0) -> 1
A47: JQI1377 | B47: R5515 | C47: ROTA TRANSPORTES - ITABUNA | E47: 46274 | F47: 0.00 | G47: 0 | H47: 0 | I47: 0 | J47: 0 | K47: 0 | L47: 0 | M47: 0 | N47: 0 | O47: 0 | P47: 0 | Q47: - | R47: - | S47: 0 | T47: 0 | U47: 0 | V47: 0 | W47: 0 | X47: 0 | Y47: 0 | Z47: 0 | AA47: 0 | AB47: 0 | AE47: - | AF47: - | AG47: 0 | AH47: 0 | AI47: 0 | AJ47: 1 | AK47: 0 | AL47: 0 | AM47: N/A | AN47: 0 | AO47: 0 | AP47: 0 | AQ47: 0 | AR47: 0 | AS47: 0 | AT47: 0 | AU47: 0 | AV47: 0 | AW47: 0 | AX47: 0 | AY47: 0 | AZ47: 0 | BA47: 0 | BB47: 0 | BC47: 0 | BD47: 0 | BE47: 0 | BF47: 0 | BG47: 0 | BH47: 0 | BI47: 0 | BJ47: 0 | BK47: 0 | BM47: =IFERROR(VALUE(F47),"") -> 0 | BN47: =IF(R47="-","",IFERROR(VALUE(LEFT(Q47,LEN(Q47)-2)),"")) | BO47: =IF(R47="-","",IFERROR(VALUE(LEFT(R47,LEN(R47)-5)),"")) | BP47: =IF(R47="-","",IFERROR(VALUE(F47),"")) | BQ47: =IF(R47="-",1,0) -> 1
A48: JQI1377 | B48: R5515 | C48: ROTA TRANSPORTES - ITABUNA | E48: 46275 | F48: 0.00 | G48: 0 | H48: 0 | I48: 0 | J48: 0 | K48: 0 | L48: 0 | M48: 0 | N48: 0 | O48: 0 | P48: 0 | Q48: - | R48: - | S48: 0 | T48: 0 | U48: 0 | V48: 0 | W48: 0 | X48: 0 | Y48: 0 | Z48: 0 | AA48: 0 | AB48: 0 | AE48: - | AF48: - | AG48: 0 | AH48: 0 | AI48: 0 | AJ48: 1 | AK48: 0 | AL48: 0 | AM48: N/A | AN48: 0 | AO48: 0 | AP48: 0 | AQ48: 0 | AR48: 0 | AS48: 0 | AT48: 0 | AU48: 0 | AV48: 0 | AW48: 0 | AX48: 0 | AY48: 0 | AZ48: 0 | BA48: 0 | BB48: 0 | BC48: 0 | BD48: 0 | BE48: 0 | BF48: 0 | BG48: 0 | BH48: 0 | BI48: 0 | BJ48: 0 | BK48: 0 | BM48: =IFERROR(VALUE(F48),"") -> 0 | BN48: =IF(R48="-","",IFERROR(VALUE(LEFT(Q48,LEN(Q48)-2)),"")) | BO48: =IF(R48="-","",IFERROR(VALUE(LEFT(R48,LEN(R48)-5)),"")) | BP48: =IF(R48="-","",IFERROR(VALUE(F48),"")) | BQ48: =IF(R48="-",1,0) -> 1
A49: JQI1377 | B49: R5515 | C49: ROTA TRANSPORTES - ITABUNA | E49: 46276 | F49: 0.00 | G49: 0 | H49: 0 | I49: 0 | J49: 0 | K49: 0 | L49: 0 | M49: 0 | N49: 0 | O49: 0 | P49: 0 | Q49: - | R49: - | S49: 0 | T49: 0 | U49: 0 | V49: 0 | W49: 0 | X49: 0 | Y49: 0 | Z49: 0 | AA49: 0 | AB49: 0 | AE49: - | AF49: - | AG49: 0 | AH49: 0 | AI49: 0 | AJ49: 1 | AK49: 0 | AL49: 0 | AM49: N/A | AN49: 0 | AO49: 0 | AP49: 0 | AQ49: 0 | AR49: 0 | AS49: 0 | AT49: 0 | AU49: 0 | AV49: 0 | AW49: 0 | AX49: 0 | AY49: 0 | AZ49: 0 | BA49: 0 | BB49: 0 | BC49: 0 | BD49: 0 | BE49: 0 | BF49: 0 | BG49: 0 | BH49: 0 | BI49: 0 | BJ49: 0 | BK49: 0 | BM49: =IFERROR(VALUE(F49),"") -> 0 | BN49: =IF(R49="-","",IFERROR(VALUE(LEFT(Q49,LEN(Q49)-2)),"")) | BO49: =IF(R49="-","",IFERROR(VALUE(LEFT(R49,LEN(R49)-5)),"")) | BP49: =IF(R49="-","",IFERROR(VALUE(F49),"")) | BQ49: =IF(R49="-",1,0) -> 1
A50: JQI1377 | B50: R5515 | C50: ROTA TRANSPORTES - ITABUNA | E50: 46277 | F50: 0.00 | G50: 0 | H50: 0 | I50: 0 | J50: 0 | K50: 0 | L50: 0 | M50: 0 | N50: 0 | O50: 0 | P50: 0 | Q50: - | R50: - | S50: 0 | T50: 0 | U50: 0 | V50: 0 | W50: 0 | X50: 0 | Y50: 0 | Z50: 0 | AA50: 0 | AB50: 0 | AE50: - | AF50: - | AG50: 0 | AH50: 0 | AI50: 0 | AJ50: 1 | AK50: 0 | AL50: 0 | AM50: N/A | AN50: 0 | AO50: 0 | AP50: 0 | AQ50: 0 | AR50: 0 | AS50: 0 | AT50: 0 | AU50: 0 | AV50: 0 | AW50: 0 | AX50: 0 | AY50: 0 | AZ50: 0 | BA50: 0 | BB50: 0 | BC50: 0 | BD50: 0 | BE50: 0 | BF50: 0 | BG50: 0 | BH50: 0 | BI50: 0 | BJ50: 0 | BK50: 0 | BM50: =IFERROR(VALUE(F50),"") -> 0 | BN50: =IF(R50="-","",IFERROR(VALUE(LEFT(Q50,LEN(Q50)-2)),"")) | BO50: =IF(R50="-","",IFERROR(VALUE(LEFT(R50,LEN(R50)-5)),"")) | BP50: =IF(R50="-","",IFERROR(VALUE(F50),"")) | BQ50: =IF(R50="-",1,0) -> 1
A51: JQI1377 | B51: R5515 | C51: ROTA TRANSPORTES - ITABUNA | E51: 46278 | F51: 0.00 | G51: 0 | H51: 0 | I51: 0 | J51: 0 | K51: 0 | L51: 0 | M51: 0 | N51: 0 | O51: 0 | P51: 0 | Q51: - | R51: - | S51: 0 | T51: 0 | U51: 0 | V51: 0 | W51: 0 | X51: 0 | Y51: 0 | Z51: 0 | AA51: 0 | AB51: 0 | AE51: - | AF51: - | AG51: 0 | AH51: 0 | AI51: 0 | AJ51: 1 | AK51: 0 | AL51: 0 | AM51: N/A | AN51: 0 | AO51: 0 | AP51: 0 | AQ51: 0 | AR51: 0 | AS51: 0 | AT51: 0 | AU51: 0 | AV51: 0 | AW51: 0 | AX51: 0 | AY51: 0 | AZ51: 0 | BA51: 0 | BB51: 0 | BC51: 0 | BD51: 0 | BE51: 0 | BF51: 0 | BG51: 0 | BH51: 0 | BI51: 0 | BJ51: 0 | BK51: 0 | BM51: =IFERROR(VALUE(F51),"") -> 0 | BN51: =IF(R51="-","",IFERROR(VALUE(LEFT(Q51,LEN(Q51)-2)),"")) | BO51: =IF(R51="-","",IFERROR(VALUE(LEFT(R51,LEN(R51)-5)),"")) | BP51: =IF(R51="-","",IFERROR(VALUE(F51),"")) | BQ51: =IF(R51="-",1,0) -> 1
A52: JQI1377 | B52: R5515 | C52: ROTA TRANSPORTES - ITABUNA | E52: 46279 | F52: 0.00 | G52: 0 | H52: 0 | I52: 0 | J52: 0 | K52: 0 | L52: 0 | M52: 0 | N52: 0 | O52: 0 | P52: 0 | Q52: - | R52: - | S52: 0 | T52: 0 | U52: 0 | V52: 0 | W52: 0 | X52: 0 | Y52: 0 | Z52: 0 | AA52: 0 | AB52: 0 | AE52: - | AF52: - | AG52: 0 | AH52: 0 | AI52: 0 | AJ52: 1 | AK52: 0 | AL52: 0 | AM52: N/A | AN52: 0 | AO52: 0 | AP52: 0 | AQ52: 0 | AR52: 0 | AS52: 0 | AT52: 0 | AU52: 0 | AV52: 0 | AW52: 0 | AX52: 0 | AY52: 0 | AZ52: 0 | BA52: 0 | BB52: 0 | BC52: 0 | BD52: 0 | BE52: 0 | BF52: 0 | BG52: 0 | BH52: 0 | BI52: 0 | BJ52: 0 | BK52: 0 | BM52: =IFERROR(VALUE(F52),"") -> 0 | BN52: =IF(R52="-","",IFERROR(VALUE(LEFT(Q52,LEN(Q52)-2)),"")) | BO52: =IF(R52="-","",IFERROR(VALUE(LEFT(R52,LEN(R52)-5)),"")) | BP52: =IF(R52="-","",IFERROR(VALUE(F52),"")) | BQ52: =IF(R52="-",1,0) -> 1
A53: JQI1405 | B53: R5535 | C53: ROTA TRANSPORTES - ITABUNA | D53: Jose Adilson Dos Santos Reis - 02053767545, Jose Raimundo dos Santos - 00335224563, PAULO SERGIO MENEZES SANTOS - 01555946569, ABILIO SANTOS COUTINHO - 92884539549 | E53: 46273 | F53: 157.61 | G53: 0.31103009 | H53: 0.28283565 | I53: 0.00077546296 | J53: 1 | K53: 5 | L53: 0 | M53: 0 | N53: 0 | O53: 0 | P53: 0 | Q53: - | R53: - | S53: 0 | T53: 0 | U53: 0 | V53: 0 | W53: 0 | X53: 0 | Y53: 0 | Z53: 0 | AA53: 0 | AB53: 0 | AC53: Avenida Amélia Amado | AD53: Rua Castro Alves | AE53: 389488.70 | AF53: 389646.31 | AG53: 0.24534722 | AH53: 0.10199074 | AI53: 0 | AJ53: 0 | AK53: 0 | AL53: 0 | AM53: N/A | AN53: 0 | AO53: 0 | AP53: 0 | AQ53: 0 | AR53: 0 | AS53: 0 | AT53: 0 | AU53: 6 | AV53: 0 | AW53: 0 | AX53: 0 | AY53: 0 | AZ53: 0 | BA53: 0 | BB53: 0 | BC53: 0 | BD53: 0 | BE53: 0 | BF53: 0 | BG53: 0 | BH53: 0 | BI53: 0 | BJ53: 0 | BK53: 0 | BM53: =IFERROR(VALUE(F53),"") -> 157.61 | BN53: =IF(R53="-","",IFERROR(VALUE(LEFT(Q53,LEN(Q53)-2)),"")) | BO53: =IF(R53="-","",IFERROR(VALUE(LEFT(R53,LEN(R53)-5)),"")) | BP53: =IF(R53="-","",IFERROR(VALUE(F53),"")) | BQ53: =IF(R53="-",1,0) -> 1
A54: JQI1405 | B54: R5535 | C54: ROTA TRANSPORTES - ITABUNA | D54: Jose Adilson Dos Santos Reis - 02053767545, RAFAEL DE JESUS BARRETO - 85830111500, PAULO SERGIO MENEZES SANTOS - 01555946569, CLODOALDO DOS SANTOS PINHEIRO - 00832134570 | E54: 46274 | F54: 271.38 | G54: 0.50534722 | H54: 0.49862269 | I54: 0.00045138889 | J54: 1 | K54: 0 | L54: 0 | M54: 0 | N54: 0 | O54: 0 | P54: 0 | Q54: - | R54: - | S54: 0 | T54: 0 | U54: 0 | V54: 0 | W54: 0 | X54: 0 | Y54: 0 | Z54: 0 | AA54: 0 | AB54: 0 | AC54: Rua K | AD54: Avenida Amélia Amado | AE54: 389646.31 | AF54: 389917.69 | AG54: 0.42402778 | AH54: 0.11854167 | AI54: 1.1574074e-05 | AJ54: 0 | AK54: 0 | AL54: 0 | AM54: N/A | AN54: 0 | AO54: 0 | AP54: 0 | AQ54: 0 | AR54: 0 | AS54: 0 | AT54: 0 | AU54: 15 | AV54: 0 | AW54: 0 | AX54: 0 | AY54: 0 | AZ54: 0 | BA54: 0 | BB54: 0 | BC54: 0 | BD54: 0 | BE54: 0 | BF54: 0 | BG54: 0 | BH54: 0 | BI54: 0 | BJ54: 0 | BK54: 0 | BM54: =IFERROR(VALUE(F54),"") -> 271.38 | BN54: =IF(R54="-","",IFERROR(VALUE(LEFT(Q54,LEN(Q54)-2)),"")) | BO54: =IF(R54="-","",IFERROR(VALUE(LEFT(R54,LEN(R54)-5)),"")) | BP54: =IF(R54="-","",IFERROR(VALUE(F54),"")) | BQ54: =IF(R54="-",1,0) -> 1
A55: JQI1405 | B55: R5535 | C55: ROTA TRANSPORTES - ITABUNA | D55: Jose Adilson Dos Santos Reis - 02053767545, PAULO SERGIO MENEZES SANTOS - 01555946569 | E55: 46275 | F55: 67.09 | G55: 0.26454861 | H55: 0.10994213 | I55: 0.00024305556 | J55: 0 | K55: 0 | L55: 0 | M55: 0 | N55: 0 | O55: 0 | P55: 0 | Q55: - | R55: - | S55: 0 | T55: 0 | U55: 0 | V55: 0 | W55: 0 | X55: 0 | Y55: 0 | Z55: 0 | AA55: 0 | AB55: 0 | AC55: Avenida Amélia Amado | AD55: Rua João Franco | AE55: 389917.69 | AF55: 389984.78 | AG55: 0.100625 | AH55: 0.30355324 | AI55: 2.3148148e-05 | AJ55: 0 | AK55: 0 | AL55: 0 | AM55: N/A | AN55: 0 | AO55: 0 | AP55: 0 | AQ55: 0 | AR55: 0 | AS55: 0 | AT55: 0 | AU55: 0 | AV55: 0 | AW55: 0 | AX55: 0 | AY55: 0 | AZ55: 0 | BA55: 0 | BB55: 0 | BC55: 0 | BD55: 0 | BE55: 0 | BF55: 0 | BG55: 0 | BH55: 0 | BI55: 0 | BJ55: 0 | BK55: 0 | BM55: =IFERROR(VALUE(F55),"") -> 67.09 | BN55: =IF(R55="-","",IFERROR(VALUE(LEFT(Q55,LEN(Q55)-2)),"")) | BO55: =IF(R55="-","",IFERROR(VALUE(LEFT(R55,LEN(R55)-5)),"")) | BP55: =IF(R55="-","",IFERROR(VALUE(F55),"")) | BQ55: =IF(R55="-",1,0) -> 1
A56: JQI1405 | B56: R5535 | C56: ROTA TRANSPORTES - ITABUNA | D56: Jose Adilson Dos Santos Reis - 02053767545, PAULO SERGIO MENEZES SANTOS - 01555946569, WILLIAN JOSE DA CUNHA - 03523954517 | E56: 46276 | F56: 261.94 | G56: 0.5055787 | H56: 0.46508102 | I56: 0.0009375 | J56: 0 | K56: 2 | L56: 0 | M56: 0 | N56: 0 | O56: 0 | P56: 0 | Q56: - | R56: - | S56: 0 | T56: 0 | U56: 0 | V56: 0 | W56: 0 | X56: 0 | Y56: 0 | Z56: 0 | AA56: 0 | AB56: 0 | AC56: Rua K | AD56: Rua K | AE56: 389984.78 | AF56: 390246.72 | AG56: 0.39334491 | AH56: 0.19789352 | AI56: 1.1574074e-05 | AJ56: 0 | AK56: 0 | AL56: 0 | AM56: N/A | AN56: 0 | AO56: 1 | AP56: 0 | AQ56: 1 | AR56: 0 | AS56: 0 | AT56: 0 | AU56: 13 | AV56: 0 | AW56: 0 | AX56: 0 | AY56: 0 | AZ56: 0 | BA56: 0 | BB56: 0 | BC56: 0 | BD56: 0 | BE56: 0 | BF56: 0 | BG56: 0 | BH56: 0 | BI56: 0 | BJ56: 0 | BK56: 0 | BM56: =IFERROR(VALUE(F56),"") -> 261.94 | BN56: =IF(R56="-","",IFERROR(VALUE(LEFT(Q56,LEN(Q56)-2)),"")) | BO56: =IF(R56="-","",IFERROR(VALUE(LEFT(R56,LEN(R56)-5)),"")) | BP56: =IF(R56="-","",IFERROR(VALUE(F56),"")) | BQ56: =IF(R56="-",1,0) -> 1
A57: JQI1405 | B57: R5535 | C57: ROTA TRANSPORTES - ITABUNA | D57: WILLIAN JOSE DA CUNHA - 03523954517 | E57: 46277 | F57: 31.40 | G57: 0.097303241 | H57: 0.07025463 | I57: 0.00012731481 | J57: 0 | K57: 0 | L57: 0 | M57: 0 | N57: 0 | O57: 0 | P57: 0 | Q57: - | R57: - | S57: 0 | T57: 0 | U57: 0 | V57: 0 | W57: 0 | X57: 0 | Y57: 0 | Z57: 0 | AA57: 0 | AB57: 0 | AC57: Rua João Franco | AD57: Avenida Amélia Amado | AE57: 390246.72 | AF57: 390278.12 | AG57: 0.05912037 | AH57: 0.058171296 | AI57: 1.1574074e-05 | AJ57: 0 | AK57: 0 | AL57: 0 | AM57: N/A | AN57: 0 | AO57: 0 | AP57: 0 | AQ57: 0 | AR57: 0 | AS57: 0 | AT57: 0 | AU57: 3 | AV57: 0 | AW57: 1 | AX57: 0 | AY57: 0 | AZ57: 0 | BA57: 0 | BB57: 0 | BC57: 0 | BD57: 0 | BE57: 0 | BF57: 0 | BG57: 0 | BH57: 0 | BI57: 0 | BJ57: 0 | BK57: 0 | BM57: =IFERROR(VALUE(F57),"") -> 31.4 | BN57: =IF(R57="-","",IFERROR(VALUE(LEFT(Q57,LEN(Q57)-2)),"")) | BO57: =IF(R57="-","",IFERROR(VALUE(LEFT(R57,LEN(R57)-5)),"")) | BP57: =IF(R57="-","",IFERROR(VALUE(F57),"")) | BQ57: =IF(R57="-",1,0) -> 1
A58: JQI1405 | B58: R5535 | C58: ROTA TRANSPORTES - ITABUNA | D58: Jose Adilson Dos Santos Reis - 02053767545 | E58: 46278 | F58: 156.92 | G58: 0.2631713 | H58: 0.25304398 | I58: 0.00054398148 | J58: 0 | K58: 5 | L58: 0 | M58: 0 | N58: 2 | O58: 0 | P58: 0 | Q58: - | R58: - | S58: 0 | T58: 0 | U58: 0 | V58: 0 | W58: 0 | X58: 0 | Y58: 0 | Z58: 0 | AA58: 0 | AB58: 0 | AC58: Avenida Amélia Amado | AD58: Avenida Amélia Amado | AE58: 390278.12 | AF58: 390435.04 | AG58: 0.2278125 | AH58: 0.076388889 | AI58: 0 | AJ58: 0 | AK58: 0 | AL58: 0 | AM58: N/A | AN58: 0 | AO58: 1 | AP58: 0 | AQ58: 0 | AR58: 0 | AS58: 0 | AT58: 0 | AU58: 3 | AV58: 0 | AW58: 0 | AX58: 0 | AY58: 0 | AZ58: 0 | BA58: 0 | BB58: 0 | BC58: 0 | BD58: 0 | BE58: 0 | BF58: 0 | BG58: 0 | BH58: 0 | BI58: 0 | BJ58: 0 | BK58: 0 | BM58: =IFERROR(VALUE(F58),"") -> 156.92 | BN58: =IF(R58="-","",IFERROR(VALUE(LEFT(Q58,LEN(Q58)-2)),"")) | BO58: =IF(R58="-","",IFERROR(VALUE(LEFT(R58,LEN(R58)-5)),"")) | BP58: =IF(R58="-","",IFERROR(VALUE(F58),"")) | BQ58: =IF(R58="-",1,0) -> 1
A59: JQI1405 | B59: R5535 | C59: ROTA TRANSPORTES - ITABUNA | D59: Jose Adilson Dos Santos Reis - 02053767545, MARCOS FILIPE LIMA DE OLIVEIRA - 85262714587, JUCIMAR DE JESUS SANTOS - 03136869559, JOSE MAURICIO SANTANA SANTOS - 97382388549, CARLISSON MESSIAS DE JESUS - 04199062580 | E59: 46279 | F59: 246.62 | G59: 0.44337963 | H59: 0.26704861 | I59: 0.00076388889 | J59: 0 | K59: 3 | L59: 0 | M59: 0 | N59: 0 | O59: 0 | P59: 0 | Q59: - | R59: - | S59: 0 | T59: 0 | U59: 0 | V59: 0 | W59: 0 | X59: 0 | Y59: 0 | Z59: 0 | AA59: 0 | AB59: 0 | AC59: Rua Castro Alves | AD59: Rua Castro Alves | AE59: 390435.04 | AF59: 390681.66 | AG59: 0.35071759 | AH59: 0.24217593 | AI59: 1.1574074e-05 | AJ59: 0 | AK59: 0 | AL59: 0 | AM59: N/A | AN59: 0 | AO59: 1 | AP59: 0 | AQ59: 0 | AR59: 0 | AS59: 0 | AT59: 0 | AU59: 6 | AV59: 0 | AW59: 0 | AX59: 0 | AY59: 0 | AZ59: 0 | BA59: 0 | BB59: 0 | BC59: 0 | BD59: 0 | BE59: 0 | BF59: 0 | BG59: 0 | BH59: 0 | BI59: 0 | BJ59: 0 | BK59: 0 | BM59: =IFERROR(VALUE(F59),"") -> 246.62 | BN59: =IF(R59="-","",IFERROR(VALUE(LEFT(Q59,LEN(Q59)-2)),"")) | BO59: =IF(R59="-","",IFERROR(VALUE(LEFT(R59,LEN(R59)-5)),"")) | BP59: =IF(R59="-","",IFERROR(VALUE(F59),"")) | BQ59: =IF(R59="-",1,0) -> 1
A60: OUR3707 | B60: R7125 | C60: ROTA TRANSPORTES - ITABUNA | D60: Jose Raimundo dos Santos - 00335224563, VALMIR JOSE DOS SANTOS - 42008476553, Samuel Brito dos Santos - 86013174563 | E60: 46273 | F60: 320.69 | G60: 0.58956019 | H60: 0.5537963 | I60: 0.00019675926 | J60: 0 | K60: 0 | L60: 0 | M60: 0 | N60: 0 | O60: 0 | P60: 0.014270833 | Q60: 130.65 L | R60: 2.45 Km/L | S60: 0.00023148148 | T60: 0.30023148 | U60: 0.24340278 | V60: 0.018981481 | W60: 0 | X60: 0 | Y60: 0 | Z60: 0 | AA60: 0 | AB60: 0 | AC60: Avenida Amélia Amado | AD60: Rua K | AE60: 938144.59 | AF60: 938465.28 | AG60: 0.47626157 | AH60: 0.17434028 | AI60: 0 | AJ60: 0 | AK60: 0 | AL60: 0 | AM60: N/A | AN60: 0 | AO60: 0 | AP60: 0 | AQ60: 0 | AR60: 0 | AS60: 0 | AT60: 0 | AU60: 20 | AV60: 0 | AW60: 0 | AX60: 0 | AY60: 0 | AZ60: 0 | BA60: 0 | BB60: 0 | BC60: 0 | BD60: 0 | BE60: 0 | BF60: 0 | BG60: 0 | BH60: 0 | BI60: 0 | BJ60: 0 | BK60: 0 | BM60: =IFERROR(VALUE(F60),"") -> 320.69 | BN60: =IF(R60="-","",IFERROR(VALUE(LEFT(Q60,LEN(Q60)-2)),"")) -> 130.65 | BO60: =IF(R60="-","",IFERROR(VALUE(LEFT(R60,LEN(R60)-5)),"")) -> 2.45 | BP60: =IF(R60="-","",IFERROR(VALUE(F60),"")) -> 320.69 | BQ60: =IF(R60="-",1,0) -> 0
A61: OUR3707 | B61: R7125 | C61: ROTA TRANSPORTES - ITABUNA | D61: Samuel Brito dos Santos - 86013174563, JEREMIAS DO SANTOS GALIZA - 82787654568 | E61: 46274 | F61: 321.54 | G61: 0.56054398 | H61: 0.53173611 | I61: 0.00023148148 | J61: 0 | K61: 0 | L61: 0 | M61: 0 | N61: 3 | O61: 0 | P61: 0 | Q61: 128.62 L | R61: 2.50 Km/L | S61: 0.00034722222 | T61: 0.27303241 | U61: 0.2380787 | V61: 0.021643519 | W61: 0 | X61: 0 | Y61: 0 | Z61: 0 | AA61: 0 | AB61: 0 | AC61: Rua Castro Alves | AD61: Rua K | AE61: 938465.28 | AF61: 938786.81 | AG61: 0.47115741 | AH61: 0.17758102 | AI61: 0 | AJ61: 0 | AK61: 0 | AL61: 0 | AM61: N/A | AN61: 0 | AO61: 1 | AP61: 0 | AQ61: 0 | AR61: 0 | AS61: 2 | AT61: 0 | AU61: 14 | AV61: 0 | AW61: 0 | AX61: 0 | AY61: 0 | AZ61: 0 | BA61: 0 | BB61: 0 | BC61: 0 | BD61: 0 | BE61: 0 | BF61: 0 | BG61: 0 | BH61: 0 | BI61: 0 | BJ61: 0 | BK61: 0 | BM61: =IFERROR(VALUE(F61),"") -> 321.54 | BN61: =IF(R61="-","",IFERROR(VALUE(LEFT(Q61,LEN(Q61)-2)),"")) -> 128.62 | BO61: =IF(R61="-","",IFERROR(VALUE(LEFT(R61,LEN(R61)-5)),"")) -> 2.5 | BP61: =IF(R61="-","",IFERROR(VALUE(F61),"")) -> 321.54 | BQ61: =IF(R61="-",1,0) -> 0
A62: OUR3707 | B62: R7125 | C62: ROTA TRANSPORTES - ITABUNA | D62: ANTONIO MAXIMO SANTOS SOUSA - 04634408546, VALMIR JOSE DOS SANTOS - 42008476553, Samuel Brito dos Santos - 86013174563 | E62: 46275 | F62: 321.04 | G62: 0.60466435 | H62: 0.52123843 | I62: 0.00055555556 | J62: 0 | K62: 0 | L62: 0 | M62: 0 | N62: 1 | O62: 0 | P62: 0.075 | Q62: 134.91 L | R62: 2.38 Km/L | S62: 0.00034722222 | T62: 0.33622685 | U62: 0.23935185 | V62: 0.020601852 | W62: 0 | X62: 0 | Y62: 0 | Z62: 0 | AA62: 0 | AB62: 0 | AC62: Rua K | AD62: Rua K | AE62: 938786.81 | AF62: 939107.85 | AG62: 0.45431713 | AH62: 0.21769676 | AI62: 0 | AJ62: 0 | AK62: 0 | AL62: 0 | AM62: N/A | AN62: 0 | AO62: 2 | AP62: 0 | AQ62: 0 | AR62: 1 | AS62: 0 | AT62: 0 | AU62: 10 | AV62: 0 | AW62: 0 | AX62: 0 | AY62: 0 | AZ62: 0 | BA62: 0 | BB62: 0 | BC62: 0 | BD62: 0 | BE62: 0 | BF62: 0 | BG62: 0 | BH62: 0 | BI62: 0 | BJ62: 0 | BK62: 0 | BM62: =IFERROR(VALUE(F62),"") -> 321.04 | BN62: =IF(R62="-","",IFERROR(VALUE(LEFT(Q62,LEN(Q62)-2)),"")) -> 134.91 | BO62: =IF(R62="-","",IFERROR(VALUE(LEFT(R62,LEN(R62)-5)),"")) -> 2.38 | BP62: =IF(R62="-","",IFERROR(VALUE(F62),"")) -> 321.04 | BQ62: =IF(R62="-",1,0) -> 0
A63: OUR3707 | B63: R7125 | C63: ROTA TRANSPORTES - ITABUNA | D63: VALMIR JOSE DOS SANTOS - 42008476553, Samuel Brito dos Santos - 86013174563 | E63: 46276 | F63: 321.26 | G63: 0.46197917 | H63: 0.43533565 | I63: 0.00053240741 | J63: 0 | K63: 0 | L63: 0 | M63: 0 | N63: 1 | O63: 0 | P63: 0.007349537 | Q63: 107.47 L | R63: 2.99 Km/L | S63: 0.00046296296 | T63: 0.23032407 | U63: 0.20162037 | V63: 0.012731481 | W63: 0 | X63: 0 | Y63: 0 | Z63: 0 | AA63: 0 | AB63: 0 | AC63: Avenida Amélia Amado | AD63: Avenida Amélia Amado | AE63: 939107.85 | AF63: 939429.10 | AG63: 0.38762731 | AH63: 0.1752662 | AI63: 0 | AJ63: 0 | AK63: 0 | AL63: 0 | AM63: N/A | AN63: 0 | AO63: 0 | AP63: 0 | AQ63: 0 | AR63: 1 | AS63: 0 | AT63: 0 | AU63: 9 | AV63: 0 | AW63: 0 | AX63: 0 | AY63: 0 | AZ63: 0 | BA63: 0 | BB63: 0 | BC63: 0 | BD63: 0 | BE63: 0 | BF63: 0 | BG63: 0 | BH63: 0 | BI63: 0 | BJ63: 0 | BK63: 0 | BM63: =IFERROR(VALUE(F63),"") -> 321.26 | BN63: =IF(R63="-","",IFERROR(VALUE(LEFT(Q63,LEN(Q63)-2)),"")) -> 107.47 | BO63: =IF(R63="-","",IFERROR(VALUE(LEFT(R63,LEN(R63)-5)),"")) -> 2.99 | BP63: =IF(R63="-","",IFERROR(VALUE(F63),"")) -> 321.26 | BQ63: =IF(R63="-",1,0) -> 0
A64: OUR3707 | B64: R7125 | C64: ROTA TRANSPORTES - ITABUNA | D64: Jose Raimundo dos Santos - 00335224563, VALMIR JOSE DOS SANTOS - 42008476553, JEREMIAS DO SANTOS GALIZA - 82787654568, EMERSON ANDRADE DA SILVA - 96170824549 | E64: 46277 | F64: 321.81 | G64: 0.58118056 | H64: 0.57701389 | I64: 0.00024305556 | J64: 0 | K64: 1 | L64: 0 | M64: 0 | N64: 1 | O64: 0 | P64: 0.010671296 | Q64: 128.29 L | R64: 2.51 Km/L | S64: 0.00023148148 | T64: 0.2962963 | U64: 0.25532407 | V64: 0.0078703704 | W64: 0 | X64: 0 | Y64: 0 | Z64: 0 | AA64: 0 | AB64: 0 | AC64: Rua K | AD64: Avenida Amélia Amado | AE64: 939429.10 | AF64: 939750.91 | AG64: 0.46552083 | AH64: 0.21015046 | AI64: 0 | AJ64: 0 | AK64: 0 | AL64: 0 | AM64: N/A | AN64: 0 | AO64: 1 | AP64: 0 | AQ64: 0 | AR64: 0 | AS64: 0 | AT64: 0 | AU64: 27 | AV64: 0 | AW64: 0 | AX64: 0 | AY64: 0 | AZ64: 0 | BA64: 0 | BB64: 0 | BC64: 0 | BD64: 0 | BE64: 0 | BF64: 0 | BG64: 0 | BH64: 0 | BI64: 0 | BJ64: 0 | BK64: 0 | BM64: =IFERROR(VALUE(F64),"") -> 321.81 | BN64: =IF(R64="-","",IFERROR(VALUE(LEFT(Q64,LEN(Q64)-2)),"")) -> 128.29 | BO64: =IF(R64="-","",IFERROR(VALUE(LEFT(R64,LEN(R64)-5)),"")) -> 2.51 | BP64: =IF(R64="-","",IFERROR(VALUE(F64),"")) -> 321.81 | BQ64: =IF(R64="-",1,0) -> 0
... A72: OUR8713 | B72: R7135 | C72: ROTA TRANSPORTES - ITABUNA | D72: JONE MARTINS DOS SANTOS - 01306290570 | E72: 46279 | F72: 307.92 | G72: 0.43077546 | H72: 0.40615741 | I72: 0 | J72: 0 | K72: 0 | L72: 0 | M72: 0 | N72: 4 | O72: 0 | P72: 0.0071759259 | Q72: 107.04 L | R72: 2.88 Km/L | S72: 0.00011574074 | T72: 0.19652778 | U72: 0.20520833 | V72: 0.015046296 | W72: 0 | X72: 0 | Y72: 0 | Z72: 0 | AA72: 0 | AB72: 0 | AC72: Largo da Rodoviária | AD72: Largo da Rodoviária | AE72: 253932.37 | AF72: 254240.28 | AG72: 0.36333333 | AH72: 0.10512731 | AI72: 0 | AJ72: 0 | AK72: 0 | AL72: 0 | AM72: N/A | AN72: 0 | AO72: 0 | AP72: 0 | AQ72: 0 | AR72: 0 | AS72: 0 | AT72: 0 | AU72: 6 | AV72: 0 | AW72: 0 | AX72: 0 | AY72: 0 | AZ72: 0 | BA72: 0 | BB72: 0 | BC72: 0 | BD72: 0 | BE72: 0 | BF72: 0 | BG72: 0 | BH72: 0 | BI72: 0 | BJ72: 0 | BK72: 0 | BM72: =IFERROR(VALUE(F72),"") -> 307.92 | BN72: =IF(R72="-","",IFERROR(VALUE(LEFT(Q72,LEN(Q72)-2)),"")) -> 107.04 | BO72: =IF(R72="-","",IFERROR(VALUE(LEFT(R72,LEN(R72)-5)),"")) -> 2.88 | BP72: =IF(R72="-","",IFERROR(VALUE(F72),"")) -> 307.92 | BQ72: =IF(R72="-",1,0) -> 0
A73: OUR9200 | B73: R7145 | C73: ROTA TRANSPORTES - ITABUNA | E73: 46273 | F73: 301.27 | G73: 0.49020833 | H73: 0 | I73: 0 | J73: 0 | K73: 0 | L73: 0 | M73: 0 | N73: 1 | O73: 0 | P73: 0.011712963 | Q73: 101.64 L | R73: 2.96 Km/L | S73: 0.00011574074 | T73: 0.26435185 | U73: 0.21157407 | V73: 0.0068287037 | W73: 0 | X73: 0 | Y73: 0 | Z73: 0 | AA73: 0 | AB73: 0 | AC73: Avenida Deraldo Peixoto de Araújo | AD73: Avenida Deraldo Peixoto de Araújo | AE73: 1126613.92 | AF73: 1126915.19 | AG73: 0.38269676 | AH73: 0.15556713 | AI73: 0 | AJ73: 0 | AK73: 0 | AL73: 0 | AM73: N/A | AN73: 0 | AO73: 0 | AP73: 0 | AQ73: 0 | AR73: 0 | AS73: 0 | AT73: 0 | AU73: 2 | AV73: 0 | AW73: 0 | AX73: 0 | AY73: 0 | AZ73: 0 | BA73: 0 | BB73: 0 | BC73: 0 | BD73: 0 | BE73: 0 | BF73: 0 | BG73: 0 | BH73: 0 | BI73: 0 | BJ73: 0 | BK73: 0 | BM73: =IFERROR(VALUE(F73),"") -> 301.27 | BN73: =IF(R73="-","",IFERROR(VALUE(LEFT(Q73,LEN(Q73)-2)),"")) -> 101.64 | BO73: =IF(R73="-","",IFERROR(VALUE(LEFT(R73,LEN(R73)-5)),"")) -> 2.96 | BP73: =IF(R73="-","",IFERROR(VALUE(F73),"")) -> 301.27 | BQ73: =IF(R73="-",1,0) -> 0
A74: OUR9200 | B74: R7145 | C74: ROTA TRANSPORTES - ITABUNA | E74: 46274 | F74: 301.52 | G74: 0.45251157 | H74: 0 | I74: 1.1574074e-05 | J74: 0 | K74: 0 | L74: 0 | M74: 0 | N74: 1 | O74: 0 | P74: 0 | Q74: 95.91 L | R74: 3.14 Km/L | S74: 0.00023148148 | T74: 0.23252315 | U74: 0.20833333 | V74: 0.0056712963 | W74: 0 | X74: 0 | Y74: 0 | Z74: 0 | AA74: 0 | AB74: 0 | AC74: Avenida Deraldo Peixoto de Araújo | AD74: Avenida Deraldo Peixoto de Araújo | AE74: 1126915.19 | AF74: 1127216.71 | AG74: 0.38017361 | AH74: 0.13520833 | AI74: 0 | AJ74: 0 | AK74: 0 | AL74: 0 | AM74: N/A | AN74: 0 | AO74: 0 | AP74: 0 | AQ74: 0 | AR74: 0 | AS74: 0 | AT74: 0 | AU74: 3 | AV74: 0 | AW74: 0 | AX74: 0 | AY74: 0 | AZ74: 0 | BA74: 0 | BB74: 0 | BC74: 0 | BD74: 0 | BE74: 0 | BF74: 0 | BG74: 0 | BH74: 0 | BI74: 0 | BJ74: 0 | BK74: 0 | BM74: =IFERROR(VALUE(F74),"") -> 301.52 | BN74: =IF(R74="-","",IFERROR(VALUE(LEFT(Q74,LEN(Q74)-2)),"")) -> 95.91 | BO74: =IF(R74="-","",IFERROR(VALUE(LEFT(R74,LEN(R74)-5)),"")) -> 3.14 | BP74: =IF(R74="-","",IFERROR(VALUE(F74),"")) -> 301.52 | BQ74: =IF(R74="-",1,0) -> 0
A75: OUR9200 | B75: R7145 | C75: ROTA TRANSPORTES - ITABUNA | E75: 46275 | F75: 302.01 | G75: 0.44505787 | H75: 0 | I75: 1.1574074e-05 | J75: 0 | K75: 0 | L75: 0 | M75: 0 | N75: 1 | O75: 0 | P75: 0 | Q75: 94.77 L | R75: 3.19 Km/L | S75: 0.00011574074 | T75: 0.22858796 | U75: 0.19872685 | V75: 0.0082175926 | W75: 0 | X75: 0 | Y75: 0 | Z75: 0 | AA75: 0 | AB75: 0 | AC75: Avenida Deraldo Peixoto de Araújo | AD75: Avenida Deraldo Peixoto de Araújo | AE75: 1127216.71 | AF75: 1127518.20 | AG75: 0.36409722 | AH75: 0.14413194 | AI75: 0 | AJ75: 0 | AK75: 0 | AL75: 0 | AM75: N/A | AN75: 0 | AO75: 0 | AP75: 0 | AQ75: 0 | AR75: 0 | AS75: 0 | AT75: 0 | AU75: 0 | AV75: 0 | AW75: 0 | AX75: 0 | AY75: 0 | AZ75: 0 | BA75: 0 | BB75: 0 | BC75: 0 | BD75: 0 | BE75: 0 | BF75: 0 | BG75: 0 | BH75: 0 | BI75: 0 | BJ75: 0 | BK75: 0 | BM75: =IFERROR(VALUE(F75),"") -> 302.01 | BN75: =IF(R75="-","",IFERROR(VALUE(LEFT(Q75,LEN(Q75)-2)),"")) -> 94.77 | BO75: =IF(R75="-","",IFERROR(VALUE(LEFT(R75,LEN(R75)-5)),"")) -> 3.19 | BP75: =IF(R75="-","",IFERROR(VALUE(F75),"")) -> 302.01 | BQ75: =IF(R75="-",1,0) -> 0
A76: OUR9200 | B76: R7145 | C76: ROTA TRANSPORTES - ITABUNA | D76: PAULO ROMA PINTO - 02932759558 | E76: 46276 | F76: 301.47 | G76: 0.44391204 | H76: 0.38997685 | I76: 6.9444444e-05 | J76: 0 | K76: 0 | L76: 0 | M76: 0 | N76: 3 | O76: 0 | P76: 0.0086921296 | Q76: 96.49 L | R76: 3.12 Km/L | S76: 0.00023148148 | T76: 0.22824074 | U76: 0.18784722 | V76: 0.011111111 | W76: 0 | X76: 0 | Y76: 0 | Z76: 0 | AA76: 0 | AB76: 0 | AC76: Avenida Deraldo Peixoto de Araújo | AD76: Avenida Deraldo Peixoto de Araújo | AE76: 1127518.20 | AF76: 1127819.66 | AG76: 0.37287037 | AH76: 0.1371412 | AI76: 0 | AJ76: 0 | AK76: 0 | AL76: 0 | AM76: N/A | AN76: 0 | AO76: 0 | AP76: 0 | AQ76: 0 | AR76: 0 | AS76: 0 | AT76: 0 | AU76: 1 | AV76: 0 | AW76: 0 | AX76: 0 | AY76: 0 | AZ76: 0 | BA76: 0 | BB76: 0 | BC76: 0 | BD76: 0 | BE76: 0 | BF76: 0 | BG76: 0 | BH76: 0 | BI76: 0 | BJ76: 0 | BK76: 0 | BM76: =IFERROR(VALUE(F76),"") -> 301.47 | BN76: =IF(R76="-","",IFERROR(VALUE(LEFT(Q76,LEN(Q76)-2)),"")) -> 96.49 | BO76: =IF(R76="-","",IFERROR(VALUE(LEFT(R76,LEN(R76)-5)),"")) -> 3.12 | BP76: =IF(R76="-","",IFERROR(VALUE(F76),"")) -> 301.47 | BQ76: =IF(R76="-",1,0) -> 0
A77: OUR9200 | B77: R7145 | C77: ROTA TRANSPORTES - ITABUNA | D77: PAULO ROMA PINTO - 02932759558 | E77: 46277 | F77: 301.99 | G77: 0.42847222 | H77: 0.41461806 | I77: 9.2592593e-05 | J77: 0 | K77: 0 | L77: 0 | M77: 0 | N77: 0 | O77: 0 | P77: 0.0072569444 | Q77: 94.45 L | R77: 3.20 Km/L | S77: 0.00034722222 | T77: 0.21539352 | U77: 0.18449074 | V77: 0.013078704 | W77: 0 | X77: 0 | Y77: 0 | Z77: 0 | AA77: 0 | AB77: 0 | AC77: Avenida Deraldo Peixoto de Araújo | AD77: Avenida Deraldo Peixoto de Araújo | AE77: 1127819.66 | AF77: 1128121.65 | AG77: 0.35497685 | AH77: 0.11108796 | AI77: 0 | AJ77: 0 | AK77: 0 | AL77: 0 | AM77: N/A | AN77: 0 | AO77: 0 | AP77: 0 | AQ77: 0 | AR77: 0 | AS77: 0 | AT77: 0 | AU77: 2 | AV77: 0 | AW77: 0 | AX77: 0 | AY77: 0 | AZ77: 0 | BA77: 0 | BB77: 0 | BC77: 0 | BD77: 0 | BE77: 0 | BF77: 0 | BG77: 0 | BH77: 0 | BI77: 0 | BJ77: 0 | BK77: 0 | BM77: =IFERROR(VALUE(F77),"") -> 301.99 | BN77: =IF(R77="-","",IFERROR(VALUE(LEFT(Q77,LEN(Q77)-2)),"")) -> 94.45 | BO77: =IF(R77="-","",IFERROR(VALUE(LEFT(R77,LEN(R77)-5)),"")) -> 3.2 | BP77: =IF(R77="-","",IFERROR(VALUE(F77),"")) -> 301.99 | BQ77: =IF(R77="-",1,0) -> 0
A78: OUR9200 | B78: R7145 | C78: ROTA TRANSPORTES - ITABUNA | E78: 46278 | F78: 299.02 | G78: 0.42047454 | H78: 0 | I78: 5.787037e-05 | J78: 0 | K78: 0 | L78: 0 | M78: 0 | N78: 3 | O78: 0 | P78: 0 | Q78: 96.78 L | R78: 3.09 Km/L | S78: 0.00069444444 | T78: 0.2056713 | U78: 0.19421296 | V78: 0.013425926 | W78: 0 | X78: 0 | Y78: 0 | Z78: 0 | AA78: 0 | AB78: 0 | AC78: Avenida Deraldo Peixoto de Araújo | AD78: Avenida Deraldo Peixoto de Araújo | AE78: 1128121.65 | AF78: 1128420.66 | AG78: 0.34866898 | AH78: 0.13729167 | AI78: 0 | AJ78: 0 | AK78: 0 | AL78: 0 | AM78: N/A | AN78: 0 | AO78: 0 | AP78: 0 | AQ78: 0 | AR78: 0 | AS78: 0 | AT78: 0 | AU78: 0 | AV78: 0 | AW78: 0 | AX78: 0 | AY78: 0 | AZ78: 0 | BA78: 0 | BB78: 0 | BC78: 0 | BD78: 0 | BE78: 0 | BF78: 0 | BG78: 0 | BH78: 0 | BI78: 0 | BJ78: 0 | BK78: 0 | BM78: =IFERROR(VALUE(F78),"") -> 299.02 | BN78: =IF(R78="-","",IFERROR(VALUE(LEFT(Q78,LEN(Q78)-2)),"")) -> 96.78 | BO78: =IF(R78="-","",IFERROR(VALUE(LEFT(R78,LEN(R78)-5)),"")) -> 3.09 | BP78: =IF(R78="-","",IFERROR(VALUE(F78),"")) -> 299.02 | BQ78: =IF(R78="-",1,0) -> 0
A79: OUR9200 | B79: R7145 | C79: ROTA TRANSPORTES - ITABUNA | E79: 46279 | F79: 301.30 | G79: 0.44636574 | H79: 0 | I79: 9.2592593e-05 | J79: 0 | K79: 0 | L79: 0 | M79: 0 | N79: 0 | O79: 0 | P79: 0 | Q79: 96.72 L | R79: 3.12 Km/L | S79: 0.00034722222 | T79: 0.22893519 | U79: 0.19965278 | V79: 0.0094907407 | W79: 0 | X79: 0 | Y79: 0 | Z79: 0 | AA79: 0 | AB79: 0 | AC79: Avenida Deraldo Peixoto de Araújo | AD79: Avenida Deraldo Peixoto de Araújo | AE79: 1128420.66 | AF79: 1128721.96 | AG79: 0.36791667 | AH79: 0.14761574 | AI79: 0 | AJ79: 0 | AK79: 0 | AL79: 0 | AM79: N/A | AN79: 0 | AO79: 0 | AP79: 0 | AQ79: 0 | AR79: 0 | AS79: 0 | AT79: 0 | AU79: 0 | AV79: 0 | AW79: 0 | AX79: 0 | AY79: 0 | AZ79: 0 | BA79: 0 | BB79: 0 | BC79: 0 | BD79: 0 | BE79: 0 | BF79: 0 | BG79: 0 | BH79: 0 | BI79: 0 | BJ79: 0 | BK79: 0 | BM79: =IFERROR(VALUE(F79),"") -> 301.3 | BN79: =IF(R79="-","",IFERROR(VALUE(LEFT(Q79,LEN(Q79)-2)),"")) -> 96.72 | BO79: =IF(R79="-","",IFERROR(VALUE(LEFT(R79,LEN(R79)-5)),"")) -> 3.12 | BP79: =IF(R79="-","",IFERROR(VALUE(F79),"")) -> 301.3 | BQ79: =IF(R79="-",1,0) -> 0
A80: OUR8149 | B80: R7155 | C80: ROTA TRANSPORTES - ITABUNA | D80: PAULO ROMA PINTO - 02932759558 | E80: 46273 | F80: 317.70 | G80: 0.43640046 | H80: 0.42524306 | I80: 5.787037e-05 | J80: 0 | K80: 0 | L80: 0 | M80: 0 | N80: 0 | O80: 0 | P80: 0 | Q80: 117.33 L | R80: 2.71 Km/L | S80: 0 | T80: 0.20243056 | U80: 0.18819444 | V80: 0.032060185 | W80: 0 | X80: 0 | Y80: 0 | Z80: 0 | AA80: 0 | AB80: 0 | AC80: Praça Basílio Oliveira | AD80: Praça Basílio Oliveira | AE80: 1201862.41 | AF80: 1202180.11 | AG80: 0.37768519 | AH80: 0.14895833 | AI80: 0 | AJ80: 0 | AK80: 0 | AL80: 0 | AM80: N/A | AN80: 0 | AO80: 0 | AP80: 0 | AQ80: 0 | AR80: 0 | AS80: 0 | AT80: 0 | AU80: 3 | AV80: 0 | AW80: 0 | AX80: 0 | AY80: 0 | AZ80: 0 | BA80: 0 | BB80: 0 | BC80: 0 | BD80: 0 | BE80: 0 | BF80: 0 | BG80: 0 | BH80: 0 | BI80: 0 | BJ80: 0 | BK80: 0 | BM80: =IFERROR(VALUE(F80),"") -> 317.7 | BN80: =IF(R80="-","",IFERROR(VALUE(LEFT(Q80,LEN(Q80)-2)),"")) -> 117.33 | BO80: =IF(R80="-","",IFERROR(VALUE(LEFT(R80,LEN(R80)-5)),"")) -> 2.71 | BP80: =IF(R80="-","",IFERROR(VALUE(F80),"")) -> 317.7 | BQ80: =IF(R80="-",1,0) -> 0
A81: OUR8149 | B81: R7155 | C81: ROTA TRANSPORTES - ITABUNA | D81: PAULO ROMA PINTO - 02932759558, CLEITON DA SILVA SANTOS - 01466358505 | E81: 46274 | F81: 316.37 | G81: 0.43820602 | H81: 0.43207176 | I81: 0 | J81: 0 | K81: 0 | L81: 0 | M81: 0 | N81: 0 | O81: 0 | P81: 0 | Q81: 108.65 L | R81: 2.91 Km/L | S81: 0 | T81: 0.18576389 | U81: 0.196875 | V81: 0.024537037 | W81: 0 | X81: 0 | Y81: 0 | Z81: 0 | AA81: 0 | AB81: 0 | AC81: Praça Basílio Oliveira | AD81: Rua Querubim Mendes Costa | AE81: 1202180.11 | AF81: 1202496.47 | AG81: 0.37074074 | AH81: 0.13618056 | AI81: 0 | AJ81: 0 | AK81: 0 | AL81: 0 | AM81: N/A | AN81: 0 | AO81: 0 | AP81: 0 | AQ81: 0 | AR81: 0 | AS81: 0 | AT81: 0 | AU81: 5 | AV81: 0 | AW81: 0 | AX81: 0 | AY81: 0 | AZ81: 0 | BA81: 0 | BB81: 0 | BC81: 0 | BD81: 0 | BE81: 0 | BF81: 0 | BG81: 0 | BH81: 0 | BI81: 0 | BJ81: 0 | BK81: 0 | BM81: =IFERROR(VALUE(F81),"") -> 316.37 | BN81: =IF(R81="-","",IFERROR(VALUE(LEFT(Q81,LEN(Q81)-2)),"")) -> 108.65 | BO81: =IF(R81="-","",IFERROR(VALUE(LEFT(R81,LEN(R81)-5)),"")) -> 2.91 | BP81: =IF(R81="-","",IFERROR(VALUE(F81),"")) -> 316.37 | BQ81: =IF(R81="-",1,0) -> 0
A82: OUR8149 | B82: R7155 | C82: ROTA TRANSPORTES - ITABUNA | D82: CLEITON DA SILVA SANTOS - 01466358505 | E82: 46275 | F82: 317.86 | G82: 0.42712963 | H82: 0.42030093 | I82: 0.00011574074 | J82: 0 | K82: 0 | L82: 0 | M82: 0 | N82: 0 | O82: 0 | P82: 0 | Q82: 105.71 L | R82: 3.01 Km/L | S82: 0.00011574074 | T82: 0.20428241 | U82: 0.1931713 | V82: 0.023263889 | W82: 0 | X82: 0 | Y82: 0 | Z82: 0 | AA82: 0 | AB82: 0 | AC82: Rua Querubim Mendes Costa | AD82: Rua Querubim Mendes Costa | AE82: 1202496.47 | AF82: 1202814.33 | AG82: 0.37900463 | AH82: 0.11484954 | AI82: 0 | AJ82: 0 | AK82: 0 | AL82: 0 | AM82: N/A | AN82: 0 | AO82: 0 | AP82: 0 | AQ82: 0 | AR82: 0 | AS82: 0 | AT82: 0 | AU82: 1 | AV82: 0 | AW82: 0 | AX82: 0 | AY82: 0 | AZ82: 0 | BA82: 0 | BB82: 0 | BC82: 0 | BD82: 0 | BE82: 0 | BF82: 0 | BG82: 0 | BH82: 0 | BI82: 0 | BJ82: 0 | BK82: 0 | BM82: =IFERROR(VALUE(F82),"") -> 317.86 | BN82: =IF(R82="-","",IFERROR(VALUE(LEFT(Q82,LEN(Q82)-2)),"")) -> 105.71 | BO82: =IF(R82="-","",IFERROR(VALUE(LEFT(R82,LEN(R82)-5)),"")) -> 3.01 | BP82: =IF(R82="-","",IFERROR(VALUE(F82),"")) -> 317.86 | BQ82: =IF(R82="-",1,0) -> 0
A83: OUR8149 | B83: R7155 | C83: ROTA TRANSPORTES - ITABUNA | D83: CLEITON DA SILVA SANTOS - 01466358505 | E83: 46276 | F83: 315.97 | G83: 0.42304398 | H83: 0.41681713 | I83: 9.2592593e-05 | J83: 0 | K83: 0 | L83: 0 | M83: 0 | N83: 0 | O83: 0 | P83: 0 | Q83: 107.31 L | R83: 2.94 Km/L | S83: 0.00011574074 | T83: 0.19756944 | U83: 0.18796296 | V83: 0.027199074 | W83: 0 | X83: 0 | Y83: 0 | Z83: 0 | AA83: 0 | AB83: 0 | AC83: Rua Querubim Mendes Costa | AD83: Rua Euzébio Ferreira | AE83: 1202814.33 | AF83: 1203130.29 | AG83: 0.36800926 | AH83: 0.076793981 | AI83: 0 | AJ83: 0 | AK83: 0 | AL83: 0 | AM83: N/A | AN83: 0 | AO83: 0 | AP83: 0 | AQ83: 0 | AR83: 0 | AS83: 0 | AT83: 0 | AU83: 4 | AV83: 0 | AW83: 0 | AX83: 0 | AY83: 0 | AZ83: 0 | BA83: 0 | BB83: 0 | BC83: 0 | BD83: 0 | BE83: 0 | BF83: 0 | BG83: 0 | BH83: 0 | BI83: 0 | BJ83: 0 | BK83: 0 | BM83: =IFERROR(VALUE(F83),"") -> 315.97 | BN83: =IF(R83="-","",IFERROR(VALUE(LEFT(Q83,LEN(Q83)-2)),"")) -> 107.31 | BO83: =IF(R83="-","",IFERROR(VALUE(LEFT(R83,LEN(R83)-5)),"")) -> 2.94 | BP83: =IF(R83="-","",IFERROR(VALUE(F83),"")) -> 315.97 | BQ83: =IF(R83="-",1,0) -> 0
A84: OUR8149 | B84: R7155 | C84: ROTA TRANSPORTES - ITABUNA | D84: CLEITON DA SILVA SANTOS - 01466358505, RAIMUNDO JOSE DE OLIVEIRA NUNES - 65617754572 | E84: 46277 | F84: 314.48 | G84: 0.43084491 | H84: 0.42377315 | I84: 0.00011574074 | J84: 0 | K84: 0 | L84: 0 | M84: 0 | N84: 0 | O84: 0 | P84: 0.0093634259 | Q84: 109.93 L | R84: 2.86 Km/L | S84: 0 | T84: 0.20810185 | U84: 0.18634259 | V84: 0.030902778 | W84: 0 | X84: 0 | Y84: 0 | Z84: 0 | AA84: 0 | AB84: 0 | AC84: Rua Euzébio Ferreira | AD84: Rua Euzébio Ferreira | AE84: 1203130.29 | AF84: 1203444.77 | AG84: 0.36961806 | AH84: 0.10782407 | AI84: 0 | AJ84: 0 | AK84: 0 | AL84: 0 | AM84: N/A | AN84: 0 | AO84: 0 | AP84: 0 | AQ84: 0 | AR84: 0 | AS84: 0 | AT84: 0 | AU84: 1 | AV84: 0 | AW84: 0 | AX84: 0 | AY84: 0 | AZ84: 0 | BA84: 0 | BB84: 0 | BC84: 0 | BD84: 0 | BE84: 0 | BF84: 0 | BG84: 0 | BH84: 0 | BI84: 0 | BJ84: 0 | BK84: 0 | BM84: =IFERROR(VALUE(F84),"") -> 314.48 | BN84: =IF(R84="-","",IFERROR(VALUE(LEFT(Q84,LEN(Q84)-2)),"")) -> 109.93 | BO84: =IF(R84="-","",IFERROR(VALUE(LEFT(R84,LEN(R84)-5)),"")) -> 2.86 | BP84: =IF(R84="-","",IFERROR(VALUE(F84),"")) -> 314.48 | BQ84: =IF(R84="-",1,0) -> 0
A85: OUR8149 | B85: R7155 | C85: ROTA TRANSPORTES - ITABUNA | D85: PAULO ROMA PINTO - 02932759558, CLEITON DA SILVA SANTOS - 01466358505 | E85: 46278 | F85: 317.49 | G85: 0.42306713 | H85: 0.40799769 | I85: 0.00011574074 | J85: 0 | K85: 0 | L85: 0 | M85: 0 | N85: 0 | O85: 0 | P85: 0.0075694444 | Q85: 112.18 L | R85: 2.83 Km/L | S85: 0 | T85: 0.19270833 | U85: 0.19039352 | V85: 0.02650463 | W85: 0 | X85: 0 | Y85: 0 | Z85: 0 | AA85: 0 | AB85: 0 | AC85: Rua Euzébio Ferreira | AD85: Praça Basílio Oliveira | AE85: 1203444.77 | AF85: 1203762.26 | AG85: 0.36159722 | AH85: 0.18758102 | AI85: 0 | AJ85: 0 | AK85: 0 | AL85: 0 | AM85: N/A | AN85: 0 | AO85: 0 | AP85: 0 | AQ85: 0 | AR85: 0 | AS85: 0 | AT85: 0 | AU85: 1 | AV85: 0 | AW85: 0 | AX85: 0 | AY85: 0 | AZ85: 0 | BA85: 0 | BB85: 0 | BC85: 0 | BD85: 0 | BE85: 0 | BF85: 0 | BG85: 0 | BH85: 0 | BI85: 0 | BJ85: 0 | BK85: 0 | BM85: =IFERROR(VALUE(F85),"") -> 317.49 | BN85: =IF(R85="-","",IFERROR(VALUE(LEFT(Q85,LEN(Q85)-2)),"")) -> 112.18 | BO85: =IF(R85="-","",IFERROR(VALUE(LEFT(R85,LEN(R85)-5)),"")) -> 2.83 | BP85: =IF(R85="-","",IFERROR(VALUE(F85),"")) -> 317.49 | BQ85: =IF(R85="-",1,0) -> 0
A86: OUR8149 | B86: R7155 | C86: ROTA TRANSPORTES - ITABUNA | D86: PAULO ROMA PINTO - 02932759558 | E86: 46279 | F86: 316.26 | G86: 0.41146991 | H86: 0.39711806 | I86: 0.00010416667 | J86: 0 | K86: 0 | L86: 0 | M86: 0 | N86: 0 | O86: 0 | P86: 0 | Q86: 111.85 L | R86: 2.83 Km/L | S86: 0 | T86: 0.17592593 | U86: 0.19259259 | V86: 0.026273148 | W86: 0 | X86: 0 | Y86: 0 | Z86: 0 | AA86: 0 | AB86: 0 | AC86: Praça Basílio Oliveira | AD86: Praça Basílio Oliveira | AE86: 1203762.26 | AF86: 1204078.52 | AG86: 0.3574537 | AH86: 0.13895833 | AI86: 0 | AJ86: 0 | AK86: 0 | AL86: 0 | AM86: N/A | AN86: 0 | AO86: 0 | AP86: 0 | AQ86: 0 | AR86: 0 | AS86: 0 | AT86: 0 | AU86: 0 | AV86: 0 | AW86: 0 | AX86: 0 | AY86: 0 | AZ86: 0 | BA86: 0 | BB86: 0 | BC86: 0 | BD86: 0 | BE86: 0 | BF86: 0 | BG86: 0 | BH86: 0 | BI86: 0 | BJ86: 0 | BK86: 0 | BM86: =IFERROR(VALUE(F86),"") -> 316.26 | BN86: =IF(R86="-","",IFERROR(VALUE(LEFT(Q86,LEN(Q86)-2)),"")) -> 111.85 | BO86: =IF(R86="-","",IFERROR(VALUE(LEFT(R86,LEN(R86)-5)),"")) -> 2.83 | BP86: =IF(R86="-","",IFERROR(VALUE(F86),"")) -> 316.26 | BQ86: =IF(R86="-",1,0) -> 0
A87: OUR1H68 | B87: R7165 | C87: ROTA TRANSPORTES - ITABUNA | D87: JOSE LUCIANO SANTOS SILVA - 00671441523 | E87: 46273 | F87: 70.59 | G87: 0.15704861 | H87: 0.085717593 | I87: 0.00045138889 | J87: 0 | K87: 0 | L87: 0 | M87: 0 | N87: 0 | O87: 0 | P87: 0.02900463 | Q87: 30.09 L | R87: 2.35 Km/L | S87: 0 | T87: 0.081134259 | U87: 0.063657407 | V87: 0.0074074074 | W87: 0 | X87: 0 | Y87: 0 | Z87: 0 | AA87: 0 | AB87: 0 | AC87: Avenida Amélia Amado | AD87: Rua K | AE87: 1161475.74 | AF87: 1161546.32 | AG87: 0.083923611 | AH87: 0.14587963 | AI87: 0 | AJ87: 0 | AK87: 0 | AL87: 0 | AM87: N/A | AN87: 0 | AO87: 0 | AP87: 0 | AQ87: 0 | AR87: 0 | AS87: 0 | AT87: 0 | AU87: 0 | AV87: 0 | AW87: 0 | AX87: 0 | AY87: 0 | AZ87: 0 | BA87: 0 | BB87: 0 | BC87: 0 | BD87: 0 | BE87: 0 | BF87: 0 | BG87: 0 | BH87: 0 | BI87: 0 | BJ87: 0 | BK87: 0 | BM87: =IFERROR(VALUE(F87),"") -> 70.59 | BN87: =IF(R87="-","",IFERROR(VALUE(LEFT(Q87,LEN(Q87)-2)),"")) -> 30.09 | BO87: =IF(R87="-","",IFERROR(VALUE(LEFT(R87,LEN(R87)-5)),"")) -> 2.35 | BP87: =IF(R87="-","",IFERROR(VALUE(F87),"")) -> 70.59 | BQ87: =IF(R87="-",1,0) -> 0
A88: OUR1H68 | B88: R7165 | C88: ROTA TRANSPORTES - ITABUNA | D88: Jose Raimundo dos Santos - 00335224563, GILMAR ALVES DE SOUSA - 32895178534 | E88: 46274 | F88: 447.70 | G88: 0.51 | H88: 0.32875 | I88: 0.00038194444 | J88: 0 | K88: 0 | L88: 0 | M88: 0 | N88: 0 | O88: 0 | P88: 0.0072106481 | Q88: 137.18 L | R88: 3.26 Km/L | S88: 0.0005787037 | T88: 0.17523148 | U88: 0.2537037 | V88: 0.041898148 | W88: 0 | X88: 0 | Y88: 0 | Z88: 0 | AA88: 0 | AB88: 0 | AC88: Avenida Amélia Amado | AD88: Avenida Alto da Boa Vista | AE88: 1161546.32 | AF88: 1161994.02 | AG88: 0.42079861 | AH88: 0.25168981 | AI88: 0 | AJ88: 0 | AK88: 0 | AL88: 0 | AM88: N/A | AN88: 0 | AO88: 1 | AP88: 0 | AQ88: 0 | AR88: 0 | AS88: 0 | AT88: 0 | AU88: 1 | AV88: 0 | AW88: 0 | AX88: 0 | AY88: 0 | AZ88: 0 | BA88: 0 | BB88: 0 | BC88: 0 | BD88: 0 | BE88: 0 | BF88: 0 | BG88: 0 | BH88: 0 | BI88: 0 | BJ88: 0 | BK88: 0 | BM88: =IFERROR(VALUE(F88),"") -> 447.7 | BN88: =IF(R88="-","",IFERROR(VALUE(LEFT(Q88,LEN(Q88)-2)),"")) -> 137.18 | BO88: =IF(R88="-","",IFERROR(VALUE(LEFT(R88,LEN(R88)-5)),"")) -> 3.26 | BP88: =IF(R88="-","",IFERROR(VALUE(F88),"")) -> 447.7 | BQ88: =IF(R88="-",1,0) -> 0
A89: OUR1H68 | B89: R7165 | C89: ROTA TRANSPORTES - ITABUNA | D89: Jose Raimundo dos Santos - 00335224563, MARCELO EDUARDO OLIVEIRA COSTA - 60245476504 | E89: 46275 | F89: 306.02 | G89: 0.45319444 | H89: 0.44430556 | I89: 4.6296296e-05 | J89: 0 | K89: 0 | L89: 0 | M89: 0 | N89: 0 | O89: 0 | P89: 0 | Q89: 108.98 L | R89: 2.81 Km/L | S89: 0 | T89: 0.17569444 | U89: 0.23159722 | V89: 0.020717593 | W89: 0 | X89: 0 | Y89: 0 | Z89: 0 | AA89: 0 | AB89: 0 | AC89: Avenida Alto da Boa Vista | AD89: Rua K | AE89: 1161994.02 | AF89: 1162300.03 | AG89: 0.37740741 | AH89: 0.15864583 | AI89: 0 | AJ89: 0 | AK89: 0 | AL89: 0 | AM89: N/A | AN89: 0 | AO89: 0 | AP89: 0 | AQ89: 0 | AR89: 0 | AS89: 0 | AT89: 0 | AU89: 2 | AV89: 0 | AW89: 0 | AX89: 0 | AY89: 0 | AZ89: 0 | BA89: 0 | BB89: 1 | BC89: 0 | BD89: 0 | BE89: 0 | BF89: 0 | BG89: 0 | BH89: 0 | BI89: 0 | BJ89: 0 | BK89: 0 | BM89: =IFERROR(VALUE(F89),"") -> 306.02 | BN89: =IF(R89="-","",IFERROR(VALUE(LEFT(Q89,LEN(Q89)-2)),"")) -> 108.98 | BO89: =IF(R89="-","",IFERROR(VALUE(LEFT(R89,LEN(R89)-5)),"")) -> 2.81 | BP89: =IF(R89="-","",IFERROR(VALUE(F89),"")) -> 306.02 | BQ89: =IF(R89="-",1,0) -> 0
A90: OUR1H68 | B90: R7165 | C90: ROTA TRANSPORTES - ITABUNA | D90: EDINALDO JOSE ALVES - 18681883534, GILMAR ALVES DE SOUSA - 32895178534, LEANDRO PINHEIRO DOS SANTOS - 02790495521 | E90: 46276 | F90: 629.86 | G90: 0.57354167 | H90: 0.49744213 | I90: 0.0056365741 | J90: 0 | K90: 0 | L90: 0 | M90: 0 | N90: 0 | O90: 0 | P90: 0.0084027778 | Q90: 188.77 L | R90: 3.34 Km/L | S90: 0.00034722222 | T90: 0.17800926 | U90: 0.26099537 | V90: 0.11400463 | W90: 0 | X90: 0 | Y90: 0 | Z90: 0 | AA90: 0 | AB90: 0 | AC90: Rua João Franco | AD90: Avenida Adno Musser | AE90: 1162300.03 | AF90: 1162929.89 | AG90: 0.48899306 | AH90: 0.19358796 | AI90: 0 | AJ90: 0 | AK90: 0 | AL90: 0 | AM90: N/A | AN90: 0 | AO90: 9 | AP90: 0 | AQ90: 0 | AR90: 0 | AS90: 0 | AT90: 0 | AU90: 6 | AV90: 0 | AW90: 0 | AX90: 0 | AY90: 0 | AZ90: 0 | BA90: 0 | BB90: 0 | BC90: 0 | BD90: 0 | BE90: 0 | BF90: 0 | BG90: 0 | BH90: 0 | BI90: 0 | BJ90: 0 | BK90: 0 | BM90: =IFERROR(VALUE(F90),"") -> 629.86 | BN90: =IF(R90="-","",IFERROR(VALUE(LEFT(Q90,LEN(Q90)-2)),"")) -> 188.77 | BO90: =IF(R90="-","",IFERROR(VALUE(LEFT(R90,LEN(R90)-5)),"")) -> 3.34 | BP90: =IF(R90="-","",IFERROR(VALUE(F90),"")) -> 629.86 | BQ90: =IF(R90="-",1,0) -> 0
A91: OUR1H68 | B91: R7165 | C91: ROTA TRANSPORTES - ITABUNA | D91: JOSELITO MATTOS SANTOS - 69101531549, LEANDRO PINHEIRO DOS SANTOS - 02790495521 | E91: 46277 | F91: 399.09 | G91: 0.4103125 | H91: 0.36516204 | I91: 0.0075231481 | J91: 0 | K91: 0 | L91: 0 | M91: 0 | N91: 0 | O91: 0 | P91: 0 | Q91: 135.15 L | R91: 2.95 Km/L | S91: 0.00023148148 | T91: 0.12071759 | U91: 0.16261574 | V91: 0.08912037 | W91: 0 | X91: 0 | Y91: 0 | Z91: 0 | AA91: 0 | AB91: 0 | AC91: Avenida Adno Musser | AD91: Avenida Alto da Boa Vista | AE91: 1162930.14 | AF91: 1163329.23 | AG91: 0.31922454 | AH91: 0.19886574 | AI91: 0 | AJ91: 0 | AK91: 0 | AL91: 0 | AM91: N/A | AN91: 0 | AO91: 7 | AP91: 0 | AQ91: 0 | AR91: 1 | AS91: 0 | AT91: 0 | AU91: 5 | AV91: 0 | AW91: 0 | AX91: 0 | AY91: 0 | AZ91: 0 | BA91: 0 | BB91: 0 | BC91: 0 | BD91: 0 | BE91: 0 | BF91: 0 | BG91: 0 | BH91: 0 | BI91: 0 | BJ91: 0 | BK91: 0 | BM91: =IFERROR(VALUE(F91),"") -> 399.09 | BN91: =IF(R91="-","",IFERROR(VALUE(LEFT(Q91,LEN(Q91)-2)),"")) -> 135.15 | BO91: =IF(R91="-","",IFERROR(VALUE(LEFT(R91,LEN(R91)-5)),"")) -> 2.95 | BP91: =IF(R91="-","",IFERROR(VALUE(F91),"")) -> 399.09 | BQ91: =IF(R91="-",1,0) -> 0
... A104: OUR3J54 | B104: R7095 | C104: ROTA TRANSPORTES - ITABUNA | D104: ALAN ANDRADE FERREIRA - 05243952508 | E104: 46277 | F104: 345.11 | G104: 0.57608796 | H104: 0.56996528 | I104: 0.00038194444 | J104: 0 | K104: 0 | L104: 0 | M104: 0 | N104: 0 | O104: 0 | P104: 0 | Q104: 121.10 L | R104: 2.85 Km/L | S104: 0.00011574074 | T104: 0.22824074 | U104: 0.23510417 | V104: 0.086122685 | W104: 5.787037e-05 | X104: 0 | Y104: 5.787037e-05 | Z104: 0 | AA104: 0 | AB104: 0 | AC104: Avenida Governador Roberto Santos | AD104: Avenida Governador Roberto Santos | AE104: 1237590.65 | AF104: 1237935.76 | AG104: 0.47861111 | AH104: 0.17400463 | AI104: 0 | AJ104: 0 | AK104: 0 | AL104: 0 | AM104: N/A | AN104: 0 | AO104: 3 | AP104: 0 | AQ104: 0 | AR104: 0 | AS104: 0 | AT104: 0 | AU104: 2 | AV104: 0 | AW104: 0 | AX104: 0 | AY104: 0 | AZ104: 0 | BA104: 0 | BB104: 0 | BC104: 0 | BD104: 0 | BE104: 0 | BF104: 0 | BG104: 0 | BH104: 0 | BI104: 0 | BJ104: 0 | BK104: 0 | BM104: =IFERROR(VALUE(F104),"") -> 345.11 | BN104: =IF(R104="-","",IFERROR(VALUE(LEFT(Q104,LEN(Q104)-2)),"")) -> 121.1 | BO104: =IF(R104="-","",IFERROR(VALUE(LEFT(R104,LEN(R104)-5)),"")) -> 2.85 | BP104: =IF(R104="-","",IFERROR(VALUE(F104),"")) -> 345.11 | BQ104: =IF(R104="-",1,0) -> 0
A105: OUR3J54 | B105: R7095 | C105: ROTA TRANSPORTES - ITABUNA | E105: 46278 | F105: 0.00 | G105: 0 | H105: 0 | I105: 0 | J105: 0 | K105: 0 | L105: 0 | M105: 0 | N105: 0 | O105: 0 | P105: 0 | Q105: - | R105: - | S105: 0 | T105: 0 | U105: 0 | V105: 0 | W105: 0 | X105: 0 | Y105: 0 | Z105: 0 | AA105: 0 | AB105: 0 | AE105: 1237935.76 | AF105: 1237935.76 | AG105: 0 | AH105: 0 | AI105: 0 | AJ105: 0 | AK105: 0 | AL105: 0 | AM105: N/A | AN105: 0 | AO105: 0 | AP105: 0 | AQ105: 0 | AR105: 0 | AS105: 0 | AT105: 0 | AU105: 0 | AV105: 0 | AW105: 0 | AX105: 0 | AY105: 0 | AZ105: 0 | BA105: 0 | BB105: 0 | BC105: 0 | BD105: 0 | BE105: 0 | BF105: 0 | BG105: 0 | BH105: 0 | BI105: 0 | BJ105: 0 | BK105: 0 | BM105: =IFERROR(VALUE(F105),"") -> 0 | BN105: =IF(R105="-","",IFERROR(VALUE(LEFT(Q105,LEN(Q105)-2)),"")) | BO105: =IF(R105="-","",IFERROR(VALUE(LEFT(R105,LEN(R105)-5)),"")) | BP105: =IF(R105="-","",IFERROR(VALUE(F105),"")) | BQ105: =IF(R105="-",1,0) -> 1
A106: OUR3J54 | B106: R7095 | C106: ROTA TRANSPORTES - ITABUNA | D106: RODRIGO DOS SANTOS - 02501564588, PAULO ROBERTO GARCIA DA SILVA - 05472412595, DULCELINO ALMEIDA DE JESUS - 88125386572 | E106: 46279 | F106: 351.16 | G106: 0.59194444 | H106: 0.49824074 | I106: 0.00059027778 | J106: 0 | K106: 0 | L106: 0 | M106: 0 | N106: 1 | O106: 0 | P106: 0 | Q106: 118.04 L | R106: 2.98 Km/L | S106: 0 | T106: 0.24282407 | U106: 0.24675926 | V106: 0.09224537 | W106: 0 | X106: 0 | Y106: 0 | Z106: 0 | AA106: 0 | AB106: 0 | AC106: Avenida Governador Roberto Santos | AD106: Avenida Governador Roberto Santos | AE106: 1237935.76 | AF106: 1238286.91 | AG106: 0.50623843 | AH106: 0.17135417 | AI106: 0 | AJ106: 0 | AK106: 0 | AL106: 0 | AM106: N/A | AN106: 0 | AO106: 0 | AP106: 0 | AQ106: 0 | AR106: 0 | AS106: 6 | AT106: 1 | AU106: 6 | AV106: 0 | AW106: 0 | AX106: 0 | AY106: 0 | AZ106: 0 | BA106: 0 | BB106: 0 | BC106: 0 | BD106: 0 | BE106: 0 | BF106: 0 | BG106: 0 | BH106: 0 | BI106: 0 | BJ106: 0 | BK106: 0 | BM106: =IFERROR(VALUE(F106),"") -> 351.16 | BN106: =IF(R106="-","",IFERROR(VALUE(LEFT(Q106,LEN(Q106)-2)),"")) -> 118.04 | BO106: =IF(R106="-","",IFERROR(VALUE(LEFT(R106,LEN(R106)-5)),"")) -> 2.98 | BP106: =IF(R106="-","",IFERROR(VALUE(F106),"")) -> 351.16 | BQ106: =IF(R106="-",1,0) -> 0
A107: 115326 | B107: R7085 | C107: ROTA TRANSPORTES - ITABUNA | D107: ALESSANDRO DA SILVA SANTOS - 91300681500 | E107: 46273 | F107: 204.70 | G107: 0.35064815 | H107: 0.34445602 | I107: 0.00074074074 | J107: 0 | K107: 0 | L107: 0 | M107: 0 | N107: 2 | O107: 0 | P107: 0 | Q107: 75.19 L | R107: 2.72 Km/L | S107: 0 | T107: 0.14768519 | U107: 0.15300926 | V107: 0.045833333 | W107: 0 | X107: 0 | Y107: 0 | Z107: 0 | AA107: 0 | AB107: 0 | AC107: Rua Castro Alves | AD107: Avenida Amélia Amado | AE107: 1199613.41 | AF107: 1199818.11 | AG107: 0.30512731 | AH107: 0.10322917 | AI107: 0.0002662037 | AJ107: 0 | AK107: 0 | AL107: 0 | AM107: N/A | AN107: 0 | AO107: 0 | AP107: 0 | AQ107: 0 | AR107: 0 | AS107: 0 | AT107: 0 | AU107: 3 | AV107: 0 | AW107: 0 | AX107: 0 | AY107: 0 | AZ107: 0 | BA107: 0 | BB107: 0 | BC107: 0 | BD107: 0 | BE107: 0 | BF107: 0 | BG107: 0 | BH107: 0 | BI107: 0 | BJ107: 0 | BK107: 0 | BM107: =IFERROR(VALUE(F107),"") -> 204.7 | BN107: =IF(R107="-","",IFERROR(VALUE(LEFT(Q107,LEN(Q107)-2)),"")) -> 75.19 | BO107: =IF(R107="-","",IFERROR(VALUE(LEFT(R107,LEN(R107)-5)),"")) -> 2.72 | BP107: =IF(R107="-","",IFERROR(VALUE(F107),"")) -> 204.7 | BQ107: =IF(R107="-",1,0) -> 0
A108: 115326 | B108: R7085 | C108: ROTA TRANSPORTES - ITABUNA | D108: ALESSANDRO DA SILVA SANTOS - 91300681500, WEKSLEY SILVA DAS NEVES - 04346712584 | E108: 46274 | F108: 408.65 | G108: 0.65219907 | H108: 0.64648148 | I108: 0.0030208333 | J108: 0 | K108: 0 | L108: 0 | M108: 0 | N108: 2 | O108: 0 | P108: 0.0074652778 | Q108: 148.46 L | R108: 2.75 Km/L | S108: 0.00023148148 | T108: 0.27962963 | U108: 0.26469907 | V108: 0.1 | W108: 0.00011574074 | X108: 0 | Y108: 0 | Z108: 0 | AA108: 0 | AB108: 0 | AC108: Avenida Amélia Amado | AD108: Avenida Amélia Amado | AE108: 1199818.11 | AF108: 1200226.75 | AG108: 0.56248843 | AH108: 0.18321759 | AI108: 0 | AJ108: 0 | AK108: 0 | AL108: 0 | AM108: N/A | AN108: 0 | AO108: 0 | AP108: 0 | AQ108: 0 | AR108: 0 | AS108: 0 | AT108: 0 | AU108: 5 | AV108: 0 | AW108: 0 | AX108: 0 | AY108: 0 | AZ108: 0 | BA108: 0 | BB108: 0 | BC108: 0 | BD108: 0 | BE108: 0 | BF108: 0 | BG108: 0 | BH108: 0 | BI108: 0 | BJ108: 0 | BK108: 0 | BM108: =IFERROR(VALUE(F108),"") -> 408.65 | BN108: =IF(R108="-","",IFERROR(VALUE(LEFT(Q108,LEN(Q108)-2)),"")) -> 148.46 | BO108: =IF(R108="-","",IFERROR(VALUE(LEFT(R108,LEN(R108)-5)),"")) -> 2.75 | BP108: =IF(R108="-","",IFERROR(VALUE(F108),"")) -> 408.65 | BQ108: =IF(R108="-",1,0) -> 0
A109: 115326 | B109: R7085 | C109: ROTA TRANSPORTES - ITABUNA | D109: ALESSANDRO DA SILVA SANTOS - 91300681500, WEKSLEY SILVA DAS NEVES - 04346712584 | E109: 46275 | F109: 408.68 | G109: 0.66631944 | H109: 0.64366898 | I109: 0.0024652778 | J109: 0 | K109: 0 | L109: 0 | M109: 0 | N109: 3 | O109: 0 | P109: 0.022511574 | Q109: 148.70 L | R109: 2.75 Km/L | S109: 0.00034722222 | T109: 0.28576389 | U109: 0.2599537 | V109: 0.10150463 | W109: 0 | X109: 0 | Y109: 0 | Z109: 0 | AA109: 0 | AB109: 0 | AC109: Avenida Amélia Amado | AD109: Rua João Franco | AE109: 1200226.75 | AF109: 1200635.43 | AG109: 0.56391204 | AH109: 0.1984375 | AI109: 0 | AJ109: 0 | AK109: 0 | AL109: 0 | AM109: N/A | AN109: 0 | AO109: 0 | AP109: 0 | AQ109: 0 | AR109: 0 | AS109: 0 | AT109: 0 | AU109: 3 | AV109: 0 | AW109: 0 | AX109: 0 | AY109: 0 | AZ109: 0 | BA109: 0 | BB109: 0 | BC109: 0 | BD109: 0 | BE109: 0 | BF109: 0 | BG109: 0 | BH109: 0 | BI109: 0 | BJ109: 0 | BK109: 0 | BM109: =IFERROR(VALUE(F109),"") -> 408.68 | BN109: =IF(R109="-","",IFERROR(VALUE(LEFT(Q109,LEN(Q109)-2)),"")) -> 148.7 | BO109: =IF(R109="-","",IFERROR(VALUE(LEFT(R109,LEN(R109)-5)),"")) -> 2.75 | BP109: =IF(R109="-","",IFERROR(VALUE(F109),"")) -> 408.68 | BQ109: =IF(R109="-",1,0) -> 0
A110: 115326 | B110: R7085 | C110: ROTA TRANSPORTES - ITABUNA | D110: ALESSANDRO DA SILVA SANTOS - 91300681500, JEREMIAS DO SANTOS GALIZA - 82787654568 | E110: 46276 | F110: 407.69 | G110: 0.6896412 | H110: 0.68184028 | I110: 0.0034953704 | J110: 0 | K110: 0 | L110: 0 | M110: 0 | N110: 3 | O110: 0 | P110: 0.0076736111 | Q110: 150.92 L | R110: 2.70 Km/L | S110: 0.00023148148 | T110: 0.26226852 | U110: 0.27002315 | V110: 0.1119213 | W110: 0 | X110: 0 | Y110: 0 | Z110: 0 | AA110: 0 | AB110: 0 | AC110: Rua Castro Alves | AD110: Rua K | AE110: 1200635.43 | AF110: 1201043.12 | AG110: 0.56440972 | AH110: 0.18133102 | AI110: 0 | AJ110: 0 | AK110: 0 | AL110: 0 | AM110: N/A | AN110: 0 | AO110: 0 | AP110: 0 | AQ110: 0 | AR110: 0 | AS110: 0 | AT110: 0 | AU110: 10 | AV110: 0 | AW110: 0 | AX110: 0 | AY110: 0 | AZ110: 0 | BA110: 0 | BB110: 0 | BC110: 0 | BD110: 0 | BE110: 0 | BF110: 0 | BG110: 0 | BH110: 0 | BI110: 0 | BJ110: 0 | BK110: 0 | BM110: =IFERROR(VALUE(F110),"") -> 407.69 | BN110: =IF(R110="-","",IFERROR(VALUE(LEFT(Q110,LEN(Q110)-2)),"")) -> 150.92 | BO110: =IF(R110="-","",IFERROR(VALUE(LEFT(R110,LEN(R110)-5)),"")) -> 2.7 | BP110: =IF(R110="-","",IFERROR(VALUE(F110),"")) -> 407.69 | BQ110: =IF(R110="-",1,0) -> 0
A111: 115326 | B111: R7085 | C111: ROTA TRANSPORTES - ITABUNA | D111: EDSON SOUZA DOS SANTOS - 82190178568, ALESSANDRO DA SILVA SANTOS - 91300681500 | E111: 46277 | F111: 386.77 | G111: 0.62084491 | H111: 0.60049769 | I111: 0.0011111111 | J111: 0 | K111: 0 | L111: 0 | M111: 0 | N111: 0 | O111: 0 | P111: 0.0072916667 | Q111: 133.01 L | R111: 2.91 Km/L | S111: 0.0005787037 | T111: 0.24837963 | U111: 0.27002315 | V111: 0.08275463 | W111: 0 | X111: 0 | Y111: 0 | Z111: 0 | AA111: 0 | AB111: 0 | AC111: Rua Castro Alves | AD111: Avenida Governador Roberto Santos | AE111: 1201043.12 | AF111: 1201429.89 | AG111: 0.51704861 | AH111: 0.23185185 | AI111: 0 | AJ111: 0 | AK111: 0 | AL111: 0 | AM111: N/A | AN111: 0 | AO111: 0 | AP111: 0 | AQ111: 0 | AR111: 0 | AS111: 0 | AT111: 0 | AU111: 9 | AV111: 0 | AW111: 0 | AX111: 0 | AY111: 0 | AZ111: 0 | BA111: 0 | BB111: 0 | BC111: 0 | BD111: 0 | BE111: 0 | BF111: 0 | BG111: 0 | BH111: 0 | BI111: 0 | BJ111: 0 | BK111: 0 | BM111: =IFERROR(VALUE(F111),"") -> 386.77 | BN111: =IF(R111="-","",IFERROR(VALUE(LEFT(Q111,LEN(Q111)-2)),"")) -> 133.01 | BO111: =IF(R111="-","",IFERROR(VALUE(LEFT(R111,LEN(R111)-5)),"")) -> 2.91 | BP111: =IF(R111="-","",IFERROR(VALUE(F111),"")) -> 386.77 | BQ111: =IF(R111="-",1,0) -> 0
A112: 115326 | B112: R7085 | C112: ROTA TRANSPORTES - ITABUNA | D112: EDSON SOUZA DOS SANTOS - 82190178568 | E112: 46278 | F112: 216.71 | G112: 0.3755787 | H112: 0.36773148 | I112: 0.00063657407 | J112: 0 | K112: 0 | L112: 0 | M112: 0 | N112: 2 | O112: 0 | P112: 0.015381944 | Q112: 77.75 L | R112: 2.79 Km/L | S112: 0 | T112: 0.1712963 | U112: 0.15127315 | V112: 0.048263889 | W112: 0.00023148148 | X112: 0 | Y112: 0 | Z112: 0 | AA112: 0 | AB112: 0 | AC112: Avenida Governador Roberto Santos | AD112: Avenida Governador Roberto Santos | AE112: 1201429.89 | AF112: 1201646.60 | AG112: 0.29520833 | AH112: 0.13931713 | AI112: 0 | AJ112: 0 | AK112: 0 | AL112: 0 | AM112: N/A | AN112: 0 | AO112: 0 | AP112: 0 | AQ112: 0 | AR112: 0 | AS112: 0 | AT112: 0 | AU112: 2 | AV112: 0 | AW112: 0 | AX112: 0 | AY112: 0 | AZ112: 0 | BA112: 0 | BB112: 0 | BC112: 0 | BD112: 0 | BE112: 0 | BF112: 0 | BG112: 0 | BH112: 0 | BI112: 0 | BJ112: 0 | BK112: 0 | BM112: =IFERROR(VALUE(F112),"") -> 216.71 | BN112: =IF(R112="-","",IFERROR(VALUE(LEFT(Q112,LEN(Q112)-2)),"")) -> 77.75 | BO112: =IF(R112="-","",IFERROR(VALUE(LEFT(R112,LEN(R112)-5)),"")) -> 2.79 | BP112: =IF(R112="-","",IFERROR(VALUE(F112),"")) -> 216.71 | BQ112: =IF(R112="-",1,0) -> 0
A113: 115326 | B113: R7085 | C113: ROTA TRANSPORTES - ITABUNA | D113: RODRIGO SANTOS DE ASSIS - 02614313580, DULCELINO ALMEIDA DE JESUS - 88125386572, OTO CLIMACO DE SANTANA - 42245079515 | E113: 46279 | F113: 288.55 | G113: 0.49915509 | H113: 0.49170139 | I113: 0.0015972222 | J113: 0 | K113: 0 | L113: 0 | M113: 0 | N113: 4 | O113: 0 | P113: 0 | Q113: 106.41 L | R113: 2.71 Km/L | S113: 0.00011574074 | T113: 0.20347222 | U113: 0.20486111 | V113: 0.070023148 | W113: 0 | X113: 0 | Y113: 0 | Z113: 0 | AA113: 0 | AB113: 0 | AC113: Avenida Governador Roberto Santos | AD113: Avenida Governador Roberto Santos | AE113: 1201646.60 | AF113: 1201935.14 | AG113: 0.42774306 | AH113: 0.15519676 | AI113: 0 | AJ113: 0 | AK113: 0 | AL113: 0 | AM113: N/A | AN113: 0 | AO113: 0 | AP113: 0 | AQ113: 0 | AR113: 0 | AS113: 3 | AT113: 0 | AU113: 1 | AV113: 0 | AW113: 0 | AX113: 0 | AY113: 0 | AZ113: 0 | BA113: 0 | BB113: 0 | BC113: 0 | BD113: 0 | BE113: 0 | BF113: 0 | BG113: 0 | BH113: 0 | BI113: 0 | BJ113: 0 | BK113: 0 | BM113: =IFERROR(VALUE(F113),"") -> 288.55 | BN113: =IF(R113="-","",IFERROR(VALUE(LEFT(Q113,LEN(Q113)-2)),"")) -> 106.41 | BO113: =IF(R113="-","",IFERROR(VALUE(LEFT(R113,LEN(R113)-5)),"")) -> 2.71 | BP113: =IF(R113="-","",IFERROR(VALUE(F113),"")) -> 288.55 | BQ113: =IF(R113="-",1,0) -> 0
A114: OUR8027 | B114: R7115 | C114: ROTA TRANSPORTES - ITABUNA | D114: SANDRO ALVES DA CRUZ - 04772139524, OTO CLIMACO DE SANTANA - 42245079515, ELTON ALMEIDA DA SILVA - 92384471520 | E114: 46273 | F114: 361.86 | G114: 0.62990741 | H114: 0.61326389 | I114: 0.0029398148 | J114: 0 | K114: 0 | L114: 0 | M114: 0 | N114: 1 | O114: 0 | P114: 0 | Q114: 114.95 L | R114: 3.15 Km/L | S114: 0.00034722222 | T114: 0.27372685 | U114: 0.30300926 | V114: 0.038773148 | W114: 0 | X114: 0 | Y114: 0 | Z114: 0 | AA114: 0 | AB114: 0 | AC114: Avenida Governador Roberto Santos | AD114: Avenida Governador Roberto Santos | AE114: 1196637.34 | AF114: 1196999.20 | AG114: 0.54827546 | AH114: 0.19550926 | AI114: 0 | AJ114: 0 | AK114: 0 | AL114: 0 | AM114: N/A | AN114: 0 | AO114: 1 | AP114: 0 | AQ114: 0 | AR114: 0 | AS114: 1 | AT114: 0 | AU114: 3 | AV114: 0 | AW114: 0 | AX114: 0 | AY114: 0 | AZ114: 0 | BA114: 0 | BB114: 0 | BC114: 0 | BD114: 0 | BE114: 0 | BF114: 0 | BG114: 0 | BH114: 0 | BI114: 0 | BJ114: 0 | BK114: 0 | BM114: =IFERROR(VALUE(F114),"") -> 361.86 | BN114: =IF(R114="-","",IFERROR(VALUE(LEFT(Q114,LEN(Q114)-2)),"")) -> 114.95 | BO114: =IF(R114="-","",IFERROR(VALUE(LEFT(R114,LEN(R114)-5)),"")) -> 3.15 | BP114: =IF(R114="-","",IFERROR(VALUE(F114),"")) -> 361.86 | BQ114: =IF(R114="-",1,0) -> 0
A115: OUR8027 | B115: R7115 | C115: ROTA TRANSPORTES - ITABUNA | D115: RODRIGO SANTOS DE ASSIS - 02614313580, OTO CLIMACO DE SANTANA - 42245079515 | E115: 46274 | F115: 360.19 | G115: 0.69123843 | H115: 0.58663194 | I115: 0.00375 | J115: 0 | K115: 0 | L115: 0 | M115: 0 | N115: 2 | O115: 0 | P115: 0 | Q115: 115.31 L | R115: 3.12 Km/L | S115: 0 | T115: 0.25520833 | U115: 0.29282407 | V115: 0.049305556 | W115: 0.00011574074 | X115: 0 | Y115: 0 | Z115: 0 | AA115: 0 | AB115: 0 | AC115: Avenida Governador Roberto Santos | AD115: Avenida Governador Roberto Santos | AE115: 1196999.20 | AF115: 1197359.38 | AG115: 0.5265162 | AH115: 0.25106481 | AI115: 0 | AJ115: 0 | AK115: 0 | AL115: 0 | AM115: N/A | AN115: 0 | AO115: 0 | AP115: 0 | AQ115: 0 | AR115: 0 | AS115: 0 | AT115: 0 | AU115: 6 | AV115: 0 | AW115: 0 | AX115: 0 | AY115: 0 | AZ115: 0 | BA115: 0 | BB115: 0 | BC115: 0 | BD115: 0 | BE115: 0 | BF115: 0 | BG115: 0 | BH115: 0 | BI115: 0 | BJ115: 0 | BK115: 0 | BM115: =IFERROR(VALUE(F115),"") -> 360.19 | BN115: =IF(R115="-","",IFERROR(VALUE(LEFT(Q115,LEN(Q115)-2)),"")) -> 115.31 | BO115: =IF(R115="-","",IFERROR(VALUE(LEFT(R115,LEN(R115)-5)),"")) -> 3.12 | BP115: =IF(R115="-","",IFERROR(VALUE(F115),"")) -> 360.19 | BQ115: =IF(R115="-",1,0) -> 0
A116: OUR8027 | B116: R7115 | C116: ROTA TRANSPORTES - ITABUNA | D116: OTO CLIMACO DE SANTANA - 42245079515, RICARDO DE JESUS LOPES - 04936290505, EDIMARCIO NASCIMENTO DOS SANTOS - 29380382839 | E116: 46275 | F116: 360.22 | G116: 0.61282407 | H116: 0.58541667 | I116: 0.0029398148 | J116: 0 | K116: 0 | L116: 0 | M116: 0 | N116: 1 | O116: 0 | P116: 0 | Q116: 117.94 L | R116: 3.05 Km/L | S116: 0.00011574074 | T116: 0.24780093 | U116: 0.28148148 | V116: 0.060185185 | W116: 0 | X116: 0 | Y116: 0 | Z116: 0 | AA116: 0 | AB116: 0 | AC116: Avenida Governador Roberto Santos | AD116: Avenida Governador Roberto Santos | AE116: 1197359.38 | AF116: 1197719.60 | AG116: 0.53083333 | AH116: 0.16696759 | AI116: 0 | AJ116: 0 | AK116: 0 | AL116: 0 | AM116: N/A | AN116: 0 | AO116: 0 | AP116: 0 | AQ116: 0 | AR116: 0 | AS116: 0 | AT116: 0 | AU116: 7 | AV116: 0 | AW116: 0 | AX116: 0 | AY116: 0 | AZ116: 0 | BA116: 0 | BB116: 0 | BC116: 0 | BD116: 0 | BE116: 0 | BF116: 0 | BG116: 0 | BH116: 0 | BI116: 0 | BJ116: 0 | BK116: 0 | BM116: =IFERROR(VALUE(F116),"") -> 360.22 | BN116: =IF(R116="-","",IFERROR(VALUE(LEFT(Q116,LEN(Q116)-2)),"")) -> 117.94 | BO116: =IF(R116="-","",IFERROR(VALUE(LEFT(R116,LEN(R116)-5)),"")) -> 3.05 | BP116: =IF(R116="-","",IFERROR(VALUE(F116),"")) -> 360.22 | BQ116: =IF(R116="-",1,0) -> 0
A117: OUR8027 | B117: R7115 | C117: ROTA TRANSPORTES - ITABUNA | D117: RODRIGO SANTOS DE ASSIS - 02614313580, OTO CLIMACO DE SANTANA - 42245079515 | E117: 46276 | F117: 360.09 | G117: 0.60940972 | H117: 0.55667824 | I117: 0.00094907407 | J117: 0 | K117: 0 | L117: 0 | M117: 0 | N117: 5 | O117: 0 | P117: 0 | Q117: 122.28 L | R117: 2.94 Km/L | S117: 0 | T117: 0.2505787 | U117: 0.26921296 | V117: 0.070949074 | W117: 0 | X117: 0 | Y117: 0 | Z117: 0 | AA117: 0 | AB117: 0 | AC117: Avenida Governador Roberto Santos | AD117: Avenida Governador Roberto Santos | AE117: 1197719.60 | AF117: 1198079.69 | AG117: 0.52481481 | AH117: 0.183125 | AI117: 0 | AJ117: 0 | AK117: 0 | AL117: 0 | AM117: N/A | AN117: 0 | AO117: 0 | AP117: 0 | AQ117: 0 | AR117: 0 | AS117: 0 | AT117: 0 | AU117: 6 | AV117: 0 | AW117: 0 | AX117: 0 | AY117: 0 | AZ117: 0 | BA117: 0 | BB117: 0 | BC117: 0 | BD117: 0 | BE117: 0 | BF117: 0 | BG117: 0 | BH117: 0 | BI117: 0 | BJ117: 0 | BK117: 0 | BM117: =IFERROR(VALUE(F117),"") -> 360.09 | BN117: =IF(R117="-","",IFERROR(VALUE(LEFT(Q117,LEN(Q117)-2)),"")) -> 122.28 | BO117: =IF(R117="-","",IFERROR(VALUE(LEFT(R117,LEN(R117)-5)),"")) -> 2.94 | BP117: =IF(R117="-","",IFERROR(VALUE(F117),"")) -> 360.09 | BQ117: =IF(R117="-",1,0) -> 0
A118: OUR8027 | B118: R7115 | C118: ROTA TRANSPORTES - ITABUNA | D118: EDSON SOUZA DOS SANTOS - 82190178568, OTO CLIMACO DE SANTANA - 42245079515, MARCELO DA SILVA ALVES - 00660499541, Joao Evangelista dos Santos - 58586342572 | E118: 46277 | F118: 178.24 | G118: 0.3221412 | H118: 0.28127315 | I118: 0.00081018519 | J118: 0 | K118: 0 | L118: 0 | M118: 0 | N118: 5 | O118: 0 | P118: 0 | Q118: 58.13 L | R118: 3.07 Km/L | S118: 0 | T118: 0.11759259 | U118: 0.12430556 | V118: 0.034884259 | W118: 0.00024305556 | X118: 0 | Y118: 0.00012731481 | Z118: 0 | AA118: 0 | AB118: 0 | AC118: Avenida Governador Roberto Santos | AD118: Rua K | AE118: 1198079.70 | AF118: 1198257.94 | AG118: 0.23189815 | AH118: 0.21137731 | AI118: 0 | AJ118: 0 | AK118: 0 | AL118: 0 | AM118: N/A | AN118: 0 | AO118: 3 | AP118: 0 | AQ118: 0 | AR118: 0 | AS118: 1 | AT118: 0 | AU118: 2 | AV118: 0 | AW118: 0 | AX118: 0 | AY118: 0 | AZ118: 0 | BA118: 0 | BB118: 0 | BC118: 0 | BD118: 0 | BE118: 0 | BF118: 0 | BG118: 0 | BH118: 0 | BI118: 0 | BJ118: 0 | BK118: 0 | BM118: =IFERROR(VALUE(F118),"") -> 178.24 | BN118: =IF(R118="-","",IFERROR(VALUE(LEFT(Q118,LEN(Q118)-2)),"")) -> 58.13 | BO118: =IF(R118="-","",IFERROR(VALUE(LEFT(R118,LEN(R118)-5)),"")) -> 3.07 | BP118: =IF(R118="-","",IFERROR(VALUE(F118),"")) -> 178.24 | BQ118: =IF(R118="-",1,0) -> 0
A119: OUR8027 | B119: R7115 | C119: ROTA TRANSPORTES - ITABUNA | D119: CARLOS BRITTO PIZZANI - 93531583549 | E119: 46279 | F119: 0.10 | G119: 0.011689815 | H119: 0.011689815 | I119: 0 | J119: 0 | K119: 0 | L119: 0 | M119: 0 | N119: 0 | O119: 0 | P119: 0 | Q119: 0.81 L | R119: 0.12 Km/L | S119: 0 | T119: 0.008912037 | U119: 0.0019675926 | V119: 0.00046296296 | W119: 0.00011574074 | X119: 0 | Y119: 0 | Z119: 0 | AA119: 0 | AB119: 0 | AC119: Rua K | AD119: Rua K | AE119: 1198257.94 | AF119: 1198258.04 | AG119: 0.0025347222 | AH119: 0.0096296296 | AI119: 0 | AJ119: 0 | AK119: 0 | AL119: 0 | AM119: N/A | AN119: 0 | AO119: 0 | AP119: 0 | AQ119: 0 | AR119: 0 | AS119: 0 | AT119: 0 | AU119: 0 | AV119: 0 | AW119: 0 | AX119: 0 | AY119: 0 | AZ119: 0 | BA119: 0 | BB119: 0 | BC119: 0 | BD119: 0 | BE119: 0 | BF119: 0 | BG119: 0 | BH119: 0 | BI119: 0 | BJ119: 0 | BK119: 0 | BM119: =IFERROR(VALUE(F119),"") -> 0.1 | BN119: =IF(R119="-","",IFERROR(VALUE(LEFT(Q119,LEN(Q119)-2)),"")) -> 0.81 | BO119: =IF(R119="-","",IFERROR(VALUE(LEFT(R119,LEN(R119)-5)),"")) -> 0.12 | BP119: =IF(R119="-","",IFERROR(VALUE(F119),"")) -> 0.1 | BQ119: =IF(R119="-",1,0) -> 0
...

Sheet Base_Frota
A1: FROTA BASE
A2: Prefixo | B2: Placa | C2: Empresa | D2: Tipo | E2: FB | F2: Ano | G2: Unidade Operacional | H2: SETOR OU NOP | I2: Linha
A3: R7565 | B3: OZT0656 | C3: ROTA | D3: ÔNIBUS | E3: MBB | F3: 2015 | G3: RT/Itabuna | H3: ITABUNA | I3: ITABUNA X CONQUISTA X ITAPENGA X CANES
A4: R10185 | B4: OZG6088 | C4: ROTA | D4: ÔNIBUS | E4: Volvo | F4: 2014 | G4: RT/Itabuna | H4: CONQUISTA | I4: ESCOLAR EM VIT. DA CONQUISTA ( 1050 R )
A5: R10195 | B5: OZI2D57 | C5: ROTA | D5: ÔNIBUS | E5: MBB | F5: 2014 | G5: RT/Itabuna | H5: ITABUNA | I5: ITABUNA / PAU BRASIL IRIZAR R
A6: R10245 | B6: OZF2403 | C6: ROTA | D6: ÔNIBUS | E6: Volvo | F6: 2014 | G6: RT/Itabuna | H6: ITABUNA | I6: RESERVA ITABUNA (OF) - VOLVO
A7: R8905 | B7: SJS2J74 | C7: ROTA | D7: ÔNIBUS | E7: MBB | F7: 2024 | G7: RT/Itabuna | H7: CONQUISTA | I7: MINA NACIONAL GRAFITE - PEDRA AZUL - MG
A8: R10345 | B8: PJT1670 | C8: ROTA | D8: ÔNIBUS | E8: MBB | F8: 2016 | G8: RT/Itabuna | H8: ILHÉUS | I8: HOTEL - CANABRAVA ILHÉUS (1200 RS)
A9: R10355 | B9: PJT0511 | C9: ROTA | D9: ÔNIBUS | E9: MBB | F9: 2016 | G9: RT/Itabuna | H9: ILHÉUS | I9: HOTEL - CANABRAVA ILHÉUS (1200 RS)
A10: R10365 | B10: PJT7012 | C10: ROTA | D10: ÔNIBUS | E10: MBB | F10: 2016 | G10: RT/Itabuna | H10: ILHÉUS | I10: HOTEL - CANABRAVA ILHÉUS (1200 RS)
A11: R10375 | B11: PJT3877 | C11: ROTA | D11: ÔNIBUS | E11: MBB | F11: 2016 | G11: RT/Itabuna | H11: ILHÉUS | I11: HOTEL - CANABRAVA ILHÉUS (1200 RS)
A12: R10385 | B12: PKC5996 | C12: ROTA | D12: ÔNIBUS | E12: Volvo | F12: 2016 | G12: RT/Itabuna | H12: ILHÉUS | I12: HOTEL - CANABRAVA ILHÉUS 1200 B310R
A13: R10405 | B13: PKC5310 | C13: ROTA | D13: ÔNIBUS | E13: Volvo | F13: 2016 | G13: RT/Itabuna | H13: ITABUNA | I13: RESERVA ITABUNA 1200 B310R
A14: R10415 | B14: GGJ8C22 | C14: ROTA | D14: ÔNIBUS | E14: MBB | F14: 2016 | G14: RT/Itabuna | H14: CONQUISTA | I14: ESCOLAR EM VIT. DA CONQUISTA (DIANTEIRO) - MB
... A49: R7075 | B49: OUR3954 | C49: ROTA | D49: ÔNIBUS | E49: MBB | F49: 2012 | G49: RT/Itabuna | H49: ITABUNA | I49: ITABUNA / ILHEUS
A50: R7085 | B50: 115326 | C50: ROTA | D50: ÔNIBUS | E50: MBB | F50: 2012 | G50: RT/Itabuna | H50: ITABUNA | I50: ITABUNA / ILHEUS
A51: R7095 | B51: OUR7533 | C51: ROTA | D51: ÔNIBUS | E51: MBB | F51: 2012 | G51: RT/Itabuna | H51: ILHÉUS | I51: ILHEUS / ITABUNA
A52: R7105 | B52: OUR3686 | C52: ROTA | D52: ÔNIBUS | E52: MBB | F52: 2013 | G52: RT/Itabuna | H52: ILHÉUS | I52: ILHEUS / ITABUNA
A53: R7125 | B53: OUR3707 | C53: ROTA | D53: ÔNIBUS | E53: MBB | F53: 2012 | G53: RT/Itabuna | H53: ITABUNA | I53: ITABUNA X OLIVENÇA C/ CATRACA
A54: R7145 | B54: OUR9200 | C54: ROTA | D54: ÔNIBUS | E54: MBB | F54: 2012 | G54: RT/Itabuna | H54: ITABUNA | I54: ITABUNA / ITAPITANGA
A55: R7155 | B55: OUR8149 | C55: ROTA | D55: ÔNIBUS | E55: MBB | F55: 2012 | G55: RT/Itabuna | H55: ITABUNA | I55: ALMADINA X ITABUNA E ILHÉUS
A56: R7175 | B56: OZM4852 | C56: ROTA | D56: ÔNIBUS | E56: MBB | F56: 2013 | G56: RT/Itabuna | H56: ILHÉUS | I56: ILHÉUS / CONQUISTA 06:00/16:30
A57: R7415 | B57: OZV6244 | C57: ROTA | D57: ÔNIBUS | E57: MBB | F57: 2014 | G57: RT/Itabuna | H57: ITABUNA | I57: RESERVA ITABUNA - URBANO
A58: R7435 | B58: OZV9425 | C58: ROTA | D58: ÔNIBUS | E58: MBB | F58: 2014 | G58: RT/Itabuna | H58: ITABUNA | I58: RESERVA ITABUNA - URBANO
A59: R7445 | B59: OZV2987 | C59: ROTA | D59: ÔNIBUS | E59: MBB | F59: 2014 | G59: RT/Itabuna | H59: ITABUNA | I59: RESERVA ITABUNA - URBANO
A60: R8695 | B60: RPV3E20 | C60: ROTA | D60: ÔNIBUS | E60: MBB | F60: 2023 | G60: RT/Itabuna | H60: CONQUISTA | I60: ESCOLAR EM VIT. DA CONQUISTA
A61: R7465 | B61: OZV5174 | C61: ROTA | D61: ÔNIBUS | E61: MBB | F61: 2014 | G61: RT/Itabuna | H61: ITABUNA | I61: RESERVA ITABUNA
A62: R7475 | B62: OZT5781 | C62: ROTA | D62: ÔNIBUS | E62: MBB | F62: 2015 | G62: RT/Itabuna | H62: ILHÉUS | I62: RESERVA EM ILHÉUS
... A74: R7745 | B74: PKN8524 | C74: ROTA | D74: ÔNIBUS | E74: MBB | F74: 2015 | G74: RT/Itabuna | H74: ITABUNA | I74: RESERVA ITABUNA
A75: R5365 | B75: SJP4A43 | C75: ROTA | D75: ÔNIBUS | E75: MBB | F75: 2014 | G75: RT/Itabuna | H75: ITABUNA
A76: R8035 | B76: PLG3095 | C76: ROTA | D76: ÔNIBUS | E76: MBB | F76: 2019 | G76: RT/Itabuna | H76: CONQUISTA | I76: ESCOLAR EM VIT. DA CONQUISTA
A77: R10295 | B77: PKE7365 | C77: ROTA | D77: ÔNIBUS | E77: Volvo | F77: 2016 | G77: RT/Itabuna | H77: ITABUNA | I77: RESERVA EM ITABUNA (1200 VOLVO)
A78: R10525 | B78: PLZ9F44 | C78: ROTA | D78: ÔNIBUS | E78: Volvo | F78: 2020 | G78: RT/Itabuna | H78: ITABUNA | I78: RESERVA EM ITABUNA
A79: R8515 | B79: RPK0J26 | C79: ROTA | D79: ÔNIBUS | E79: MBB | F79: 2023 | G79: RT/Itabuna | H79: ITABUNA | I79: P. SEGURO 11:00 X ITACARÉ(13:00)- ITN 08:00-ITC 05:15)
A80: R8525 | B80: RPK0B75 | C80: ROTA | D80: ÔNIBUS | E80: MBB | F80: 2023 | G80: RT/Itabuna | H80: ITABUNA | I80: P. SEGURO (11:00 X ITACARÉ(13:00)- ITN 08:00-ITC 05:15)
A81: R10515 | B81: PLH4088 | C81: ROTA | D81: ÔNIBUS | E81: Volvo | F81: 2019 | G81: RT/Itabuna | H81: ITABUNA | I81: RESERVA EM ITABUNA (BUSCAR B360 R VOLVO)
A82: R8705 | B82: RPV1G14 | C82: ROTA | D82: ÔNIBUS | E82: MBB | F82: 2023 | G82: RT/Itabuna | H82: CONQUISTA | I82: ESCOLAR EM VIT. DA CONQUISTA
A83: R8715 | B83: SJN0C19 | C83: ROTA | D83: ÔNIBUS | E83: MBB | F83: 2024 | G83: RT/Itabuna | H83: CONQUISTA | I83: ESCOLAR EM VIT. DA CONQUISTA
A84: R8725 | B84: SJN2E11 | C84: ROTA | D84: ÔNIBUS | E84: MBB | F84: 2024 | G84: RT/Itabuna | H84: ILHÉUS | I84: A SERVIÇO DA BARRY CALLEBAUT - EM ILHÉUS
A85: R8755 | B85: SJN4F98 | C85: ROTA | D85: ÔNIBUS | E85: MBB | F85: 2024 | G85: RT/Itabuna | H85: ITABUNA | I85: A SERVIÇO DA BARRY CALLEBAUT - EM ITABUNA
A86: R10535 | B86: PLZ9C39 | C86: ROTA | D86: ÔNIBUS | E86: Volvo | F86: 2020 | G86: RT/Itabuna | H86: ITABUNA | I86: RESERVA EM ITABUNA
A87: R8925 | B87: SJS2E47 | C87: ROTA | D87: ÔNIBUS | E87: MBB | F87: 2024 | G87: RT/Itabuna | H87: CONQUISTA | I87: MINA NACIONAL GRAFITE - PEDRA AZUL - MG
... A91: R7245 | B91: OZM9744 | C91: ROTA | D91: ÔNIBUS | E91: MBB | F91: 2014 | G91: RT/Itabuna | H91: ITABUNA | I91: RESERVA EM PORTO SEGURO

Sheet Metas
B2: METAS E PARÂMETROS — GESTÃO DE MÉDIA DE COMBUSTÍVEL
B4: Preço médio do diesel (R$/L) | D4: 6 | E4: << ATUALIZAR com o preço real pago (não fornecido na base) >>
B6: Metas de eficiência por Modelo/Fabricante × Unidade Operacional (Setor)
B7: Meta inicial sugerida = mediana do km/L real dos veículos válidos do próprio grupo, apurada nesta base (08/09 a 14/09/2026). Ajuste manualmente para a meta oficial da empresa quando disponível.
B9: Fabricante/Modelo (FB) | C9: Unidade Operacional (Setor) | D9: Nº de veículos na Base_Frota | E9: Km/L real do grupo no período (agregado) | F9: Meta (Km/L) — editável | G9: Fonte da meta
B10: MBB | C10: CONQUISTA | D10: 16 | E10: 2.59 | F10: 3.24 | G10: Mediana do grupo (sugestão inicial) — substituir por meta oficial
B11: MBB | C11: ILHÉUS | D11: 21 | E11: 2.92 | F11: 2.84 | G11: Mediana do grupo (sugestão inicial) — substituir por meta oficial
B12: MBB | C12: ITABUNA | D12: 43 | E12: 3.11 | F12: 3.02 | G12: Mediana do grupo (sugestão inicial) — substituir por meta oficial
B13: Volvo | C13: CONQUISTA | D13: 2 | E13: 2.88 | F13: 2.91 | G13: Mediana do grupo (sugestão inicial) — substituir por meta oficial
B14: Volvo | C14: ILHÉUS | D14: 1 | E14: Sem dados no período | G14: Sem veículos com reporte numérico no período
B15: Volvo | C15: ITABUNA | D15: 6 | E15: 2.41 | F15: 4.61 | G15: Mediana do grupo (sugestão inicial) — substituir por meta oficial

Sheet Analise_Consumo
A1: GESTÃO DE MÉDIA DE COMBUSTÍVEL — ANÁLISE POR VEÍCULO (km/L real = km ÷ litros, não média das médias)
A2: km/L real calculado apenas com os dias em que a telemetria reportou número (média ≠ "-"), para não distorcer o indicador com dias sem medição. Base: Boletim 08/09 a 14/09/2026.
A4: Prefixo | B4: Placa | C4: Fabricante/Modelo | D4: Setor/UO | E4: Classificação de reporte | F4: Km totais (todos os dias) | G4: Km em dias com reporte | H4: Litros em dias com reporte | I4: Dias com reporte | J4: Dias com tracinho | K4: Km/L real | L4: Meta (Km/L) | M4: Desvio vs meta (%) | N4: Status | O4: Preço diesel (R$/L) | P4: Custo por Km (R$) | Q4: Custo total no período (R$) | R4: Economia potencial (L) | S4: Economia potencial (R$)
A5: R10175 | B5: OZG5113 | C5: Volvo | D5: CONQUISTA | E5: Deixou de reportar | F5: =SUMIFS('Boletim_do_Veiculo_2026-09-08_2'!$BM:$BM,'Boletim_do_Veiculo_2026-09-08_2'!$B:$B,$A5) -> 321.58 | G5: =SUMIFS('Boletim_do_Veiculo_2026-09-08_2'!$BP:$BP,'Boletim_do_Veiculo_2026-09-08_2'!$B:$B,$A5) -> 321.54 | H5: =SUMIFS('Boletim_do_Veiculo_2026-09-08_2'!$BN:$BN,'Boletim_do_Veiculo_2026-09-08_2'!$B:$B,$A5) -> 110.5 | I5: =COUNTIFS('Boletim_do_Veiculo_2026-09-08_2'!$B:$B,$A5,'Boletim_do_Veiculo_2026-09-08_2'!$R:$R,"<>-") -> 4 | J5: =COUNTIFS('Boletim_do_Veiculo_2026-09-08_2'!$B:$B,$A5,'Boletim_do_Veiculo_2026-09-08_2'!$R:$R,"-") -> 1 | K5: =IF(H5=0,"Sem dados",G5/H5) -> 2.9098643 | L5: =IFERROR(INDEX(Metas!$F$10:$F$15,MATCH(1,INDEX((Metas!$B$10:$B$15=C5)*(Metas!$C$10:$C$15=D5),0),0)),"") -> 2.91 | M5: =IF(OR(K5="Sem dados",L5="",L5=0),"",(K5-L5)/L5) -> -4.6648318e-05 | N5: =IF(K5="Sem dados","Sem dados suficientes",IF(M5="","Sem meta definida",IF(M5>=0.02,"Acima da meta",IF(M5<=-0.1,"Crítico: abaixo da meta",IF(M5<0,"Abaixo da meta","Na meta"))))) -> Abaixo da meta | O5: =Metas!$D$4 -> 6 | P5: =IF(K5="Sem dados","",IFERROR(O5/K5,"Km=0 c/ consumo>0 (ver nota)")) -> 2.0619519 | Q5: =H5*O5 -> 663 | R5: =IF(OR(K5="Sem dados",L5="",L5=0,K5>=L5),0,H5-(G5/L5)) -> 0.0051546392 | S5: =R5*O5 -> 0.030927835
A6: R10185 | B6: OZG6088 | C6: Volvo | D6: CONQUISTA | E6: Deixou de reportar | F6: =SUMIFS('Boletim_do_Veiculo_2026-09-08_2'!$BM:$BM,'Boletim_do_Veiculo_2026-09-08_2'!$B:$B,$A6) -> 0 | G6: =SUMIFS('Boletim_do_Veiculo_2026-09-08_2'!$BP:$BP,'Boletim_do_Veiculo_2026-09-08_2'!$B:$B,$A6) -> 0 | H6: =SUMIFS('Boletim_do_Veiculo_2026-09-08_2'!$BN:$BN,'Boletim_do_Veiculo_2026-09-08_2'!$B:$B,$A6) -> 1.08 | I6: =COUNTIFS('Boletim_do_Veiculo_2026-09-08_2'!$B:$B,$A6,'Boletim_do_Veiculo_2026-09-08_2'!$R:$R,"<>-") -> 3 | J6: =COUNTIFS('Boletim_do_Veiculo_2026-09-08_2'!$B:$B,$A6,'Boletim_do_Veiculo_2026-09-08_2'!$R:$R,"-") -> 2 | K6: =IF(H6=0,"Sem dados",G6/H6) -> 0 | L6: =IFERROR(INDEX(Metas!$F$10:$F$15,MATCH(1,INDEX((Metas!$B$10:$B$15=C6)*(Metas!$C$10:$C$15=D6),0),0)),"") -> 2.91 | M6: =IF(OR(K6="Sem dados",L6="",L6=0),"",(K6-L6)/L6) -> -1 | N6: =IF(K6="Sem dados","Sem dados suficientes",IF(M6="","Sem meta definida",IF(M6>=0.02,"Acima da meta",IF(M6<=-0.1,"Crítico: abaixo da meta",IF(M6<0,"Abaixo da meta","Na meta"))))) -> Crítico: abaixo da meta | O6: =Metas!$D$4 -> 6 | P6: =IF(K6="Sem dados","",IFERROR(O6/K6,"Km=0 c/ consumo>0 (ver nota)")) -> Km=0 c/ consumo>0 (ver nota) | Q6: =H6*O6 -> 6.48 | R6: =IF(OR(K6="Sem dados",L6="",L6=0,K6>=L6),0,H6-(G6/L6)) -> 1.08 | S6: =R6*O6 -> 6.48
A7: R10195 | B7: OZI2D57 | C7: MBB | D7: ITABUNA | E7: Reporte contínuo | F7: =SUMIFS('Boletim_do_Veiculo_2026-09-08_2'!$BM:$BM,'Boletim_do_Veiculo_2026-09-08_2'!$B:$B,$A7) -> 1615.15 | G7: =SUMIFS('Boletim_do_Veiculo_2026-09-08_2'!$BP:$BP,'Boletim_do_Veiculo_2026-09-08_2'!$B:$B,$A7) -> 1615.15 | H7: =SUMIFS('Boletim_do_Veiculo_2026-09-08_2'!$BN:$BN,'Boletim_do_Veiculo_2026-09-08_2'!$B:$B,$A7) -> 593.39 | I7: =COUNTIFS('Boletim_do_Veiculo_2026-09-08_2'!$B:$B,$A7,'Boletim_do_Veiculo_2026-09-08_2'!$R:$R,"<>-") -> 7 | J7: =COUNTIFS('Boletim_do_Veiculo_2026-09-08_2'!$B:$B,$A7,'Boletim_do_Veiculo_2026-09-08_2'!$R:$R,"-") -> 0 | K7: =IF(H7=0,"Sem dados",G7/H7) -> 2.721903 | L7: =IFERROR(INDEX(Metas!$F$10:$F$15,MATCH(1,INDEX((Metas!$B$10:$B$15=C7)*(Metas!$C$10:$C$15=D7),0),0)),"") -> 3.02 | M7: =IF(OR(K7="Sem dados",L7="",L7=0),"",(K7-L7)/L7) -> -0.098707628 | N7: =IF(K7="Sem dados","Sem dados suficientes",IF(M7="","Sem meta definida",IF(M7>=0.02,"Acima da meta",IF(M7<=-0.1,"Crítico: abaixo da meta",IF(M7<0,"Abaixo da meta","Na meta"))))) -> Abaixo da meta | O7: =Metas!$D$4 -> 6 | P7: =IF(K7="Sem dados","",IFERROR(O7/K7,"Km=0 c/ consumo>0 (ver nota)")) -> 2.2043402 | Q7: =H7*O7 -> 3560.34 | R7: =IF(OR(K7="Sem dados",L7="",L7=0,K7>=L7),0,H7-(G7/L7)) -> 58.572119 | S7: =R7*O7 -> 351.43272
A8: R10245 | B8: OZF2403 | C8: Volvo | D8: ITABUNA | E8: Reporte contínuo | F8: =SUMIFS('Boletim_do_Veiculo_2026-09-08_2'!$BM:$BM,'Boletim_do_Veiculo_2026-09-08_2'!$B:$B,$A8) -> 0 | G8: =SUMIFS('Boletim_do_Veiculo_2026-09-08_2'!$BP:$BP,'Boletim_do_Veiculo_2026-09-08_2'!$B:$B,$A8) -> 0 | H8: =SUMIFS('Boletim_do_Veiculo_2026-09-08_2'!$BN:$BN,'Boletim_do_Veiculo_2026-09-08_2'!$B:$B,$A8) -> 1.26 | I8: =COUNTIFS('Boletim_do_Veiculo_2026-09-08_2'!$B:$B,$A8,'Boletim_do_Veiculo_2026-09-08_2'!$R:$R,"<>-") -> 3 | J8: =COUNTIFS('Boletim_do_Veiculo_2026-09-08_2'!$B:$B,$A8,'Boletim_do_Veiculo_2026-09-08_2'!$R:$R,"-") -> 0 | K8: =IF(H8=0,"Sem dados",G8/H8) -> 0 | L8: =IFERROR(INDEX(Metas!$F$10:$F$15,MATCH(1,INDEX((Metas!$B$10:$B$15=C8)*(Metas!$C$10:$C$15=D8),0),0)),"") -> 4.61 | M8: =IF(OR(K8="Sem dados",L8="",L8=0),"",(K8-L8)/L8) -> -1 | N8: =IF(K8="Sem dados","Sem dados suficientes",IF(M8="","Sem meta definida",IF(M8>=0.02,"Acima da meta",IF(M8<=-0.1,"Crítico: abaixo da meta",IF(M8<0,"Abaixo da meta","Na meta"))))) -> Crítico: abaixo da meta | O8: =Metas!$D$4 -> 6 | P8: =IF(K8="Sem dados","",IFERROR(O8/K8,"Km=0 c/ consumo>0 (ver nota)")) -> Km=0 c/ consumo>0 (ver nota) | Q8: =H8*O8 -> 7.56 | R8: =IF(OR(K8="Sem dados",L8="",L8=0,K8>=L8),0,H8-(G8/L8)) -> 1.26 | S8: =R8*O8 -> 7.56
A9: R10295 | B9: PKE7365 | C9: Volvo | D9: ITABUNA | E9: Reporte contínuo | F9: =SUMIFS('Boletim_do_Veiculo_2026-09-08_2'!$BM:$BM,'Boletim_do_Veiculo_2026-09-08_2'!$B:$B,$A9) -> 1.37 | G9: =SUMIFS('Boletim_do_Veiculo_2026-09-08_2'!$BP:$BP,'Boletim_do_Veiculo_2026-09-08_2'!$B:$B,$A9) -> 1.37 | H9: =SUMIFS('Boletim_do_Veiculo_2026-09-08_2'!$BN:$BN,'Boletim_do_Veiculo_2026-09-08_2'!$B:$B,$A9) -> 834.42 | I9: =COUNTIFS('Boletim_do_Veiculo_2026-09-08_2'!$B:$B,$A9,'Boletim_do_Veiculo_2026-09-08_2'!$R:$R,"<>-") -> 7 | J9: =COUNTIFS('Boletim_do_Veiculo_2026-09-08_2'!$B:$B,$A9,'Boletim_do_Veiculo_2026-09-08_2'!$R:$R,"-") -> 0 | K9: =IF(H9=0,"Sem dados",G9/H9) -> 0.001641859 | L9: =IFERROR(INDEX(Metas!$F$10:$F$15,MATCH(1,INDEX((Metas!$B$10:$B$15=C9)*(Metas!$C$10:$C$15=D9),0),0)),"") -> 4.61 | M9: =IF(OR(K9="Sem dados",L9="",L9=0),"",(K9-L9)/L9) -> -0.99964385 | N9: =IF(K9="Sem dados","Sem dados suficientes",IF(M9="","Sem meta definida",IF(M9>=0.02,"Acima da meta",IF(M9<=-0.1,"Crítico: abaixo da meta",IF(M9<0,"Abaixo da meta","Na meta"))))) -> Crítico: abaixo da meta | O9: =Metas!$D$4 -> 6 | P9: =IF(K9="Sem dados","",IFERROR(O9/K9,"Km=0 c/ consumo>0 (ver nota)")) -> 3654.3942 | Q9: =H9*O9 -> 5006.52 | R9: =IF(OR(K9="Sem dados",L9="",L9=0,K9>=L9),0,H9-(G9/L9)) -> 834.12282 | S9: =R9*O9 -> 5004.7369
A10: R10355 | B10: PJT0511 | C10: MBB | D10: ILHÉUS | E10: Reporte contínuo | F10: =SUMIFS('Boletim_do_Veiculo_2026-09-08_2'!$BM:$BM,'Boletim_do_Veiculo_2026-09-08_2'!$B:$B,$A10) -> 861.59 | G10: =SUMIFS('Boletim_do_Veiculo_2026-09-08_2'!$BP:$BP,'Boletim_do_Veiculo_2026-09-08_2'!$B:$B,$A10) -> 861.59 | H10: =SUMIFS('Boletim_do_Veiculo_2026-09-08_2'!$BN:$BN,'Boletim_do_Veiculo_2026-09-08_2'!$B:$B,$A10) -> 315.55 | I10: =COUNTIFS('Boletim_do_Veiculo_2026-09-08_2'!$B:$B,$A10,'Boletim_do_Veiculo_2026-09-08_2'!$R:$R,"<>-") -> 7 | J10: =COUNTIFS('Boletim_do_Veiculo_2026-09-08_2'!$B:$B,$A10,'Boletim_do_Veiculo_2026-09-08_2'!$R:$R,"-") -> 0 | K10: =IF(H10=0,"Sem dados",G10/H10) -> 2.7304389 | L10: =IFERROR(INDEX(Metas!$F$10:$F$15,MATCH(1,INDEX((Metas!$B$10:$B$15=C10)*(Metas!$C$10:$C$15=D10),0),0)),"") -> 2.84 | M10: =IF(OR(K10="Sem dados",L10="",L10=0),"",(K10-L10)/L10) -> -0.038577846 | N10: =IF(K10="Sem dados","Sem dados suficientes",IF(M10="","Sem meta definida",IF(M10>=0.02,"Acima da meta",IF(M10<=-0.1,"Crítico: abaixo da meta",IF(M10<0,"Abaixo da meta","Na meta"))))) -> Abaixo da meta | O10: =Metas!$D$4 -> 6 | P10: =IF(K10="Sem dados","",IFERROR(O10/K10,"Km=0 c/ consumo>0 (ver nota)")) -> 2.1974489 | Q10: =H10*O10 -> 1893.3 | R10: =IF(OR(K10="Sem dados",L10="",L10=0,K10>=L10),0,H10-(G10/L10)) -> 12.173239 | S10: =R10*O10 -> 73.039437
A11: R10365 | B11: PJT7012 | C11: MBB | D11: ILHÉUS | E11: Reporte contínuo | F11: =SUMIFS('Boletim_do_Veiculo_2026-09-08_2'!$BM:$BM,'Boletim_do_Veiculo_2026-09-08_2'!$B:$B,$A11) -> 1738.37 | G11: =SUMIFS('Boletim_do_Veiculo_2026-09-08_2'!$BP:$BP,'Boletim_do_Veiculo_2026-09-08_2'!$B:$B,$A11) -> 1738.37 | H11: =SUMIFS('Boletim_do_Veiculo_2026-09-08_2'!$BN:$BN,'Boletim_do_Veiculo_2026-09-08_2'!$B:$B,$A11) -> 691.58 | I11: =COUNTIFS('Boletim_do_Veiculo_2026-09-08_2'!$B:$B,$A11,'Boletim_do_Veiculo_2026-09-08_2'!$R:$R,"<>-") -> 7 | J11: =COUNTIFS('Boletim_do_Veiculo_2026-09-08_2'!$B:$B,$A11,'Boletim_do_Veiculo_2026-09-08_2'!$R:$R,"-") -> 0 | K11: =IF(H11=0,"Sem dados",G11/H11) -> 2.513621 | L11: =IFERROR(INDEX(Metas!$F$10:$F$15,MATCH(1,INDEX((Metas!$B$10:$B$15=C11)*(Metas!$C$10:$C$15=D11),0),0)),"") -> 2.84 | M11: =IF(OR(K11="Sem dados",L11="",L11=0),"",(K11-L11)/L11) -> -0.11492219 | N11: =IF(K11="Sem dados","Sem dados suficientes",IF(M11="","Sem meta definida",IF(M11>=0.02,"Acima da meta",IF(M11<=-0.1,"Crítico: abaixo da meta",IF(M11<0,"Abaixo da meta","Na meta"))))) -> Crítico: abaixo da meta | O11: =Metas!$D$4 -> 6 | P11: =IF(K11="Sem dados","",IFERROR(O11/K11,"Km=0 c/ consumo>0 (ver nota)")) -> 2.3869947 | Q11: =H11*O11 -> 4149.48 | R11: =IF(OR(K11="Sem dados",L11="",L11=0,K11>=L11),0,H11-(G11/L11)) -> 79.477887 | S11: =R11*O11 -> 476.86732
A12: R10375 | B12: PJT3877 | C12: MBB | D12: ILHÉUS | E12: Reporte retomado / aparente correção | F12: =SUMIFS('Boletim_do_Veiculo_2026-09-08_2'!$BM:$BM,'Boletim_do_Veiculo_2026-09-08_2'!$B:$B,$A12) -> 1171.97 | G12: =SUMIFS('Boletim_do_Veiculo_2026-09-08_2'!$BP:$BP,'Boletim_do_Veiculo_2026-09-08_2'!$B:$B,$A12) -> 1171.97 | H12: =SUMIFS('Boletim_do_Veiculo_2026-09-08_2'!$BN:$BN,'Boletim_do_Veiculo_2026-09-08_2'!$B:$B,$A12) -> 524.59 | I12: =COUNTIFS('Boletim_do_Veiculo_2026-09-08_2'!$B:$B,$A12,'Boletim_do_Veiculo_2026-09-08_2'!$R:$R,"<>-") -> 6 | J12: =COUNTIFS('Boletim_do_Veiculo_2026-09-08_2'!$B:$B,$A12,'Boletim_do_Veiculo_2026-09-08_2'!$R:$R,"-") -> 1 | K12: =IF(H12=0,"Sem dados",G12/H12) -> 2.2340685 | L12: =IFERROR(INDEX(Metas!$F$10:$F$15,MATCH(1,INDEX((Metas!$B$10:$B$15=C12)*(Metas!$C$10:$C$15=D12),0),0)),"") -> 2.84 | M12: =IF(OR(K12="Sem dados",L12="",L12=0),"",(K12-L12)/L12) -> -0.21335616 | N12: =IF(K12="Sem dados","Sem dados suficientes",IF(M12="","Sem meta definida",IF(M12>=0.02,"Acima da meta",IF(M12<=-0.1,"Crítico: abaixo da meta",IF(M12<0,"Abaixo da meta","Na meta"))))) -> Crítico: abaixo da meta | O12: =Metas!$D$4 -> 6 | P12: =IF(K12="Sem dados","",IFERROR(O12/K12,"Km=0 c/ consumo>0 (ver nota)")) -> 2.6856831 | Q12: =H12*O12 -> 3147.54 | R12: =IF(OR(K12="Sem dados",L12="",L12=0,K12>=L12),0,H12-(G12/L12)) -> 111.92451 | S12: =R12*O12 -> 671.54704
A13: R10405 | B13: PKC5310 | C13: Volvo | D13: ITABUNA | E13: Reporte contínuo | F13: =SUMIFS('Boletim_do_Veiculo_2026-09-08_2'!$BM:$BM,'Boletim_do_Veiculo_2026-09-08_2'!$B:$B,$A13) -> 1781.93 | G13: =SUMIFS('Boletim_do_Veiculo_2026-09-08_2'!$BP:$BP,'Boletim_do_Veiculo_2026-09-08_2'!$B:$B,$A13) -> 1781.93 | H13: =SUMIFS('Boletim_do_Veiculo_2026-09-08_2'!$BN:$BN,'Boletim_do_Veiculo_2026-09-08_2'!$B:$B,$A13) -> 647.53 | I13: =COUNTIFS('Boletim_do_Veiculo_2026-09-08_2'!$B:$B,$A13,'Boletim_do_Veiculo_2026-09-08_2'!$R:$R,"<>-") -> 7 | J13: =COUNTIFS('Boletim_do_Veiculo_2026-09-08_2'!$B:$B,$A13,'Boletim_do_Veiculo_2026-09-08_2'!$R:$R,"-") -> 0 | K13: =IF(H13=0,"Sem dados",G13/H13) -> 2.7518879 | L13: =IFERROR(INDEX(Metas!$F$10:$F$15,MATCH(1,INDEX((Metas!$B$10:$B$15=C13)*(Metas!$C$10:$C$15=D13),0),0)),"") -> 4.61 | M13: =IF(OR(K13="Sem dados",L13="",L13=0),"",(K13-L13)/L13) -> -0.40306118 | N13: =IF(K13="Sem dados","Sem dados suficientes",IF(M13="","Sem meta definida",IF(M13>=0.02,"Acima da meta",IF(M13<=-0.1,"Crítico: abaixo da meta",IF(M13<0,"Abaixo da meta","Na meta"))))) -> Crítico: abaixo da meta | O13: =Metas!$D$4 -> 6 | P13: =IF(K13="Sem dados","",IFERROR(O13/K13,"Km=0 c/ consumo>0 (ver nota)")) -> 2.1803213 | Q13: =H13*O13 -> 3885.18 | R13: =IF(OR(K13="Sem dados",L13="",L13=0,K13>=L13),0,H13-(G13/L13)) -> 260.99421 | S13: =R13*O13 -> 1565.9652
A14: R10415 | B14: GGJ8C22 | C14: MBB | D14: CONQUISTA | E14: Reporte contínuo | F14: =SUMIFS('Boletim_do_Veiculo_2026-09-08_2'!$BM:$BM,'Boletim_do_Veiculo_2026-09-08_2'!$B:$B,$A14) -> 1318.27 | G14: =SUMIFS('Boletim_do_Veiculo_2026-09-08_2'!$BP:$BP,'Boletim_do_Veiculo_2026-09-08_2'!$B:$B,$A14) -> 1318.27 | H14: =SUMIFS('Boletim_do_Veiculo_2026-09-08_2'!$BN:$BN,'Boletim_do_Veiculo_2026-09-08_2'!$B:$B,$A14) -> 405.69 | I14: =COUNTIFS('Boletim_do_Veiculo_2026-09-08_2'!$B:$B,$A14,'Boletim_do_Veiculo_2026-09-08_2'!$R:$R,"<>-") -> 7 | J14: =COUNTIFS('Boletim_do_Veiculo_2026-09-08_2'!$B:$B,$A14,'Boletim_do_Veiculo_2026-09-08_2'!$R:$R,"-") -> 0 | K14: =IF(H14=0,"Sem dados",G14/H14) -> 3.2494516 | L14: =IFERROR(INDEX(Metas!$F$10:$F$15,MATCH(1,INDEX((Metas!$B$10:$B$15=C14)*(Metas!$C$10:$C$15=D14),0),0)),"") -> 3.24 | M14: =IF(OR(K14="Sem dados",L14="",L14=0),"",(K14-L14)/L14) -> 0.0029171456 | N14: =IF(K14="Sem dados","Sem dados suficientes",IF(M14="","Sem meta definida",IF(M14>=0.02,"Acima da meta",IF(M14<=-0.1,"Crítico: abaixo da meta",IF(M14<0,"Abaixo da meta","Na meta"))))) -> Na meta | O14: =Metas!$D$4 -> 6 | P14: =IF(K14="Sem dados","",IFERROR(O14/K14,"Km=0 c/ consumo>0 (ver nota)")) -> 1.8464654 | Q14: =H14*O14 -> 2434.14 | R14: =IF(OR(K14="Sem dados",L14="",L14=0,K14>=L14),0,H14-(G14/L14)) -> 0 | S14: =R14*O14 -> 0
A15: R10435 | B15: GFF4J44 | C15: MBB | D15: CONQUISTA | E15: Reporte contínuo | F15: =SUMIFS('Boletim_do_Veiculo_2026-09-08_2'!$BM:$BM,'Boletim_do_Veiculo_2026-09-08_2'!$B:$B,$A15) -> 1320.54 | G15: =SUMIFS('Boletim_do_Veiculo_2026-09-08_2'!$BP:$BP,'Boletim_do_Veiculo_2026-09-08_2'!$B:$B,$A15) -> 1320.54 | H15: =SUMIFS('Boletim_do_Veiculo_2026-09-08_2'!$BN:$BN,'Boletim_do_Veiculo_2026-09-08_2'!$B:$B,$A15) -> 420.6 | I15: =COUNTIFS('Boletim_do_Veiculo_2026-09-08_2'!$B:$B,$A15,'Boletim_do_Veiculo_2026-09-08_2'!$R:$R,"<>-") -> 7 | J15: =COUNTIFS('Boletim_do_Veiculo_2026-09-08_2'!$B:$B,$A15,'Boletim_do_Veiculo_2026-09-08_2'!$R:$R,"-") -> 0 | K15: =IF(H15=0,"Sem dados",G15/H15) -> 3.1396576 | L15: =IFERROR(INDEX(Metas!$F$10:$F$15,MATCH(1,INDEX((Metas!$B$10:$B$15=C15)*(Metas!$C$10:$C$15=D15),0),0)),"") -> 3.24 | M15: =IF(OR(K15="Sem dados",L15="",L15=0),"",(K15-L15)/L15) -> -0.030969867 | N15: =IF(K15="Sem dados","Sem dados suficientes",IF(M15="","Sem meta definida",IF(M15>=0.02,"Acima da meta",IF(M15<=-0.1,"Crítico: abaixo da meta",IF(M15<0,"Abaixo da meta","Na meta"))))) -> Abaixo da meta | O15: =Metas!$D$4 -> 6 | P15: =IF(K15="Sem dados","",IFERROR(O15/K15,"Km=0 c/ consumo>0 (ver nota)")) -> 1.9110364 | Q15: =H15*O15 -> 2523.6 | R15: =IF(OR(K15="Sem dados",L15="",L15=0,K15>=L15),0,H15-(G15/L15)) -> 13.025926 | S15: =R15*O15 -> 78.155556
A16: R10515 | B16: PLH4088 | C16: Volvo | D16: ITABUNA | E16: Reporte contínuo | F16: =SUMIFS('Boletim_do_Veiculo_2026-09-08_2'!$BM:$BM,'Boletim_do_Veiculo_2026-09-08_2'!$B:$B,$A16) -> 0 | G16: =SUMIFS('Boletim_do_Veiculo_2026-09-08_2'!$BP:$BP,'Boletim_do_Veiculo_2026-09-08_2'!$B:$B,$A16) -> 0 | H16: =SUMIFS('Boletim_do_Veiculo_2026-09-08_2'!$BN:$BN,'Boletim_do_Veiculo_2026-09-08_2'!$B:$B,$A16) -> 1.23 | I16: =COUNTIFS('Boletim_do_Veiculo_2026-09-08_2'!$B:$B,$A16,'Boletim_do_Veiculo_2026-09-08_2'!$R:$R,"<>-") -> 3 | J16: =COUNTIFS('Boletim_do_Veiculo_2026-09-08_2'!$B:$B,$A16,'Boletim_do_Veiculo_2026-09-08_2'!$R:$R,"-") -> 0 | K16: =IF(H16=0,"Sem dados",G16/H16) -> 0 | L16: =IFERROR(INDEX(Metas!$F$10:$F$15,MATCH(1,INDEX((Metas!$B$10:$B$15=C16)*(Metas!$C$10:$C$15=D16),0),0)),"") -> 4.61 | M16: =IF(OR(K16="Sem dados",L16="",L16=0),"",(K16-L16)/L16) -> -1 | N16: =IF(K16="Sem dados","Sem dados suficientes",IF(M16="","Sem meta definida",IF(M16>=0.02,"Acima da meta",IF(M16<=-0.1,"Crítico: abaixo da meta",IF(M16<0,"Abaixo da meta","Na meta"))))) -> Crítico: abaixo da meta | O16: =Metas!$D$4 -> 6 | P16: =IF(K16="Sem dados","",IFERROR(O16/K16,"Km=0 c/ consumo>0 (ver nota)")) -> Km=0 c/ consumo>0 (ver nota) | Q16: =H16*O16 -> 7.38 | R16: =IF(OR(K16="Sem dados",L16="",L16=0,K16>=L16),0,H16-(G16/L16)) -> 1.23 | S16: =R16*O16 -> 7.38
... A83: R9395 | B83: TGV9E72 | C83: MBB | D83: CONQUISTA | E83: Reporte contínuo | F83: =SUMIFS('Boletim_do_Veiculo_2026-09-08_2'!$BM:$BM,'Boletim_do_Veiculo_2026-09-08_2'!$B:$B,$A83) -> 2975.85 | G83: =SUMIFS('Boletim_do_Veiculo_2026-09-08_2'!$BP:$BP,'Boletim_do_Veiculo_2026-09-08_2'!$B:$B,$A83) -> 2975.85 | H83: =SUMIFS('Boletim_do_Veiculo_2026-09-08_2'!$BN:$BN,'Boletim_do_Veiculo_2026-09-08_2'!$B:$B,$A83) -> 760.89 | I83: =COUNTIFS('Boletim_do_Veiculo_2026-09-08_2'!$B:$B,$A83,'Boletim_do_Veiculo_2026-09-08_2'!$R:$R,"<>-") -> 7 | J83: =COUNTIFS('Boletim_do_Veiculo_2026-09-08_2'!$B:$B,$A83,'Boletim_do_Veiculo_2026-09-08_2'!$R:$R,"-") -> 0 | K83: =IF(H83=0,"Sem dados",G83/H83) -> 3.9110121 | L83: =IFERROR(INDEX(Metas!$F$10:$F$15,MATCH(1,INDEX((Metas!$B$10:$B$15=C83)*(Metas!$C$10:$C$15=D83),0),0)),"") -> 3.24 | M83: =IF(OR(K83="Sem dados",L83="",L83=0),"",(K83-L83)/L83) -> 0.2071025 | N83: =IF(K83="Sem dados","Sem dados suficientes",IF(M83="","Sem meta definida",IF(M83>=0.02,"Acima da meta",IF(M83<=-0.1,"Crítico: abaixo da meta",IF(M83<0,"Abaixo da meta","Na meta"))))) -> Acima da meta | O83: =Metas!$D$4 -> 6 | P83: =IF(K83="Sem dados","",IFERROR(O83/K83,"Km=0 c/ consumo>0 (ver nota)")) -> 1.5341297 | Q83: =H83*O83 -> 4565.34 | R83: =IF(OR(K83="Sem dados",L83="",L83=0,K83>=L83),0,H83-(G83/L83)) -> 0 | S83: =R83*O83 -> 0

Sheet Painel
B2: PAINEL EXECUTIVO — GESTÃO DE MÉDIA DE COMBUSTÍVEL
B3: ROTA Transportes - Itabuna | Boletim 08/09/2026 a 14/09/2026 | Frota válida (Base_Frota) presente no boletim
B5: Veículos válidos analisados | F5: Km totais (todos os dias)
B6: =COUNTA(Analise_Consumo!A5:A83) -> 79 | F6: =SUM(Analise_Consumo!F5:F83) -> 99881.31
B9: Km em dias com reporte | F9: Litros consumidos (dias com reporte)
B10: =SUM(Analise_Consumo!G5:G83) -> 88055.96 | F10: =SUM(Analise_Consumo!H5:H83) -> 29872.12
B13: Km/L real da frota (km ÷ litros) | F13: Custo total diesel no período (R$)
B14: =IFERROR(SUM(Analise_Consumo!G5:G83)/SUM(Analise_Consumo!H5:H83),"") -> 2.947764 | F14: =SUM(Analise_Consumo!Q5:Q83) -> 179232.72
B17: Economia potencial no período (L) | F17: Economia potencial no período (R$)
B18: =SUM(Analise_Consumo!R5:R83) -> 3345.9593 | F18: =SUM(Analise_Consumo!S5:S83) -> 20075.756
B22: Continuidade do reporte de média (telemetria) — veículos válidos
B23: Classificação | C23: Qtde de veículos | D23: % do total
B24: Reporte contínuo | C24: =COUNTIF(Analise_Consumo!E5:E83,B24) -> 52 | D24: =IFERROR(C24/COUNTA(Analise_Consumo!A5:A83),0) -> 0.65822785
B25: Reporte retomado / aparente correção | C25: =COUNTIF(Analise_Consumo!E5:E83,B25) -> 12 | D25: =IFERROR(C25/COUNTA(Analise_Consumo!A5:A83),0) -> 0.15189873
B26: Intermitente | C26: =COUNTIF(Analise_Consumo!E5:E83,B26) -> 1 | D26: =IFERROR(C26/COUNTA(Analise_Consumo!A5:A83),0) -> 0.012658228
B27: Deixou de reportar | C27: =COUNTIF(Analise_Consumo!E5:E83,B27) -> 4 | D27: =IFERROR(C27/COUNTA(Analise_Consumo!A5:A83),0) -> 0.050632911
B28: Sem reporte em todo o período observado | C28: =COUNTIF(Analise_Consumo!E5:E83,B28) -> 10 | D28: =IFERROR(C28/COUNTA(Analise_Consumo!A5:A83),0) -> 0.12658228
B29: Dados insuficientes ou inconsistentes | C29: =COUNTIF(Analise_Consumo!E5:E83,B29) -> 0 | D29: =IFERROR(C29/COUNTA(Analise_Consumo!A5:A83),0) -> 0
B32: Comparação entre Unidades Operacionais equivalentes (Setor)
B33: Setor | C33: Veículos | D33: Km em dias com reporte | E33: Litros | F33: Km/L real (ponderado) | G33: Custo total (R$)
B34: CONQUISTA | C34: =COUNTIF(Analise_Consumo!D5:D83,B34) -> 17 | D34: =SUMIFS(Analise_Consumo!G5:G83,Analise_Consumo!D5:D83,B34) -> 8665.45 | E34: =SUMIFS(Analise_Consumo!H5:H83,Analise_Consumo!D5:D83,B34) -> 3327.63 | F34: =IFERROR(D34/E34,"") -> 2.6040906 | G34: =SUMIFS(Analise_Consumo!Q5:Q83,Analise_Consumo!D5:D83,B34) -> 19965.78
B35: ILHÉUS | C35: =COUNTIF(Analise_Consumo!D5:D83,B35) -> 17 | D35: =SUMIFS(Analise_Consumo!G5:G83,Analise_Consumo!D5:D83,B35) -> 28323.89 | E35: =SUMIFS(Analise_Consumo!H5:H83,Analise_Consumo!D5:D83,B35) -> 9715.89 | F35: =IFERROR(D35/E35,"") -> 2.9152131 | G35: =SUMIFS(Analise_Consumo!Q5:Q83,Analise_Consumo!D5:D83,B35) -> 58295.34
B36: ITABUNA | C36: =COUNTIF(Analise_Consumo!D5:D83,B36) -> 45 | D36: =SUMIFS(Analise_Consumo!G5:G83,Analise_Consumo!D5:D83,B36) -> 51066.62 | E36: =SUMIFS(Analise_Consumo!H5:H83,Analise_Consumo!D5:D83,B36) -> 16828.6 | F36: =IFERROR(D36/E36,"") -> 3.0345139 | G36: =SUMIFS(Analise_Consumo!Q5:Q83,Analise_Consumo!D5:D83,B36) -> 100971.6
B39: Ranking de oportunidades — Top 10 veículos por economia potencial estimada (R$)
B40: # | C40: Prefixo | D40: Placa | E40: Setor | F40: Km/L real | G40: Meta | H40: Economia potencial (R$) | I40: Status
B41: 1 | C41: =IFERROR(INDEX(Analise_Consumo!$A$5:$A$83,MATCH(1,INDEX((Analise_Consumo!$S$5:$S$83=H41)*(COUNTIF($C$41:$C41,Analise_Consumo!$A$5:$A$83)=0),0),0)),"") -> R7045 | D41: =IFERROR(INDEX(Analise_Consumo!$B$5:$B$83,MATCH(1,INDEX((Analise_Consumo!$S$5:$S$83=H41)*(COUNTIF($C$41:$C41,Analise_Consumo!$A$5:$A$83)=0),0),0)),"") | E41: =IFERROR(INDEX(Analise_Consumo!$D$5:$D$83,MATCH(1,INDEX((Analise_Consumo!$S$5:$S$83=H41)*(COUNTIF($C$41:$C41,Analise_Consumo!$A$5:$A$83)=0),0),0)),"") | F41: =IFERROR(INDEX(Analise_Consumo!$K$5:$K$83,MATCH(1,INDEX((Analise_Consumo!$S$5:$S$83=H41)*(COUNTIF($C$41:$C41,Analise_Consumo!$A$5:$A$83)=0),0),0)),"") | G41: =IFERROR(INDEX(Analise_Consumo!$L$5:$L$83,MATCH(1,INDEX((Analise_Consumo!$S$5:$S$83=H41)*(COUNTIF($C$41:$C41,Analise_Consumo!$A$5:$A$83)=0),0),0)),"") | H41: =IFERROR(LARGE(Analise_Consumo!$S$5:$S$83,1),"") -> 5139 | I41: =IFERROR(INDEX(Analise_Consumo!$N$5:$N$83,MATCH(1,INDEX((Analise_Consumo!$S$5:$S$83=H41)*(COUNTIF($C$41:$C41,Analise_Consumo!$A$5:$A$83)=0),0),0)),"")
B42: 2 | C42: =IFERROR(INDEX(Analise_Consumo!$A$5:$A$83,MATCH(1,INDEX((Analise_Consumo!$S$5:$S$83=H42)*(COUNTIF($C$41:$C42,Analise_Consumo!$A$5:$A$83)=0),0),0)),"") -> R10295 | D42: =IFERROR(INDEX(Analise_Consumo!$B$5:$B$83,MATCH(1,INDEX((Analise_Consumo!$S$5:$S$83=H42)*(COUNTIF($C$41:$C42,Analise_Consumo!$A$5:$A$83)=0),0),0)),"") | E42: =IFERROR(INDEX(Analise_Consumo!$D$5:$D$83,MATCH(1,INDEX((Analise_Consumo!$S$5:$S$83=H42)*(COUNTIF($C$41:$C42,Analise_Consumo!$A$5:$A$83)=0),0),0)),"") | F42: =IFERROR(INDEX(Analise_Consumo!$K$5:$K$83,MATCH(1,INDEX((Analise_Consumo!$S$5:$S$83=H42)*(COUNTIF($C$41:$C42,Analise_Consumo!$A$5:$A$83)=0),0),0)),"") | G42: =IFERROR(INDEX(Analise_Consumo!$L$5:$L$83,MATCH(1,INDEX((Analise_Consumo!$S$5:$S$83=H42)*(COUNTIF($C$41:$C42,Analise_Consumo!$A$5:$A$83)=0),0),0)),"") | H42: =IFERROR(LARGE(Analise_Consumo!$S$5:$S$83,2),"") -> 5004.7369 | I42: =IFERROR(INDEX(Analise_Consumo!$N$5:$N$83,MATCH(1,INDEX((Analise_Consumo!$S$5:$S$83=H42)*(COUNTIF($C$41:$C42,Analise_Consumo!$A$5:$A$83)=0),0),0)),"")
B43: 3 | C43: =IFERROR(INDEX(Analise_Consumo!$A$5:$A$83,MATCH(1,INDEX((Analise_Consumo!$S$5:$S$83=H43)*(COUNTIF($C$41:$C43,Analise_Consumo!$A$5:$A$83)=0),0),0)),"") -> R10405 | D43: =IFERROR(INDEX(Analise_Consumo!$B$5:$B$83,MATCH(1,INDEX((Analise_Consumo!$S$5:$S$83=H43)*(COUNTIF($C$41:$C43,Analise_Consumo!$A$5:$A$83)=0),0),0)),"") | E43: =IFERROR(INDEX(Analise_Consumo!$D$5:$D$83,MATCH(1,INDEX((Analise_Consumo!$S$5:$S$83=H43)*(COUNTIF($C$41:$C43,Analise_Consumo!$A$5:$A$83)=0),0),0)),"") | F43: =IFERROR(INDEX(Analise_Consumo!$K$5:$K$83,MATCH(1,INDEX((Analise_Consumo!$S$5:$S$83=H43)*(COUNTIF($C$41:$C43,Analise_Consumo!$A$5:$A$83)=0),0),0)),"") | G43: =IFERROR(INDEX(Analise_Consumo!$L$5:$L$83,MATCH(1,INDEX((Analise_Consumo!$S$5:$S$83=H43)*(COUNTIF($C$41:$C43,Analise_Consumo!$A$5:$A$83)=0),0),0)),"") | H43: =IFERROR(LARGE(Analise_Consumo!$S$5:$S$83,3),"") -> 1565.9652 | I43: =IFERROR(INDEX(Analise_Consumo!$N$5:$N$83,MATCH(1,INDEX((Analise_Consumo!$S$5:$S$83=H43)*(COUNTIF($C$41:$C43,Analise_Consumo!$A$5:$A$83)=0),0),0)),"")
B44: 4 | C44: =IFERROR(INDEX(Analise_Consumo!$A$5:$A$83,MATCH(1,INDEX((Analise_Consumo!$S$5:$S$83=H44)*(COUNTIF($C$41:$C44,Analise_Consumo!$A$5:$A$83)=0),0),0)),"") -> R7245 | D44: =IFERROR(INDEX(Analise_Consumo!$B$5:$B$83,MATCH(1,INDEX((Analise_Consumo!$S$5:$S$83=H44)*(COUNTIF($C$41:$C44,Analise_Consumo!$A$5:$A$83)=0),0),0)),"") | E44: =IFERROR(INDEX(Analise_Consumo!$D$5:$D$83,MATCH(1,INDEX((Analise_Consumo!$S$5:$S$83=H44)*(COUNTIF($C$41:$C44,Analise_Consumo!$A$5:$A$83)=0),0),0)),"") | F44: =IFERROR(INDEX(Analise_Consumo!$K$5:$K$83,MATCH(1,INDEX((Analise_Consumo!$S$5:$S$83=H44)*(COUNTIF($C$41:$C44,Analise_Consumo!$A$5:$A$83)=0),0),0)),"") | G44: =IFERROR(INDEX(Analise_Consumo!$L$5:$L$83,MATCH(1,INDEX((Analise_Consumo!$S$5:$S$83=H44)*(COUNTIF($C$41:$C44,Analise_Consumo!$A$5:$A$83)=0),0),0)),"") | H44: =IFERROR(LARGE(Analise_Consumo!$S$5:$S$83,4),"") -> 1162.5389 | I44: =IFERROR(INDEX(Analise_Consumo!$N$5:$N$83,MATCH(1,INDEX((Analise_Consumo!$S$5:$S$83=H44)*(COUNTIF($C$41:$C44,Analise_Consumo!$A$5:$A$83)=0),0),0)),"")
B45: 5 | C45: =IFERROR(INDEX(Analise_Consumo!$A$5:$A$83,MATCH(1,INDEX((Analise_Consumo!$S$5:$S$83=H45)*(COUNTIF($C$41:$C45,Analise_Consumo!$A$5:$A$83)=0),0),0)),"") -> R7485 | D45: =IFERROR(INDEX(Analise_Consumo!$B$5:$B$83,MATCH(1,INDEX((Analise_Consumo!$S$5:$S$83=H45)*(COUNTIF($C$41:$C45,Analise_Consumo!$A$5:$A$83)=0),0),0)),"") | E45: =IFERROR(INDEX(Analise_Consumo!$D$5:$D$83,MATCH(1,INDEX((Analise_Consumo!$S$5:$S$83=H45)*(COUNTIF($C$41:$C45,Analise_Consumo!$A$5:$A$83)=0),0),0)),"") | F45: =IFERROR(INDEX(Analise_Consumo!$K$5:$K$83,MATCH(1,INDEX((Analise_Consumo!$S$5:$S$83=H45)*(COUNTIF($C$41:$C45,Analise_Consumo!$A$5:$A$83)=0),0),0)),"") | G45: =IFERROR(INDEX(Analise_Consumo!$L$5:$L$83,MATCH(1,INDEX((Analise_Consumo!$S$5:$S$83=H45)*(COUNTIF($C$41:$C45,Analise_Consumo!$A$5:$A$83)=0),0),0)),"") | H45: =IFERROR(LARGE(Analise_Consumo!$S$5:$S$83,5),"") -> 886.04535 | I45: =IFERROR(INDEX(Analise_Consumo!$N$5:$N$83,MATCH(1,INDEX((Analise_Consumo!$S$5:$S$83=H45)*(COUNTIF($C$41:$C45,Analise_Consumo!$A$5:$A$83)=0),0),0)),"")
B46: 6 | C46: =IFERROR(INDEX(Analise_Consumo!$A$5:$A$83,MATCH(1,INDEX((Analise_Consumo!$S$5:$S$83=H46)*(COUNTIF($C$41:$C46,Analise_Consumo!$A$5:$A$83)=0),0),0)),"") -> R7125 | D46: =IFERROR(INDEX(Analise_Consumo!$B$5:$B$83,MATCH(1,INDEX((Analise_Consumo!$S$5:$S$83=H46)*(COUNTIF($C$41:$C46,Analise_Consumo!$A$5:$A$83)=0),0),0)),"") | E46: =IFERROR(INDEX(Analise_Consumo!$D$5:$D$83,MATCH(1,INDEX((Analise_Consumo!$S$5:$S$83=H46)*(COUNTIF($C$41:$C46,Analise_Consumo!$A$5:$A$83)=0),0),0)),"") | F46: =IFERROR(INDEX(Analise_Consumo!$K$5:$K$83,MATCH(1,INDEX((Analise_Consumo!$S$5:$S$83=H46)*(COUNTIF($C$41:$C46,Analise_Consumo!$A$5:$A$83)=0),0),0)),"") | G46: =IFERROR(INDEX(Analise_Consumo!$L$5:$L$83,MATCH(1,INDEX((Analise_Consumo!$S$5:$S$83=H46)*(COUNTIF($C$41:$C46,Analise_Consumo!$A$5:$A$83)=0),0),0)),"") | H46: =IFERROR(LARGE(Analise_Consumo!$S$5:$S$83,6),"") -> 853.16026 | I46: =IFERROR(INDEX(Analise_Consumo!$N$5:$N$83,MATCH(1,INDEX((Analise_Consumo!$S$5:$S$83=H46)*(COUNTIF($C$41:$C46,Analise_Consumo!$A$5:$A$83)=0),0),0)),"")
B47: 7 | C47: =IFERROR(INDEX(Analise_Consumo!$A$5:$A$83,MATCH(1,INDEX((Analise_Consumo!$S$5:$S$83=H47)*(COUNTIF($C$41:$C47,Analise_Consumo!$A$5:$A$83)=0),0),0)),"") -> R10375 | D47: =IFERROR(INDEX(Analise_Consumo!$B$5:$B$83,MATCH(1,INDEX((Analise_Consumo!$S$5:$S$83=H47)*(COUNTIF($C$41:$C47,Analise_Consumo!$A$5:$A$83)=0),0),0)),"") | E47: =IFERROR(INDEX(Analise_Consumo!$D$5:$D$83,MATCH(1,INDEX((Analise_Consumo!$S$5:$S$83=H47)*(COUNTIF($C$41:$C47,Analise_Consumo!$A$5:$A$83)=0),0),0)),"") | F47: =IFERROR(INDEX(Analise_Consumo!$K$5:$K$83,MATCH(1,INDEX((Analise_Consumo!$S$5:$S$83=H47)*(COUNTIF($C$41:$C47,Analise_Consumo!$A$5:$A$83)=0),0),0)),"") | G47: =IFERROR(INDEX(Analise_Consumo!$L$5:$L$83,MATCH(1,INDEX((Analise_Consumo!$S$5:$S$83=H47)*(COUNTIF($C$41:$C47,Analise_Consumo!$A$5:$A$83)=0),0),0)),"") | H47: =IFERROR(LARGE(Analise_Consumo!$S$5:$S$83,7),"") -> 671.54704 | I47: =IFERROR(INDEX(Analise_Consumo!$N$5:$N$83,MATCH(1,INDEX((Analise_Consumo!$S$5:$S$83=H47)*(COUNTIF($C$41:$C47,Analise_Consumo!$A$5:$A$83)=0),0),0)),"")
B48: 8 | C48: =IFERROR(INDEX(Analise_Consumo!$A$5:$A$83,MATCH(1,INDEX((Analise_Consumo!$S$5:$S$83=H48)*(COUNTIF($C$41:$C48,Analise_Consumo!$A$5:$A$83)=0),0),0)),"") -> R10365 | D48: =IFERROR(INDEX(Analise_Consumo!$B$5:$B$83,MATCH(1,INDEX((Analise_Consumo!$S$5:$S$83=H48)*(COUNTIF($C$41:$C48,Analise_Consumo!$A$5:$A$83)=0),0),0)),"") | E48: =IFERROR(INDEX(Analise_Consumo!$D$5:$D$83,MATCH(1,INDEX((Analise_Consumo!$S$5:$S$83=H48)*(COUNTIF($C$41:$C48,Analise_Consumo!$A$5:$A$83)=0),0),0)),"") | F48: =IFERROR(INDEX(Analise_Consumo!$K$5:$K$83,MATCH(1,INDEX((Analise_Consumo!$S$5:$S$83=H48)*(COUNTIF($C$41:$C48,Analise_Consumo!$A$5:$A$83)=0),0),0)),"") | G48: =IFERROR(INDEX(Analise_Consumo!$L$5:$L$83,MATCH(1,INDEX((Analise_Consumo!$S$5:$S$83=H48)*(COUNTIF($C$41:$C48,Analise_Consumo!$A$5:$A$83)=0),0),0)),"") | H48: =IFERROR(LARGE(Analise_Consumo!$S$5:$S$83,8),"") -> 476.86732 | I48: =IFERROR(INDEX(Analise_Consumo!$N$5:$N$83,MATCH(1,INDEX((Analise_Consumo!$S$5:$S$83=H48)*(COUNTIF($C$41:$C48,Analise_Consumo!$A$5:$A$83)=0),0),0)),"")
B49: 9 | C49: =IFERROR(INDEX(Analise_Consumo!$A$5:$A$83,MATCH(1,INDEX((Analise_Consumo!$S$5:$S$83=H49)*(COUNTIF($C$41:$C49,Analise_Consumo!$A$5:$A$83)=0),0),0)),"") -> R7085 | D49: =IFERROR(INDEX(Analise_Consumo!$B$5:$B$83,MATCH(1,INDEX((Analise_Consumo!$S$5:$S$83=H49)*(COUNTIF($C$41:$C49,Analise_Consumo!$A$5:$A$83)=0),0),0)),"") | E49: =IFERROR(INDEX(Analise_Consumo!$D$5:$D$83,MATCH(1,INDEX((Analise_Consumo!$S$5:$S$83=H49)*(COUNTIF($C$41:$C49,Analise_Consumo!$A$5:$A$83)=0),0),0)),"") | F49: =IFERROR(INDEX(Analise_Consumo!$K$5:$K$83,MATCH(1,INDEX((Analise_Consumo!$S$5:$S$83=H49)*(COUNTIF($C$41:$C49,Analise_Consumo!$A$5:$A$83)=0),0),0)),"") | G49: =IFERROR(INDEX(Analise_Consumo!$L$5:$L$83,MATCH(1,INDEX((Analise_Consumo!$S$5:$S$83=H49)*(COUNTIF($C$41:$C49,Analise_Consumo!$A$5:$A$83)=0),0),0)),"") | H49: =IFERROR(LARGE(Analise_Consumo!$S$5:$S$83,9),"") -> 429.89166 | I49: =IFERROR(INDEX(Analise_Consumo!$N$5:$N$83,MATCH(1,INDEX((Analise_Consumo!$S$5:$S$83=H49)*(COUNTIF($C$41:$C49,Analise_Consumo!$A$5:$A$83)=0),0),0)),"")
B50: 10 | C50: =IFERROR(INDEX(Analise_Consumo!$A$5:$A$83,MATCH(1,INDEX((Analise_Consumo!$S$5:$S$83=H50)*(COUNTIF($C$41:$C50,Analise_Consumo!$A$5:$A$83)=0),0),0)),"") -> R8525 | D50: =IFERROR(INDEX(Analise_Consumo!$B$5:$B$83,MATCH(1,INDEX((Analise_Consumo!$S$5:$S$83=H50)*(COUNTIF($C$41:$C50,Analise_Consumo!$A$5:$A$83)=0),0),0)),"") | E50: =IFERROR(INDEX(Analise_Consumo!$D$5:$D$83,MATCH(1,INDEX((Analise_Consumo!$S$5:$S$83=H50)*(COUNTIF($C$41:$C50,Analise_Consumo!$A$5:$A$83)=0),0),0)),"") | F50: =IFERROR(INDEX(Analise_Consumo!$K$5:$K$83,MATCH(1,INDEX((Analise_Consumo!$S$5:$S$83=H50)*(COUNTIF($C$41:$C50,Analise_Consumo!$A$5:$A$83)=0),0),0)),"") | G50: =IFERROR(INDEX(Analise_Consumo!$L$5:$L$83,MATCH(1,INDEX((Analise_Consumo!$S$5:$S$83=H50)*(COUNTIF($C$41:$C50,Analise_Consumo!$A$5:$A$83)=0),0),0)),"") | H50: =IFERROR(LARGE(Analise_Consumo!$S$5:$S$83,10),"") -> 391.11258 | I50: =IFERROR(INDEX(Analise_Consumo!$N$5:$N$83,MATCH(1,INDEX((Analise_Consumo!$S$5:$S$83=H50)*(COUNTIF($C$41:$C50,Analise_Consumo!$A$5:$A$83)=0),0),0)),"")

Sheet Análise por Veículo
A1: Placa | B1: Prefixo | C1: UO/Localidade | D1: Setor | E1: Classificação | F1: Primeiro dia com registro | G1: Último dia com registro | H1: Dias com registro no boletim | I1: Dias com média numérica | J1: Dias com tracinho | K1: Situação no último registro | L1: Distância (km) nos dias com tracinho | M1: Correspondência/ressalva de cruzamento | N1: Observação objetiva
A2: OZG5113 | B2: R10175 | C2: RT/Itabuna | D2: CONQUISTA | E2: Deixou de reportar | F2: 2026-09-08 | G2: 2026-09-14 | H2: 5 | I2: 4 | J2: 1 | K2: Sem reporte (tracinho) | L2: 0 | M2: Placa OZG5B13 nao encontrada na Base_Frota; correspondencia feita pelo prefixo ['R10175'] | N2: Cobertura de apenas 5 dia(s) no boletim (período tem 7 dias); dias sem linha no boletim não foram tratados como interrupção. Reportou normalmente até 2026-09-11 e ficou sem reporte (tracinho) do dia 2026-09-14 até o fim do período observado (2026-09-14).
A3: OZG6088 | B3: R10185 | C3: RT/Itabuna | D3: CONQUISTA | E3: Deixou de reportar | F3: 2026-09-08 | G3: 2026-09-14 | H3: 5 | I3: 3 | J3: 2 | K3: Sem reporte (tracinho) | L3: 0 | N3: Cobertura de apenas 5 dia(s) no boletim (período tem 7 dias); dias sem linha no boletim não foram tratados como interrupção. Reportou normalmente até 2026-09-10 e ficou sem reporte (tracinho) do dia 2026-09-12 até o fim do período observado (2026-09-14).
A4: OZI2D57 | B4: R10195 | C4: RT/Itabuna | D4: ITABUNA | E4: Reporte contínuo | F4: 2026-09-08 | G4: 2026-09-14 | H4: 7 | I4: 7 | J4: 0 | K4: Reportando (numérico) | L4: 0 | N4: Reportou média numérica (telemetria) em todos os dias com registro no boletim.
A5: OZF2403 | B5: R10245 | C5: RT/Itabuna | D5: ITABUNA | E5: Reporte contínuo | F5: 2026-09-09 | G5: 2026-09-14 | H5: 3 | I5: 3 | J5: 0 | K5: Reportando (numérico) | L5: 0 | N5: Cobertura de apenas 3 dia(s) no boletim (período tem 7 dias); dias sem linha no boletim não foram tratados como interrupção. Reportou média numérica (telemetria) em todos os dias com registro no boletim.
A6: PKE7365 | B6: R10295 | C6: RT/Itabuna | D6: ITABUNA | E6: Reporte contínuo | F6: 2026-09-08 | G6: 2026-09-14 | H6: 7 | I6: 7 | J6: 0 | K6: Reportando (numérico) | L6: 0 | N6: Reportou média numérica (telemetria) em todos os dias com registro no boletim.
A7: PJT0511 | B7: R10355 | C7: RT/Itabuna | D7: ILHÉUS | E7: Reporte contínuo | F7: 2026-09-08 | G7: 2026-09-14 | H7: 7 | I7: 7 | J7: 0 | K7: Reportando (numérico) | L7: 0 | M7: Placa PJT0F11 nao encontrada na Base_Frota; correspondencia feita pelo prefixo ['R10355'] | N7: Reportou média numérica (telemetria) em todos os dias com registro no boletim.
A8: PJT7012 | B8: R10365 | C8: RT/Itabuna | D8: ILHÉUS | E8: Reporte contínuo | F8: 2026-09-08 | G8: 2026-09-14 | H8: 7 | I8: 7 | J8: 0 | K8: Reportando (numérico) | L8: 0 | M8: Placa PJT7A12 nao encontrada na Base_Frota; correspondencia feita pelo prefixo ['R10365'] | N8: Reportou média numérica (telemetria) em todos os dias com registro no boletim.
A9: PJT3877 | B9: R10375 | C9: RT/Itabuna | D9: ILHÉUS | E9: Reporte retomado / aparente correção | F9: 2026-09-08 | G9: 2026-09-14 | H9: 7 | I9: 6 | J9: 1 | K9: Reportando (numérico) | L9: 0 | N9: Ficou sem reporte (tracinho) de 2026-09-13 a 2026-09-13 (após dias com registros numéricos) e voltou a apresentar números a partir de 2026-09-14 — indício de correção conforme regra do estudo (sem confirmação de manutenção registrada).
A10: PKC5310 | B10: R10405 | C10: RT/Itabuna | D10: ITABUNA | E10: Reporte contínuo | F10: 2026-09-08 | G10: 2026-09-14 | H10: 7 | I10: 7 | J10: 0 | K10: Reportando (numérico) | L10: 0 | N10: Reportou média numérica (telemetria) em todos os dias com registro no boletim.
A11: GGJ8C22 | B11: R10415 | C11: RT/Itabuna | D11: CONQUISTA | E11: Reporte contínuo | F11: 2026-09-08 | G11: 2026-09-14 | H11: 7 | I11: 7 | J11: 0 | K11: Reportando (numérico) | L11: 0 | N11: Reportou média numérica (telemetria) em todos os dias com registro no boletim.
A12: GFF4J44 | B12: R10435 | C12: RT/Itabuna | D12: CONQUISTA | E12: Reporte contínuo | F12: 2026-09-08 | G12: 2026-09-14 | H12: 7 | I12: 7 | J12: 0 | K12: Reportando (numérico) | L12: 0 | N12: Reportou média numérica (telemetria) em todos os dias com registro no boletim.
A13: PLH4088 | B13: R10515 | C13: RT/Itabuna | D13: ITABUNA | E13: Reporte contínuo | F13: 2026-09-08 | G13: 2026-09-11 | H13: 3 | I13: 3 | J13: 0 | K13: Reportando (numérico) | L13: 0 | N13: Cobertura de apenas 3 dia(s) no boletim (período tem 7 dias); dias sem linha no boletim não foram tratados como interrupção. Reportou média numérica (telemetria) em todos os dias com registro no boletim.
A14: PLZ9F44 | B14: R10525 | C14: RT/Itabuna | D14: ITABUNA | E14: Reporte contínuo | F14: 2026-09-08 | G14: 2026-09-14 | H14: 7 | I14: 7 | J14: 0 | K14: Reportando (numérico) | L14: 0 | N14: Reportou média numérica (telemetria) em todos os dias com registro no boletim.
A15: PLZ9C39 | B15: R10535 | C15: RT/Itabuna | D15: ITABUNA | E15: Reporte retomado / aparente correção | F15: 2026-09-08 | G15: 2026-09-14 | H15: 7 | I15: 6 | J15: 1 | K15: Reportando (numérico) | L15: 140.6 | N15: Ficou sem reporte (tracinho) de 2026-09-08 a 2026-09-08 (desde o início do período observado) e voltou a apresentar números a partir de 2026-09-09 — indício de correção conforme regra do estudo (sem confirmação de manutenção registrada).
A16: RCR9E39 | B16: R10575 | C16: RT/Itabuna | D16: ITABUNA | E16: Reporte contínuo | F16: 2026-09-08 | G16: 2026-09-14 | H16: 7 | I16: 7 | J16: 0 | K16: Reportando (numérico) | L16: 0 | N16: Reportou média numérica (telemetria) em todos os dias com registro no boletim.
A17: SJP4A43 | B17: R5365 | C17: RT/Itabuna | D17: ITABUNA | E17: Sem reporte em todo o período observado | F17: 2026-09-08 | G17: 2026-09-14 | H17: 5 | I17: 0 | J17: 5 | K17: Sem reporte (tracinho) | L17: 1046.8 | N17: Cobertura de apenas 5 dia(s) no boletim (período tem 7 dias); dias sem linha no boletim não foram tratados como interrupção. Nenhum registro numérico de média em todo o período observado (todos os dias com tracinho).
A18: JQI1371 | B18: R5495 | C18: RT/Itabuna | D18: ITABUNA | E18: Sem reporte em todo o período observado | F18: 2026-09-08 | G18: 2026-09-14 | H18: 6 | I18: 0 | J18: 6 | K18: Sem reporte (tracinho) | L18: 355.1 | N18: Cobertura de apenas 6 dia(s) no boletim (período tem 7 dias); dias sem linha no boletim não foram tratados como interrupção. Nenhum registro numérico de média em todo o período observado (todos os dias com tracinho).
A19: PJK8498 | B19: R6175 | C19: RT/Itabuna | D19: ITABUNA | E19: Reporte contínuo | F19: 2026-09-08 | G19: 2026-09-14 | H19: 6 | I19: 6 | J19: 0 | K19: Reportando (numérico) | L19: 0 | N19: Cobertura de apenas 6 dia(s) no boletim (período tem 7 dias); dias sem linha no boletim não foram tratados como interrupção. Reportou média numérica (telemetria) em todos os dias com registro no boletim.
A20: PJK7178 | B20: R6435 | C20: RT/Itabuna | D20: ILHÉUS | E20: Reporte contínuo | F20: 2026-09-08 | G20: 2026-09-14 | H20: 7 | I20: 7 | J20: 0 | K20: Reportando (numérico) | L20: 0 | M20: Placa JOK7724 nao encontrada na Base_Frota; correspondencia feita pelo prefixo ['R6435'] | N20: Reportou média numérica (telemetria) em todos os dias com registro no boletim.
A21: NYP4733 | B21: R6465 | C21: RT/Itabuna | D21: ITABUNA | E21: Sem reporte em todo o período observado | F21: 2026-09-08 | G21: 2026-09-11 | H21: 4 | I21: 0 | J21: 4 | K21: Sem reporte (tracinho) | L21: 91.1 | N21: Cobertura de apenas 4 dia(s) no boletim (período tem 7 dias); dias sem linha no boletim não foram tratados como interrupção. Nenhum registro numérico de média em todo o período observado (todos os dias com tracinho).
A22: NZO2423 | B22: R6755 | C22: RT/Itabuna | D22: ITABUNA | E22: Reporte retomado / aparente correção | F22: 2026-09-08 | G22: 2026-09-13 | H22: 5 | I22: 4 | J22: 1 | K22: Reportando (numérico) | L22: 218.5 | M22: ATENÇÃO: o boletim reporta 2 placas diferentes para o prefixo R6755 na mesma semana (NZO2423, NZO4525); Base_Frota cadastra a placa NZO2423. Possível erro de digitação/OCR na captura da placa ou troca de veículo sob o mesmo prefixo — os registros foram tratados como um único veículo (chave = prefixo) e devem ser confirmados junto à operação. | N22: Cobertura de apenas 5 dia(s) no boletim (período tem 7 dias); dias sem linha no boletim não foram tratados como interrupção. Ficou sem reporte (tracinho) de 2026-09-11 a 2026-09-11 (após dias com registros numéricos) e voltou a apresentar números a partir de 2026-09-13 — indício de correção conforme regra do estudo (sem confirmação de manutenção registrada). ATENÇÃO: há dia(s) com registros simultâneos numérico e tracinho para este veículo (ver Ocorrências).
A23: NZQ2847 | B23: R6795 | C23: RT/Itabuna | D23: ITABUNA | E23: Reporte contínuo | F23: 2026-09-08 | G23: 2026-09-14 | H23: 7 | I23: 7 | J23: 0 | K23: Reportando (numérico) | L23: 0 | N23: Reportou média numérica (telemetria) em todos os dias com registro no boletim.
A24: NZO9187 | B24: R6815 | C24: RT/Itabuna | D24: ITABUNA | E24: Sem reporte em todo o período observado | F24: 2026-09-08 | G24: 2026-09-14 | H24: 7 | I24: 0 | J24: 7 | K24: Sem reporte (tracinho) | L24: 2397.5 | N24: Nenhum registro numérico de média em todo o período observado (todos os dias com tracinho).
A25: OUH1140 | B25: R6845 | C25: RT/Itabuna | D25: ILHÉUS | E25: Reporte retomado / aparente correção | F25: 2026-09-08 | G25: 2026-09-14 | H25: 6 | I25: 5 | J25: 1 | K25: Reportando (numérico) | L25: 0 | N25: Cobertura de apenas 6 dia(s) no boletim (período tem 7 dias); dias sem linha no boletim não foram tratados como interrupção. Ficou sem reporte (tracinho) de 2026-09-08 a 2026-09-08 (desde o início do período observado) e voltou a apresentar números a partir de 2026-09-09 — indício de correção conforme regra do estudo (sem confirmação de manutenção registrada).
A26: OUH3940 | B26: R6855 | C26: RT/Itabuna | D26: ILHÉUS | E26: Reporte retomado / aparente correção | F26: 2026-09-08 | G26: 2026-09-14 | H26: 7 | I26: 6 | J26: 1 | K26: Reportando (numérico) | L26: 0 | N26: Ficou sem reporte (tracinho) de 2026-09-12 a 2026-09-12 (após dias com registros numéricos) e voltou a apresentar números a partir de 2026-09-13 — indício de correção conforme regra do estudo (sem confirmação de manutenção registrada).
A27: OUH0435 | B27: R6865 | C27: RT/Itabuna | D27: ILHÉUS | E27: Reporte retomado / aparente correção | F27: 2026-09-08 | G27: 2026-09-14 | H27: 7 | I27: 6 | J27: 1 | K27: Reportando (numérico) | L27: 0 | N27: Ficou sem reporte (tracinho) de 2026-09-13 a 2026-09-13 (após dias com registros numéricos) e voltou a apresentar números a partir de 2026-09-14 — indício de correção conforme regra do estudo (sem confirmação de manutenção registrada).
A28: OUJ6028 | B28: R6885 | C28: RT/Itabuna | D28: ITABUNA | E28: Reporte contínuo | F28: 2026-09-08 | G28: 2026-09-14 | H28: 7 | I28: 7 | J28: 0 | K28: Reportando (numérico) | L28: 0 | N28: Reportou média numérica (telemetria) em todos os dias com registro no boletim.
A29: OUI1672 | B29: R6895 | C29: RT/Itabuna | D29: ITABUNA | E29: Reporte contínuo | F29: 2026-09-08 | G29: 2026-09-14 | H29: 7 | I29: 7 | J29: 0 | K29: Reportando (numérico) | L29: 0 | N29: Reportou média numérica (telemetria) em todos os dias com registro no boletim.
A30: OUK1247 | B30: R6925 | C30: RT/Itabuna | D30: ILHÉUS | E30: Reporte contínuo | F30: 2026-09-08 | G30: 2026-09-14 | H30: 7 | I30: 7 | J30: 0 | K30: Reportando (numérico) | L30: 0 | N30: Reportou média numérica (telemetria) em todos os dias com registro no boletim.
A31: OUK9535 | B31: R6935 | C31: RT/Itabuna | D31: ITABUNA | E31: Reporte contínuo | F31: 2026-09-08 | G31: 2026-09-14 | H31: 6 | I31: 6 | J31: 0 | K31: Reportando (numérico) | L31: 0 | N31: Cobertura de apenas 6 dia(s) no boletim (período tem 7 dias); dias sem linha no boletim não foram tratados como interrupção. Reportou média numérica (telemetria) em todos os dias com registro no boletim.
A32: OUK8533 | B32: R6945 | C32: RT/Itabuna | D32: ITABUNA | E32: Reporte retomado / aparente correção | F32: 2026-09-08 | G32: 2026-09-14 | H32: 7 | I32: 6 | J32: 1 | K32: Reportando (numérico) | L32: 0 | N32: Ficou sem reporte (tracinho) de 2026-09-13 a 2026-09-13 (após dias com registros numéricos) e voltou a apresentar números a partir de 2026-09-14 — indício de correção conforme regra do estudo (sem confirmação de manutenção registrada).
A33: OUO5005 | B33: R6955 | C33: RT/Itabuna | D33: CONQUISTA | E33: Reporte contínuo | F33: 2026-09-08 | G33: 2026-09-14 | H33: 5 | I33: 5 | J33: 0 | K33: Reportando (numérico) | L33: 0 | N33: Cobertura de apenas 5 dia(s) no boletim (período tem 7 dias); dias sem linha no boletim não foram tratados como interrupção. Reportou média numérica (telemetria) em todos os dias com registro no boletim.
A34: OUK7363 | B34: R6965 | C34: RT/Itabuna | D34: CONQUISTA | E34: Sem reporte em todo o período observado | F34: 2026-09-08 | G34: 2026-09-14 | H34: 6 | I34: 0 | J34: 6 | K34: Sem reporte (tracinho) | L34: 1677.9 | N34: Cobertura de apenas 6 dia(s) no boletim (período tem 7 dias); dias sem linha no boletim não foram tratados como interrupção. Nenhum registro numérico de média em todo o período observado (todos os dias com tracinho).
... A41: OUO0218 | B41: R7045 | C41: RT/Itabuna | D41: CONQUISTA | E41: Reporte contínuo | F41: 2026-09-08 | G41: 2026-09-14 | H41: 7 | I41: 7 | J41: 0 | K41: Reportando (numérico) | L41: 0 | N41: Reportou média numérica (telemetria) em todos os dias com registro no boletim.
A42: PLACA ILEGÍVEL (cadastro corrompido — prefixo R7085) | B42: R7085 | C42: RT/Itabuna | D42: ITABUNA | E42: Reporte contínuo | F42: 2026-09-08 | G42: 2026-09-14 | H42: 7 | I42: 7 | J42: 0 | K42: Reportando (numérico) | L42: 0 | M42: Placa do boletim ilegivel/corrompida; correspondencia feita pelo prefixo R7085 | N42: Reportou média numérica (telemetria) em todos os dias com registro no boletim.
A43: OUR7533 | B43: R7095 | C43: RT/Itabuna | D43: ILHÉUS | E43: Reporte retomado / aparente correção | F43: 2026-09-08 | G43: 2026-09-14 | H43: 7 | I43: 6 | J43: 1 | K43: Reportando (numérico) | L43: 0 | M43: Placa OUR3J54 nao encontrada na Base_Frota; correspondencia feita pelo prefixo ['R7095'] | N43: Ficou sem reporte (tracinho) de 2026-09-13 a 2026-09-13 (após dias com registros numéricos) e voltou a apresentar números a partir de 2026-09-14 — indício de correção conforme regra do estudo (sem confirmação de manutenção registrada).
A44: OUR3707 | B44: R7125 | C44: RT/Itabuna | D44: ITABUNA | E44: Reporte contínuo | F44: 2026-09-08 | G44: 2026-09-14 | H44: 7 | I44: 7 | J44: 0 | K44: Reportando (numérico) | L44: 0 | N44: Reportou média numérica (telemetria) em todos os dias com registro no boletim.
A45: OUR9200 | B45: R7145 | C45: RT/Itabuna | D45: ITABUNA | E45: Reporte contínuo | F45: 2026-09-08 | G45: 2026-09-14 | H45: 7 | I45: 7 | J45: 0 | K45: Reportando (numérico) | L45: 0 | N45: Reportou média numérica (telemetria) em todos os dias com registro no boletim.
A46: OUR8149 | B46: R7155 | C46: RT/Itabuna | D46: ITABUNA | E46: Reporte contínuo | F46: 2026-09-08 | G46: 2026-09-14 | H46: 7 | I46: 7 | J46: 0 | K46: Reportando (numérico) | L46: 0 | N46: Reportou média numérica (telemetria) em todos os dias com registro no boletim.
A47: OZM4852 | B47: R7175 | C47: RT/Itabuna | D47: ILHÉUS | E47: Reporte contínuo | F47: 2026-09-08 | G47: 2026-09-14 | H47: 7 | I47: 7 | J47: 0 | K47: Reportando (numérico) | L47: 0 | N47: Reportou média numérica (telemetria) em todos os dias com registro no boletim.
A48: OZM0738 | B48: R7195 | C48: RT/Itabuna | D48: CONQUISTA | E48: Reporte contínuo | F48: 2026-09-14 | G48: 2026-09-14 | H48: 1 | I48: 1 | J48: 0 | K48: Reportando (numérico) | L48: 0 | N48: Cobertura de apenas 1 dia(s) no boletim (período tem 7 dias); dias sem linha no boletim não foram tratados como interrupção. Reportou média numérica (telemetria) em todos os dias com registro no boletim.
A49: OZM9744 | B49: R7245 | C49: RT/Itabuna | D49: ITABUNA | E49: Reporte contínuo | F49: 2026-09-08 | G49: 2026-09-14 | H49: 7 | I49: 7 | J49: 0 | K49: Reportando (numérico) | L49: 0 | N49: Reportou média numérica (telemetria) em todos os dias com registro no boletim.
A50: OZV6244 | B50: R7415 | C50: RT/Itabuna | D50: ITABUNA | E50: Reporte contínuo | F50: 2026-09-08 | G50: 2026-09-14 | H50: 6 | I50: 6 | J50: 0 | K50: Reportando (numérico) | L50: 0 | N50: Cobertura de apenas 6 dia(s) no boletim (período tem 7 dias); dias sem linha no boletim não foram tratados como interrupção. Reportou média numérica (telemetria) em todos os dias com registro no boletim.
A51: OZV9425 | B51: R7435 | C51: RT/Itabuna | D51: ITABUNA | E51: Reporte contínuo | F51: 2026-09-08 | G51: 2026-09-14 | H51: 6 | I51: 6 | J51: 0 | K51: Reportando (numérico) | L51: 0 | N51: Cobertura de apenas 6 dia(s) no boletim (período tem 7 dias); dias sem linha no boletim não foram tratados como interrupção. Reportou média numérica (telemetria) em todos os dias com registro no boletim.
A52: OZV2987 | B52: R7445 | C52: RT/Itabuna | D52: ITABUNA | E52: Reporte contínuo | F52: 2026-09-08 | G52: 2026-09-14 | H52: 6 | I52: 6 | J52: 0 | K52: Reportando (numérico) | L52: 0 | N52: Cobertura de apenas 6 dia(s) no boletim (período tem 7 dias); dias sem linha no boletim não foram tratados como interrupção. Reportou média numérica (telemetria) em todos os dias com registro no boletim.
A53: OZV7879 | B53: R7455 | C53: RT/Itabuna | D53: ITABUNA | E53: Sem reporte em todo o período observado | F53: 2026-09-08 | G53: 2026-09-14 | H53: 6 | I53: 0 | J53: 6 | K53: Sem reporte (tracinho) | L53: 810.6 | N53: Cobertura de apenas 6 dia(s) no boletim (período tem 7 dias); dias sem linha no boletim não foram tratados como interrupção. Nenhum registro numérico de média em todo o período observado (todos os dias com tracinho).
A54: OZV5174 | B54: R7465 | C54: RT/Itabuna | D54: ITABUNA | E54: Reporte contínuo | F54: 2026-09-08 | G54: 2026-09-14 | H54: 7 | I54: 7 | J54: 0 | K54: Reportando (numérico) | L54: 0 | N54: Reportou média numérica (telemetria) em todos os dias com registro no boletim.
A55: OZT5781 | B55: R7475 | C55: RT/Itabuna | D55: ILHÉUS | E55: Reporte contínuo | F55: 2026-09-08 | G55: 2026-09-14 | H55: 7 | I55: 7 | J55: 0 | K55: Reportando (numérico) | L55: 0 | N55: Reportou média numérica (telemetria) em todos os dias com registro no boletim.
... A59: OZT2347 | B59: R7525 | C59: RT/Itabuna | D59: ILHÉUS | E59: Reporte contínuo | F59: 2026-09-08 | G59: 2026-09-14 | H59: 7 | I59: 7 | J59: 0 | K59: Reportando (numérico) | L59: 0 | N59: Reportou média numérica (telemetria) em todos os dias com registro no boletim.
A60: OZT6736 | B60: R7535 | C60: RT/Itabuna | D60: ITABUNA | E60: Reporte contínuo | F60: 2026-09-08 | G60: 2026-09-14 | H60: 5 | I60: 5 | J60: 0 | K60: Reportando (numérico) | L60: 0 | M60: Placa OZT6763 nao encontrada na Base_Frota; correspondencia feita pelo prefixo ['R7535'] | N60: Cobertura de apenas 5 dia(s) no boletim (período tem 7 dias); dias sem linha no boletim não foram tratados como interrupção. Reportou média numérica (telemetria) em todos os dias com registro no boletim.
A61: OZT9896 | B61: R7545 | C61: RT/Itabuna | D61: ITABUNA | E61: Deixou de reportar | F61: 2026-09-08 | G61: 2026-09-14 | H61: 6 | I61: 4 | J61: 2 | K61: Sem reporte (tracinho) | L61: 0 | N61: Cobertura de apenas 6 dia(s) no boletim (período tem 7 dias); dias sem linha no boletim não foram tratados como interrupção. Reportou normalmente até 2026-09-11 e ficou sem reporte (tracinho) do dia 2026-09-12 até o fim do período observado (2026-09-14).
A62: OZT8368 | B62: R7555 | C62: RT/Itabuna | D62: ITABUNA | E62: Deixou de reportar | F62: 2026-09-09 | G62: 2026-09-13 | H62: 3 | I62: 2 | J62: 1 | K62: Sem reporte (tracinho) | L62: 0 | N62: Cobertura de apenas 3 dia(s) no boletim (período tem 7 dias); dias sem linha no boletim não foram tratados como interrupção. Reportou normalmente até 2026-09-11 e ficou sem reporte (tracinho) do dia 2026-09-13 até o fim do período observado (2026-09-13).
A63: OZT0656 | B63: R7565 | C63: RT/Itabuna | D63: ITABUNA | E63: Sem reporte em todo o período observado | F63: 2026-09-08 | G63: 2026-09-14 | H63: 7 | I63: 0 | J63: 7 | K63: Sem reporte (tracinho) | L63: 2893.8 | N63: Nenhum registro numérico de média em todo o período observado (todos os dias com tracinho).
A64: PJR3626 | B64: R7585 | C64: RT/Itabuna | D64: ITABUNA | E64: Reporte contínuo | F64: 2026-09-08 | G64: 2026-09-14 | H64: 7 | I64: 7 | J64: 0 | K64: Reportando (numérico) | L64: 0 | N64: Reportou média numérica (telemetria) em todos os dias com registro no boletim.
A65: PKN3551 | B65: R7725 | C65: RT/Itabuna | D65: ITABUNA | E65: Reporte contínuo | F65: 2026-09-08 | G65: 2026-09-14 | H65: 7 | I65: 7 | J65: 0 | K65: Reportando (numérico) | L65: 0 | M65: Placa PKN3F51 nao encontrada na Base_Frota; correspondencia feita pelo prefixo ['R7725'] | N65: Reportou média numérica (telemetria) em todos os dias com registro no boletim.
A66: PKN8524 | B66: R7745 | C66: RT/Itabuna | D66: ITABUNA | E66: Sem reporte em todo o período observado | F66: 2026-09-08 | G66: 2026-09-14 | H66: 5 | I66: 0 | J66: 5 | K66: Sem reporte (tracinho) | L66: 1233.8 | N66: Cobertura de apenas 5 dia(s) no boletim (período tem 7 dias); dias sem linha no boletim não foram tratados como interrupção. Nenhum registro numérico de média em todo o período observado (todos os dias com tracinho).
A67: PLE8D78 | B67: R8025 | C67: RT/Itabuna | D67: CONQUISTA | E67: Reporte retomado / aparente correção | F67: 2026-09-08 | G67: 2026-09-14 | H67: 6 | I67: 5 | J67: 1 | K67: Reportando (numérico) | L67: 0 | N67: Cobertura de apenas 6 dia(s) no boletim (período tem 7 dias); dias sem linha no boletim não foram tratados como interrupção. Ficou sem reporte (tracinho) de 2026-09-11 a 2026-09-11 (após dias com registros numéricos) e voltou a apresentar números a partir de 2026-09-12 — indício de correção conforme regra do estudo (sem confirmação de manutenção registrada).
A68: PLG3095 | B68: R8035 | C68: RT/Itabuna | D68: CONQUISTA | E68: Reporte contínuo | F68: 2026-09-08 | G68: 2026-09-14 | H68: 6 | I68: 6 | J68: 0 | K68: Reportando (numérico) | L68: 0 | N68: Cobertura de apenas 6 dia(s) no boletim (período tem 7 dias); dias sem linha no boletim não foram tratados como interrupção. Reportou média numérica (telemetria) em todos os dias com registro no boletim.
A69: PLE2634 | B69: R8045 | C69: RT/Itabuna | D69: CONQUISTA | E69: Sem reporte em todo o período observado | F69: 2026-09-14 | G69: 2026-09-14 | H69: 1 | I69: 0 | J69: 1 | K69: Sem reporte (tracinho) | L69: 0 | M69: Placa PLE2G34 nao encontrada na Base_Frota; correspondencia feita pelo prefixo ['R8045'] | N69: Cobertura de apenas 1 dia(s) no boletim (período tem 7 dias); dias sem linha no boletim não foram tratados como interrupção. Nenhum registro numérico de média em todo o período observado (todos os dias com tracinho).
A70: RPL2B23 | B70: R8425 | C70: RT/Itabuna | D70: ITABUNA | E70: Intermitente | F70: 2026-09-09 | G70: 2026-09-14 | H70: 6 | I70: 2 | J70: 4 | K70: Reportando (numérico) | L70: 0.5 | N70: Cobertura de apenas 6 dia(s) no boletim (período tem 7 dias); dias sem linha no boletim não foram tratados como interrupção. 2 episódios de interrupção do reporte ao longo do período; situação no último registro: Reportando (numérico).
A71: RPK0J26 | B71: R8515 | C71: RT/Itabuna | D71: ITABUNA | E71: Reporte contínuo | F71: 2026-09-08 | G71: 2026-09-14 | H71: 7 | I71: 7 | J71: 0 | K71: Reportando (numérico) | L71: 0 | N71: Reportou média numérica (telemetria) em todos os dias com registro no boletim.
A72: RPK0B75 | B72: R8525 | C72: RT/Itabuna | D72: ITABUNA | E72: Reporte contínuo | F72: 2026-09-08 | G72: 2026-09-14 | H72: 7 | I72: 7 | J72: 0 | K72: Reportando (numérico) | L72: 0 | N72: Reportou média numérica (telemetria) em todos os dias com registro no boletim.
A73: RPV1G14 | B73: R8705 | C73: RT/Itabuna | D73: CONQUISTA | E73: Reporte contínuo | F73: 2026-09-08 | G73: 2026-09-14 | H73: 6 | I73: 6 | J73: 0 | K73: Reportando (numérico) | L73: 0 | N73: Cobertura de apenas 6 dia(s) no boletim (período tem 7 dias); dias sem linha no boletim não foram tratados como interrupção. Reportou média numérica (telemetria) em todos os dias com registro no boletim.
A74: SJN0C19 | B74: R8715 | C74: RT/Itabuna | D74: CONQUISTA | E74: Reporte contínuo | F74: 2026-09-08 | G74: 2026-09-14 | H74: 7 | I74: 7 | J74: 0 | K74: Reportando (numérico) | L74: 0 | N74: Reportou média numérica (telemetria) em todos os dias com registro no boletim.
A75: SJN2E11 | B75: R8725 | C75: RT/Itabuna | D75: ILHÉUS | E75: Reporte contínuo | F75: 2026-09-08 | G75: 2026-09-14 | H75: 7 | I75: 7 | J75: 0 | K75: Reportando (numérico) | L75: 0 | N75: Reportou média numérica (telemetria) em todos os dias com registro no boletim.
A76: SJN4F98 | B76: R8755 | C76: RT/Itabuna | D76: ITABUNA | E76: Reporte contínuo | F76: 2026-09-08 | G76: 2026-09-14 | H76: 7 | I76: 7 | J76: 0 | K76: Reportando (numérico) | L76: 0 | N76: Reportou média numérica (telemetria) em todos os dias com registro no boletim.
A77: SJS2J74 | B77: R8905 | C77: RT/Itabuna | D77: CONQUISTA | E77: Sem reporte em todo o período observado | F77: 2026-09-08 | G77: 2026-09-14 | H77: 6 | I77: 0 | J77: 6 | K77: Sem reporte (tracinho) | L77: 1177.6 | N77: Cobertura de apenas 6 dia(s) no boletim (período tem 7 dias); dias sem linha no boletim não foram tratados como interrupção. Nenhum registro numérico de média em todo o período observado (todos os dias com tracinho).
A78: SJS2E47 | B78: R8925 | C78: RT/Itabuna | D78: CONQUISTA | E78: Reporte contínuo | F78: 2026-09-09 | G78: 2026-09-11 | H78: 2 | I78: 2 | J78: 0 | K78: Reportando (numérico) | L78: 0 | N78: Cobertura de apenas 2 dia(s) no boletim (período tem 7 dias); dias sem linha no boletim não foram tratados como interrupção. Reportou média numérica (telemetria) em todos os dias com registro no boletim.
A79: SJS6G95 | B79: R8945 | C79: RT/Itabuna | D79: CONQUISTA | E79: Reporte contínuo | F79: 2026-09-08 | G79: 2026-09-14 | H79: 5 | I79: 5 | J79: 0 | K79: Reportando (numérico) | L79: 0 | N79: Cobertura de apenas 5 dia(s) no boletim (período tem 7 dias); dias sem linha no boletim não foram tratados como interrupção. Reportou média numérica (telemetria) em todos os dias com registro no boletim.
A80: TGV9E72 | B80: R9395 | C80: RT/Itabuna | D80: CONQUISTA | E80: Reporte contínuo | F80: 2026-09-08 | G80: 2026-09-14 | H80: 7 | I80: 7 | J80: 0 | K80: Reportando (numérico) | L80: 0 | N80: Reportou média numérica (telemetria) em todos os dias com registro no boletim.

Sheet Ocorrências
A1: Data | B1: Prefixo | C1: Placa | D1: Média (registro original) | E1: Distância (km) | F1: Tipo de ocorrência
A2: 2026-09-14 | B2: R10175 | C2: OZG5113 | D2: - | E2: 0.04 | F2: Início de interrupção do reporte
A3: 2026-09-12 | B3: R10185 | C3: OZG6088 | D3: - | E3: 0 | F3: Início de interrupção do reporte
A4: 2026-09-13 | B4: R10375 | C4: PJT3877 | D4: - | E4: 0 | F4: Início de interrupção do reporte
A5: 2026-09-14 | B5: R10375 | C5: PJT3877 | D5: 2.24 Km/L | E5: 259.31 | F5: Retomada do reporte (números voltam a aparecer)
A6: 2026-09-09 | B6: R10535 | C6: PLZ9C39 | D6: 95.30 Km/L | E6: 250.63 | F6: Retomada do reporte (números voltam a aparecer)
A7: 2026-09-11 | B7: R6755 | C7: NZO2423 | D7: - | E7: 218.52 | F7: Início de interrupção do reporte
A8: 2026-09-13 | B8: R6755 | C8: NZO2423 | D8: 0.00 Km/L | E8: 0 | F8: Retomada do reporte (números voltam a aparecer)
A9: 2026-09-09 | B9: R6845 | C9: OUH1140 | D9: 3.44 Km/L | E9: 91.7 | F9: Retomada do reporte (números voltam a aparecer)
A10: 2026-09-12 | B10: R6855 | C10: OUH3940 | D10: - | E10: 0 | F10: Início de interrupção do reporte
A11: 2026-09-13 | B11: R6855 | C11: OUH3940 | D11: 2.59 Km/L | E11: 79.15 | F11: Retomada do reporte (números voltam a aparecer)
A12: 2026-09-13 | B12: R6865 | C12: OUH0435 | D12: - | E12: 0 | F12: Início de interrupção do reporte
A13: 2026-09-14 | B13: R6865 | C13: OUH0435 | D13: 3.07 Km/L | E13: 157.01 | F13: Retomada do reporte (números voltam a aparecer)
... A29: 2026-09-14 | B29: R8425 | C29: RPL2B23 | D29: 2.73 Km/L | E29: 152.62 | F29: Retomada do reporte (números voltam a aparecer)

Sheet Excluídos
A1: Veículos presentes no Boletim que NÃO constam na Base_Frota — mantidos fora da análise principal de continuidade de reporte, registros originais preservados na aba do boletim.
A2: Placa | B2: Prefixo | C2: UO/Localidade | D2: Período dos registros | E2: Qtd. de registros no boletim | F2: Motivo da exclusão
A3: TGV4B86 | B3: POLO - ITN | C3: ROTA TRANSPORTES - ITABUNA | D3: 2026-09-08 a 2026-09-14 | E3: 7 | F3: Placa TGV4B86 (prefixo ['POLO - ITN']) nao consta na Base_Frota
A4: SKP4F49 | B4: Polo - ITN 01 | C4: ROTA TRANSPORTES - ITABUNA | D4: 2026-09-08 a 2026-09-12 | E4: 5 | F4: Placa SKP4F49 (prefixo ['POLO - ITN 01']) nao consta na Base_Frota
A5: NYJ8D37 | B5: R10015 | C5: ROTA TRANSPORTES - ITABUNA | D5: 2026-09-08 a 2026-09-14 | E5: 7 | F5: Placa NYJ8D37 (prefixo ['R10015']) nao consta na Base_Frota
A6: NZS2H15 | B6: R10045 | C6: ROTA TRANSPORTES - ITABUNA | D6: 2026-09-08 a 2026-09-14 | E6: 7 | F6: Placa NZS2H15 (prefixo ['R10045']) nao consta na Base_Frota
A7: NZS2017 | B7: R10055 | C7: ROTA TRANSPORTES - ITABUNA | D7: 2026-09-08 a 2026-09-14 | E7: 7 | F7: Placa NZS2017 (prefixo ['R10055']) nao consta na Base_Frota
A8: OLG4715 | B8: R10115 | C8: ROTA TRANSPORTES - ITABUNA | D8: 2026-09-08 a 2026-09-14 | E8: 7 | F8: Placa OLG4715 (prefixo ['R10115']) nao consta na Base_Frota
A9: OLG5094 | B9: R10135 | C9: ROTA TRANSPORTES - ITABUNA | D9: 2026-09-08 a 2026-09-14 | E9: 7 | F9: Placa OLG5094 (prefixo ['R10135']) nao consta na Base_Frota
A10: OLG5B65 | B10: R10145 | C10: ROTA TRANSPORTES - ITABUNA | D10: 2026-09-08 a 2026-09-14 | E10: 6 | F10: Placa OLG5B65 (prefixo ['R10145']) nao consta na Base_Frota
A11: OLG3I24 | B11: R10155 | C11: ROTA TRANSPORTES - ITABUNA | D11: 2026-09-08 a 2026-09-14 | E11: 7 | F11: Placa OLG3I24 (prefixo ['R10155']) nao consta na Base_Frota
A12: OZG1534 | B12: R10205 | C12: ROTA TRANSPORTES - ITABUNA | D12: 2026-09-11 a 2026-09-11 | E12: 1 | F12: Placa OZG1534 (prefixo ['R10205']) nao consta na Base_Frota
A13: OZF0604 | B13: R10225 | C13: ROTA TRANSPORTES - ITABUNA | D13: 2026-09-08 a 2026-09-14 | E13: 6 | F13: Placa OZF0604 (prefixo ['R10225']) nao consta na Base_Frota
A14: OZG1786 | B14: R10255 | C14: ROTA TRANSPORTES - ITABUNA | D14: 2026-09-08 a 2026-09-14 | E14: 4 | F14: Placa OZG1786 (prefixo ['R10255']) nao consta na Base_Frota
... A194: TMP1F94 | B194: R9765 | C194: ROTA TRANSPORTES - ITABUNA | D194: 2026-09-08 a 2026-09-14 | E194: 6 | F194: Placa TMP1F94 (prefixo ['R9765']) nao consta na Base_Frota

Sheet Sem_Registro_Boletim
A1: Veículos da Base_Frota que NÃO possuem nenhum registro no boletim do período (08/09 a 14/09/2026).
A2: Placa | B2: Prefixo | C2: UO | D2: Setor
A3: PJT1670 | B3: R10345 | C3: RT/Itabuna | D3: ILHÉUS
A4: PKC5996 | B4: R10385 | C4: RT/Itabuna | D4: ILHÉUS
A5: NZO1912 | B5: R6765 | C5: RT/Itabuna | D5: ITABUNA
A6: NZO4523 | B6: R6775 | C6: RT/Itabuna | D6: ITABUNA
A7: OUH912 | B7: R6875 | C7: RT/Itabuna | D7: ILHÉUS
A8: OUK7418 | B8: R6915 | C8: RT/Itabuna | D8: ITABUNA
A9: OUR3954 | B9: R7075 | C9: RT/Itabuna | D9: ITABUNA
A10: OUR3686 | B10: R7105 | C10: RT/Itabuna | D10: ILHÉUS
A11: RPV3E20 | B11: R8695 | C11: RT/Itabuna | D11: CONQUISTA
A12: PKN2985 | B12: R7695 | C12: RT/Itabuna | D12: ILHÉUS

Sheet Resumo
B2: RESUMO — DISPONIBILIDADE E CONTINUIDADE DO REPORTE DE MÉDIA DE COMBUSTÍVEL
B3: Boletim ROTA Transportes - Itabuna | Período: 08/09/2026 a 14/09/2026
B5: Total de veículos na Base_Frota | E5: 89
B6: Total de veículos válidos presentes no boletim | E6: 79
B7: Total de veículos válidos sem nenhum registro no boletim | E7: 10
B8: Total de veículos excluídos (boletim, fora da Base_Frota) | E8: 192
B9: Período esperado | E9: 2026-09-08 a 2026-09-14
B10: Confirmação do período | E10: 2026-09-08 a 2026-09-14 (todas as 1628 linhas do boletim estão dentro do período esperado; nenhuma divergência de data encontrada)
B11: Registros com placa ilegível/corrompida no boletim | E11: 7
B12: Registros com inconsistência de hodômetro (>5 km de divergência) | E12: 2
B13: Dias com registros simultâneos numérico e tracinho (mesmo veículo/dia) | E13: 3
B15: Classificação (base: veículos válidos presentes no boletim)
B16: Classificação | C16: Quantidade | D16: % do total
B17: Reporte contínuo | C17: 52 | D17: 0.658
B18: Reporte retomado / aparente correção | C18: 12 | D18: 0.152
B19: Intermitente | C19: 1 | D19: 0.013
B20: Deixou de reportar | C20: 4 | D20: 0.051
B21: Sem reporte em todo o período observado | C21: 10 | D21: 0.127
B22: Dados insuficientes ou inconsistentes | C22: 0 | D22: 0
B24: Excluídos por localidade (UO informada no boletim)
B25: Localidade | C25: Quantidade
B26: ROTA TRANSPORTES - ITABUNA | C26: 192
B28: Lista prioritária de investigação — veículos que rodaram sem reportar média (ordenado por classificação de risco e distância percorrida sem reporte)
B29: Prefixo | C29: Placa | D29: Classificação | E29: Situação no último registro | F29: Km nos dias com tracinho | G29: Último dia com registro
B30: R10175 | C30: OZG5113 | D30: Deixou de reportar | E30: Sem reporte (tracinho) | F30: 0 | G30: 2026-09-14
B31: R10185 | C31: OZG6088 | D31: Deixou de reportar | E31: Sem reporte (tracinho) | F31: 0 | G31: 2026-09-14
B32: R7545 | C32: OZT9896 | D32: Deixou de reportar | E32: Sem reporte (tracinho) | F32: 0 | G32: 2026-09-14
B33: R7555 | C33: OZT8368 | D33: Deixou de reportar | E33: Sem reporte (tracinho) | F33: 0 | G33: 2026-09-13
B34: R7565 | C34: OZT0656 | D34: Sem reporte em todo o período observado | E34: Sem reporte (tracinho) | F34: 2893.8 | G34: 2026-09-14
B35: R6815 | C35: NZO9187 | D35: Sem reporte em todo o período observado | E35: Sem reporte (tracinho) | F35: 2397.5 | G35: 2026-09-14
B36: R6965 | C36: OUK7363 | D36: Sem reporte em todo o período observado | E36: Sem reporte (tracinho) | F36: 1677.9 | G36: 2026-09-14
B37: R7745 | C37: PKN8524 | D37: Sem reporte em todo o período observado | E37: Sem reporte (tracinho) | F37: 1233.8 | G37: 2026-09-14
B38: R8905 | C38: SJS2J74 | D38: Sem reporte em todo o período observado | E38: Sem reporte (tracinho) | F38: 1177.6 | G38: 2026-09-14
B39: R5365 | C39: SJP4A43 | D39: Sem reporte em todo o período observado | E39: Sem reporte (tracinho) | F39: 1046.8 | G39: 2026-09-14
B40: R7455 | C40: OZV7879 | D40: Sem reporte em todo o período observado | E40: Sem reporte (tracinho) | F40: 810.6 | G40: 2026-09-14
B41: R5495 | C41: JQI1371 | D41: Sem reporte em todo o período observado | E41: Sem reporte (tracinho) | F41: 355.1 | G41: 2026-09-14
... B44: R8425 | C44: RPL2B23 | D44: Intermitente | E44: Reportando (numérico) | F44: 0.5 | G44: 2026-09-14
B47: Regras e limitações desta análise
B48: • "-" (tracinho) na Média de Consumo = telemetria não importou a média naquele registro (sem comunicação/sem dado).
B49: • Qualquer valor numérico, inclusive 0,00, conta como reporte (comunicação ocorreu).
B50: • Datas sem linha no boletim NÃO foram tratadas como interrupção — apenas a sequência de dias efetivamente registrados foi avaliada.
B51: • Retomada de números após tracinho é tratada como indício de correção, sem confirmação de manutenção (não há registro de OS nesta base).
B52: • Não foi atribuída causa mecânica nem responsabilidade ao motorista em nenhuma classificação.
B53: • km/L é sempre calculado por (km totais ÷ litros totais) no grupo/veículo — nunca pela média simples das médias diárias.
B54: • Frota válida = exclusivamente veículos cadastrados na aba Base_Frota, cruzados pela Placa (normalizada) e, em caso de divergência, pelo Prefixo.
